Workbook

Sheet Welcome
B1: WT spreadsheet by gszabi99 | G1: v2.0
A4: Guided weaponry data spreadsheet: link
A5: Unused assets of War Thunder: link
A6: Feedback: link
A7: Discord: link

Sheet Updates
A1: Updates
A2: Version | B2: Name | C2: Release | E2: Announcement (UTC) | F2: Internal date in game files | G2: First devblog | I2: Last update release to first devblog | J2: First devblog to release | K2: Last dev server to release | L2: Time between updates | M2: Date diff | V2: Avg announcement time | X2: Avg release | Y2: Avg first devblog
A3: 1.27 | B3: - | C3: 41304 | D3: =CHOOSE(WEEKDAY(C3,2),"Monday","Tuesday","Wednesday","Thursday","Friday","Saturday","Sunday") -> Wednesday | E3: - | F3: - | G3: - | H3: - | I3: - | J3: - | K3: - | L3: - | X3: =C3 -> 41304
A4: 1.29 | B4: - | C4: 41352 | D4: =CHOOSE(WEEKDAY(C4,2),"Monday","Tuesday","Wednesday","Thursday","Friday","Saturday","Sunday") -> Tuesday | E4: - | F4: - | G4: - | H4: - | I4: - | J4: - | K4: - | L4: =C4-C3 -> 48 | X4: =C4 -> 41352
A5: 1.31 | B5: - | C5: 41436 | D5: =CHOOSE(WEEKDAY(C5,2),"Monday","Tuesday","Wednesday","Thursday","Friday","Saturday","Sunday") -> Tuesday | E5: 41435.785 | F5: - | G5: - | H5: - | I5: - | J5: - | K5: - | L5: =C5-C4 -> 84 | V5: =INT(E5) -> 41435 | W5: =E5-V5 -> 0.78472222 | X5: =C5 -> 41436
A6: 1.33 | B6: - | C6: 41493 | D6: =CHOOSE(WEEKDAY(C6,2),"Monday","Tuesday","Wednesday","Thursday","Friday","Saturday","Sunday") -> Wednesday | E6: - | F6: - | G6: - | H6: - | I6: - | J6: - | K6: - | L6: =C6-C5 -> 57 | X6: =C6 -> 41493
A7: 1.35 | B7: - | C7: 41543 | D7: =CHOOSE(WEEKDAY(C7,2),"Monday","Tuesday","Wednesday","Thursday","Friday","Saturday","Sunday") -> Thursday | E7: - | F7: - | G7: - | H7: - | I7: - | J7: - | K7: - | L7: =C7-C6 -> 50 | X7: =C7 -> 41543
A8: 1.37 | B8: - | C8: 41626 | D8: =CHOOSE(WEEKDAY(C8,2),"Monday","Tuesday","Wednesday","Thursday","Friday","Saturday","Sunday") -> Wednesday | E8: - | F8: - | G8: =Devblogs!FO2 -> 41561 | H8: =Devblogs!FP2 -> Monday | I8: =_xludf.DAYS(G8,C7) -> #NAME? | J8: =_xludf.DAYS(C8,G8) -> #NAME? | K8: - | L8: =C8-C7 -> 83 | X8: =C8 -> 41626 | Y8: =G8 -> 41561
A9: 1.39 | B9: - | C9: 41744 | D9: =CHOOSE(WEEKDAY(C9,2),"Monday","Tuesday","Wednesday","Thursday","Friday","Saturday","Sunday") -> Tuesday | E9: - | F9: - | G9: =Devblogs!FL2 -> 41649 | H9: =Devblogs!FM2 -> Friday | I9: =_xludf.DAYS(G9,C8) -> #NAME? | J9: =_xludf.DAYS(C9,G9) -> #NAME? | K9: - | L9: =C9-C8 -> 118 | X9: =C9-365 -> 41379 | Y9: =G9-365 -> 41284
A10: 1.41 | B10: - | C10: 41774 | D10: =CHOOSE(WEEKDAY(C10,2),"Monday","Tuesday","Wednesday","Thursday","Friday","Saturday","Sunday") -> Thursday | E10: 41773.852 | F10: - | G10: =Devblogs!FI2 -> 41747 | H10: =Devblogs!FJ2 -> Friday | I10: =_xludf.DAYS(G10,C9) -> #NAME? | J10: =_xludf.DAYS(C10,G10) -> #NAME? | K10: - | L10: =C10-C9 -> 30 | V10: =INT(E10) -> 41773 | W10: =E10-V10 -> 0.85208333 | X10: =C10-365 -> 41409 | Y10: =G10-365 -> 41382
A11: 1.43 | B11: - | C11: 41921 | D11: =CHOOSE(WEEKDAY(C11,2),"Monday","Tuesday","Wednesday","Thursday","Friday","Saturday","Sunday") -> Thursday | E11: 41920.778 | F11: - | G11: =Devblogs!FF2 -> 41795 | H11: =Devblogs!FG2 -> Thursday | I11: =_xludf.DAYS(G11,C10) -> #NAME? | J11: =_xludf.DAYS(C11,G11) -> #NAME? | K11: - | L11: =C11-C10 -> 147 | V11: =INT(E11) -> 41920 | W11: =E11-V11 -> 0.77847222 | X11: =C11-365 -> 41556 | Y11: =G11-365 -> 41430
A12: 1.45 | B12: Steel Generals | C12: 41989 | D12: =CHOOSE(WEEKDAY(C12,2),"Monday","Tuesday","Wednesday","Thursday","Friday","Saturday","Sunday") -> Tuesday | E12: 41988.872 | F12: - | G12: =Devblogs!FC2 -> 41941 | H12: =Devblogs!FD2 -> Wednesday | I12: =_xludf.DAYS(G12,C11) -> #NAME? | J12: =_xludf.DAYS(C12,G12) -> #NAME? | K12: - | L12: =C12-C11 -> 68 | V12: =INT(E12) -> 41988 | W12: =E12-V12 -> 0.87222222 | X12: =C12-365 -> 41624 | Y12: =G12-365 -> 41576
A13: 1.47 | B13: Big Guns | C13: 42059 | D13: =CHOOSE(WEEKDAY(C13,2),"Monday","Tuesday","Wednesday","Thursday","Friday","Saturday","Sunday") -> Tuesday | E13: 42058.954 | F13: - | G13: =Devblogs!EZ2 -> 42037 | H13: =Devblogs!FA2 -> Monday | I13: =_xludf.DAYS(G13,C12) -> #NAME? | J13: =_xludf.DAYS(C13,G13) -> #NAME? | K13: - | L13: =C13-C12 -> 70 | V13: =INT(E13) -> 42058 | W13: =E13-V13 -> 0.95416667 | X13: =C13-365*2 -> 41329 | Y13: =G13-365*2 -> 41307
A14: 1.49 | B14: Weapons of Victory | C14: 42124 | D14: =CHOOSE(WEEKDAY(C14,2),"Monday","Tuesday","Wednesday","Thursday","Friday","Saturday","Sunday") -> Thursday | E14: 42123.813 | F14: - | G14: =Devblogs!EW2 -> 42111 | H14: =Devblogs!EX2 -> Friday | I14: =_xludf.DAYS(G14,C13) -> #NAME? | J14: =_xludf.DAYS(C14,G14) -> #NAME? | K14: - | L14: =C14-C13 -> 65 | V14: =INT(E14) -> 42123 | W14: =E14-V14 -> 0.81319444 | X14: =C14-365*2 -> 41394 | Y14: =G14-365*2 -> 41381
A15: 1.51 | B15: Cold Steel | C15: 42185 | D15: =CHOOSE(WEEKDAY(C15,2),"Monday","Tuesday","Wednesday","Thursday","Friday","Saturday","Sunday") -> Tuesday | E15: 42184.913 | F15: - | G15: =Devblogs!ET2 -> 42171 | H15: =Devblogs!EU2 -> Tuesday | I15: =_xludf.DAYS(G15,C14) -> #NAME? | J15: =_xludf.DAYS(C15,G15) -> #NAME? | K15: - | L15: =C15-C14 -> 61 | V15: =INT(E15) -> 42184 | W15: =E15-V15 -> 0.91319444 | X15: =C15-365*2 -> 41455 | Y15: =G15-365*2 -> 41441
A16: 1.53 | B16: Firestorm | C16: 42313 | D16: =CHOOSE(WEEKDAY(C16,2),"Monday","Tuesday","Wednesday","Thursday","Friday","Saturday","Sunday") -> Thursday | E16: 42312.797 | F16: - | G16: =Devblogs!EQ2 -> 42221 | H16: =Devblogs!ER2 -> Wednesday | I16: =_xludf.DAYS(G16,C15) -> #NAME? | J16: =_xludf.DAYS(C16,G16) -> #NAME? | K16: - | L16: =C16-C15 -> 128 | V16: =INT(E16) -> 42312 | W16: =E16-V16 -> 0.79652778 | X16: =C16-365*2 -> 41583 | Y16: =G16-365*2 -> 41491
A17: 1.55 | B17: Royal Armour | C17: 42353 | D17: =CHOOSE(WEEKDAY(C17,2),"Monday","Tuesday","Wednesday","Thursday","Friday","Saturday","Sunday") -> Tuesday | E17: 42352.993 | F17: - | G17: =Devblogs!EN2 -> 42341 | H17: =Devblogs!EO2 -> Thursday | I17: =_xludf.DAYS(G17,C16) -> #NAME? | J17: =_xludf.DAYS(C17,G17) -> #NAME? | K17: - | L17: =C17-C16 -> 40 | V17: =INT(E17) -> 42352 | W17: =E17-V17 -> 0.99305556 | X17: =C17-365*2 -> 41623 | Y17: =G17-365*2 -> 41611
A18: 1.57 | B18: Battle March | C18: 42444 | D18: =CHOOSE(WEEKDAY(C18,2),"Monday","Tuesday","Wednesday","Thursday","Friday","Saturday","Sunday") -> Tuesday | E18: 42443.917 | F18: - | G18: =Devblogs!EK2 -> 42395 | H18: =Devblogs!EL2 -> Tuesday | I18: =_xludf.DAYS(G18,C17) -> #NAME? | J18: =_xludf.DAYS(C18,G18) -> #NAME? | K18: =C18-'Dev servers'!C3 -> 7 | L18: =C18-C17 -> 91 | V18: =INT(E18) -> 42443 | W18: =E18-V18 -> 0.91666667 | X18: =C18-365*2-366 -> 41348 | Y18: =G18-365*3 -> 41300
A19: 1.59 | B19: Flaming Arrows | C19: 42530 | D19: =CHOOSE(WEEKDAY(C19,2),"Monday","Tuesday","Wednesday","Thursday","Friday","Saturday","Sunday") -> Thursday | E19: 42529.797 | F19: - | G19: =Devblogs!EH2 -> 42452 | H19: =Devblogs!EI2 -> Wednesday | I19: =_xludf.DAYS(G19,C18) -> #NAME? | J19: =_xludf.DAYS(C19,G19) -> #NAME? | K19: =C19-'Dev servers'!C5 -> 10 | L19: =C19-C18 -> 86 | V19: =INT(E19) -> 42529 | W19: =E19-V19 -> 0.79652778 | X19: =C19-365*2-366 -> 41434 | Y19: =G19-365*2-366 -> 41356
A20: 1.61 | B20: Road to Glory | C20: 42585 | D20: =CHOOSE(WEEKDAY(C20,2),"Monday","Tuesday","Wednesday","Thursday","Friday","Saturday","Sunday") -> Wednesday | E20: 42584.858 | F20: - | G20: =Devblogs!EE2 -> 42557 | H20: =Devblogs!EF2 -> Wednesday | I20: =_xludf.DAYS(G20,C19) -> #NAME? | J20: =_xludf.DAYS(C20,G20) -> #NAME? | K20: =C20-'Dev servers'!C6 -> 4 | L20: =C20-C19 -> 55 | V20: =INT(E20) -> 42584 | W20: =E20-V20 -> 0.85763889 | X20: =C20-365*2-366 -> 41489 | Y20: =G20-365*2-366 -> 41461
A21: 1.63 | B21: Desert Hunters | C21: 42642 | D21: =CHOOSE(WEEKDAY(C21,2),"Monday","Tuesday","Wednesday","Thursday","Friday","Saturday","Sunday") -> Thursday | E21: 42641.76 | F21: - | G21: =Devblogs!EB2 -> 42615 | H21: =Devblogs!EC2 -> Friday | I21: =_xludf.DAYS(G21,C20) -> #NAME? | J21: =_xludf.DAYS(C21,G21) -> #NAME? | K21: =C21-'Dev servers'!C7 -> 14 | L21: =C21-C20 -> 57 | V21: =INT(E21) -> 42641 | W21: =E21-V21 -> 0.76041667 | X21: =C21-365*2-366 -> 41546 | Y21: =G21-365*2-366 -> 41519
A22: 1.65 | B22: Way of the Samurai | C22: 42724 | D22: =CHOOSE(WEEKDAY(C22,2),"Monday","Tuesday","Wednesday","Thursday","Friday","Saturday","Sunday") -> Tuesday | E22: 42723.876 | F22: - | G22: =Devblogs!DY2 -> 42684 | H22: =Devblogs!DZ2 -> Thursday | I22: =_xludf.DAYS(G22,C21) -> #NAME? | J22: =_xludf.DAYS(C22,G22) -> #NAME? | K22: =C22-'Dev servers'!C8 -> 10 | L22: =C22-C21 -> 82 | V22: =INT(E22) -> 42723 | W22: =E22-V22 -> 0.87638889 | X22: =C22-365*2-366 -> 41628 | Y22: =G22-365*2-366 -> 41588
A23: 1.67 | B23: Assault | C23: 42810 | D23: =CHOOSE(WEEKDAY(C23,2),"Monday","Tuesday","Wednesday","Thursday","Friday","Saturday","Sunday") -> Thursday | E23: 42809.909 | F23: - | G23: =Devblogs!DV2 -> 42780 | H23: =Devblogs!DW2 -> Tuesday | I23: =_xludf.DAYS(G23,C22) -> #NAME? | J23: =_xludf.DAYS(C23,G23) -> #NAME? | K23: =C23-'Dev servers'!C9 -> 5 | L23: =C23-C22 -> 86 | V23: =INT(E23) -> 42809 | W23: =E23-V23 -> 0.90902778 | X23: =C23-365*3-366 -> 41349 | Y23: =G23-365*3-366 -> 41319
A24: 1.69 | B24: Regia Aeronautica | C24: 42880 | D24: =CHOOSE(WEEKDAY(C24,2),"Monday","Tuesday","Wednesday","Thursday","Friday","Saturday","Sunday") -> Thursday | E24: 42879.894 | F24: - | G24: =Devblogs!DS2 -> 42857 | H24: =Devblogs!DT2 -> Tuesday | I24: =_xludf.DAYS(G24,C23) -> #NAME? | J24: =_xludf.DAYS(C24,G24) -> #NAME? | K24: =C24-'Dev servers'!C10 -> 7 | L24: =C24-C23 -> 70 | M24: 0 day diff | N24: 1 day diff | O24: 2 day diff | P24: 3 day diff | Q24: 4 day diff | R24: 5 day diff | S24: 6 day diff | T24: 7 day diff | U24: 7+ day diff | V24: =INT(E24) -> 42879 | W24: =E24-V24 -> 0.89444444 | X24: =C24-365*3-366 -> 41419 | Y24: =G24-365*3-366 -> 41396
A25: 1.71 | B25: New E.R.A. | C25: 42996 | D25: =CHOOSE(WEEKDAY(C25,2),"Monday","Tuesday","Wednesday","Thursday","Friday","Saturday","Sunday") -> Monday | E25: 42996.347 | F25: 42992 | G25: =Devblogs!DP2 -> 42965 | H25: =Devblogs!DQ2 -> Friday | I25: =_xludf.DAYS(G25,C24) -> #NAME? | J25: =_xludf.DAYS(C25,G25) -> #NAME? | K25: =C25-'Dev servers'!C12 -> 4 | L25: =C25-C24 -> 116 | M25: =C25=F25 -> FALSE | N25: =OR(C25+1=F25,C25=F25+1) -> FALSE | O25: =OR(C25+2=F25,C25=F25+2) -> FALSE | P25: =OR(C25+3=F25,C25=F25+3) -> FALSE | Q25: =OR(C25+4=F25,C25=F25+4) -> TRUE | R25: =OR(C25+5=F25,C25=F25+5) -> FALSE | S25: =OR(C25+6=F25,C25=F25+6) -> FALSE | T25: =OR(C25+7=F25,C25=F25+7) -> FALSE | U25: =OR(C25+8<=F25,C25>=F25+8) -> FALSE | V25: =INT(E25) -> 42996 | W25: =E25-V25 -> 0.34722222 | X25: =C25-365*3-366 -> 41535 | Y25: =G25-365*3-366 -> 41504
A26: 1.73 | B26: Vive la France | C26: 43040 | D26: =CHOOSE(WEEKDAY(C26,2),"Monday","Tuesday","Wednesday","Thursday","Friday","Saturday","Sunday") -> Wednesday | E26: 43040.324 | F26: 43035 | G26: =Devblogs!DM2 -> 43019 | H26: =Devblogs!DN2 -> Wednesday | I26: =_xludf.DAYS(G26,C25) -> #NAME? | J26: =_xludf.DAYS(C26,G26) -> #NAME? | K26: =C26-'Dev servers'!C13 -> 4 | L26: =C26-C25 -> 44 | M26: =C26=F26 -> FALSE | N26: =OR(C26+1=F26,C26=F26+1) -> FALSE | O26: =OR(C26+2=F26,C26=F26+2) -> FALSE | P26: =OR(C26+3=F26,C26=F26+3) -> FALSE | Q26: =OR(C26+4=F26,C26=F26+4) -> FALSE | R26: =OR(C26+5=F26,C26=F26+5) -> TRUE | S26: =OR(C26+6=F26,C26=F26+6) -> FALSE | T26: =OR(C26+7=F26,C26=F26+7) -> FALSE | U26: =OR(C26+8<=F26,C26>=F26+8) -> FALSE | V26: =INT(E26) -> 43040 | W26: =E26-V26 -> 0.32430556 | X26: =C26-365*3-366 -> 41579 | Y26: =G26-365*3-366 -> 41558
A27: 1.75 | B27: La Résistance | C27: 43088 | D27: =CHOOSE(WEEKDAY(C27,2),"Monday","Tuesday","Wednesday","Thursday","Friday","Saturday","Sunday") -> Tuesday | E27: 43087.851 | F27: 43087 | G27: =Devblogs!DJ2 -> 43071 | H27: =Devblogs!DK2 -> Saturday | I27: =_xludf.DAYS(G27,C26) -> #NAME? | J27: =_xludf.DAYS(C27,G27) -> #NAME? | K27: =C27-'Dev servers'!C15 -> 3 | L27: =C27-C26 -> 48 | M27: =C27=F27 -> FALSE | N27: =OR(C27+1=F27,C27=F27+1) -> TRUE | O27: =OR(C27+2=F27,C27=F27+2) -> FALSE | P27: =OR(C27+3=F27,C27=F27+3) -> FALSE | Q27: =OR(C27+4=F27,C27=F27+4) -> FALSE | R27: =OR(C27+5=F27,C27=F27+5) -> FALSE | S27: =OR(C27+6=F27,C27=F27+6) -> FALSE | T27: =OR(C27+7=F27,C27=F27+7) -> FALSE | U27: =OR(C27+8<=F27,C27>=F27+8) -> FALSE | V27: =INT(E27) -> 43087 | W27: =E27-V27 -> 0.85138889 | X27: =C27-365*3-366 -> 41627 | Y27: =G27-365*3-366 -> 41610
A28: 1.77 | B28: Advancing Storm | C28: 43173 | D28: =CHOOSE(WEEKDAY(C28,2),"Monday","Tuesday","Wednesday","Thursday","Friday","Saturday","Sunday") -> Wednesday | E28: 43172.837 | F28: 43172 | G28: =Devblogs!DG2 -> 43138 | H28: =Devblogs!DH2 -> Wednesday | I28: =_xludf.DAYS(G28,C27) -> #NAME? | J28: =_xludf.DAYS(C28,G28) -> #NAME? | K28: =C28-'Dev servers'!C17 -> 4 | L28: =C28-C27 -> 85 | M28: =C28=F28 -> FALSE | N28: =OR(C28+1=F28,C28=F28+1) -> TRUE | O28: =OR(C28+2=F28,C28=F28+2) -> FALSE | P28: =OR(C28+3=F28,C28=F28+3) -> FALSE | Q28: =OR(C28+4=F28,C28=F28+4) -> FALSE | R28: =OR(C28+5=F28,C28=F28+5) -> FALSE | S28: =OR(C28+6=F28,C28=F28+6) -> FALSE | T28: =OR(C28+7=F28,C28=F28+7) -> FALSE | U28: =OR(C28+8<=F28,C28>=F28+8) -> FALSE | V28: =INT(E28) -> 43172 | W28: =E28-V28 -> 0.83680556 | X28: =C28-365*4-366 -> 41347 | Y28: =G28-365*4-366 -> 41312
A29: 1.79 | B29: Project X | C29: 43263 | D29: =CHOOSE(WEEKDAY(C29,2),"Monday","Tuesday","Wednesday","Thursday","Friday","Saturday","Sunday") -> Tuesday | E29: 43262.836 | F29: 43257 | G29: =Devblogs!DD2 -> 43231 | H29: =Devblogs!DE2 -> Friday | I29: =_xludf.DAYS(G29,C28) -> #NAME? | J29: =_xludf.DAYS(C29,G29) -> #NAME? | K29: =C29-'Dev servers'!C19 -> 3 | L29: =C29-C28 -> 90 | M29: =C29=F29 -> FALSE | N29: =OR(C29+1=F29,C29=F29+1) -> FALSE | O29: =OR(C29+2=F29,C29=F29+2) -> FALSE | P29: =OR(C29+3=F29,C29=F29+3) -> FALSE | Q29: =OR(C29+4=F29,C29=F29+4) -> FALSE | R29: =OR(C29+5=F29,C29=F29+5) -> FALSE | S29: =OR(C29+6=F29,C29=F29+6) -> TRUE | T29: =OR(C29+7=F29,C29=F29+7) -> FALSE | U29: =OR(C29+8<=F29,C29>=F29+8) -> FALSE | V29: =INT(E29) -> 43262 | W29: =E29-V29 -> 0.83611111 | X29: =C29-365*4-366 -> 41437 | Y29: =G29-365*4-366 -> 41405
A30: 1.81 | B30: The Valkyries | C30: 43362 | D30: =CHOOSE(WEEKDAY(C30,2),"Monday","Tuesday","Wednesday","Thursday","Friday","Saturday","Sunday") -> Wednesday | E30: 43361.835 | F30: 43354 | G30: =Devblogs!DA2 -> 43333 | H30: =Devblogs!DB2 -> Tuesday | I30: =_xludf.DAYS(G30,C29) -> #NAME? | J30: =_xludf.DAYS(C30,G30) -> #NAME? | K30: =C30-'Dev servers'!C22 -> 4 | L30: =C30-C29 -> 99 | M30: =C30=F30 -> FALSE | N30: =OR(C30+1=F30,C30=F30+1) -> FALSE | O30: =OR(C30+2=F30,C30=F30+2) -> FALSE | P30: =OR(C30+3=F30,C30=F30+3) -> FALSE | Q30: =OR(C30+4=F30,C30=F30+4) -> FALSE | R30: =OR(C30+5=F30,C30=F30+5) -> FALSE | S30: =OR(C30+6=F30,C30=F30+6) -> FALSE | T30: =OR(C30+7=F30,C30=F30+7) -> FALSE | U30: =OR(C30+8<=F30,C30>=F30+8) -> TRUE | V30: =INT(E30) -> 43361 | W30: =E30-V30 -> 0.83541667 | X30: =C30-365*4-366 -> 41536 | Y30: =G30-365*4-366 -> 41507
A31: 1.83 | B31: Masters of the Sea | C31: 43396 | D31: =CHOOSE(WEEKDAY(C31,2),"Monday","Tuesday","Wednesday","Thursday","Friday","Saturday","Sunday") -> Tuesday | E31: 43395.84 | F31: 43396 | G31: =Devblogs!CX2 -> 43382 | H31: =Devblogs!CY2 -> Tuesday | I31: =_xludf.DAYS(G31,C30) -> #NAME? | J31: =_xludf.DAYS(C31,G31) -> #NAME? | K31: =C31-'Dev servers'!C23 -> 7 | L31: =C31-C30 -> 34 | M31: =C31=F31 -> TRUE | N31: =OR(C31+1=F31,C31=F31+1) -> FALSE | O31: =OR(C31+2=F31,C31=F31+2) -> FALSE | P31: =OR(C31+3=F31,C31=F31+3) -> FALSE | Q31: =OR(C31+4=F31,C31=F31+4) -> FALSE | R31: =OR(C31+5=F31,C31=F31+5) -> FALSE | S31: =OR(C31+6=F31,C31=F31+6) -> FALSE | T31: =OR(C31+7=F31,C31=F31+7) -> FALSE | U31: =OR(C31+8<=F31,C31>=F31+8) -> FALSE | V31: =INT(E31) -> 43395 | W31: =E31-V31 -> 0.83958333 | X31: =C31-365*4-366 -> 41570 | Y31: =G31-365*4-366 -> 41556
A32: 1.85 | B32: Supersonic | C32: 43451 | D32: =CHOOSE(WEEKDAY(C32,2),"Monday","Tuesday","Wednesday","Thursday","Friday","Saturday","Sunday") -> Monday | E32: 43450.844 | F32: 43452 | G32: =Devblogs!CU2 -> 43427 | H32: =Devblogs!CV2 -> Friday | I32: =_xludf.DAYS(G32,C31) -> #NAME? | J32: =_xludf.DAYS(C32,G32) -> #NAME? | K32: =C32-'Dev servers'!C25 -> 4 | L32: =C32-C31 -> 55 | M32: =C32=F32 -> FALSE | N32: =OR(C32+1=F32,C32=F32+1) -> TRUE | O32: =OR(C32+2=F32,C32=F32+2) -> FALSE | P32: =OR(C32+3=F32,C32=F32+3) -> FALSE | Q32: =OR(C32+4=F32,C32=F32+4) -> FALSE | R32: =OR(C32+5=F32,C32=F32+5) -> FALSE | S32: =OR(C32+6=F32,C32=F32+6) -> FALSE | T32: =OR(C32+7=F32,C32=F32+7) -> FALSE | U32: =OR(C32+8<=F32,C32>=F32+8) -> FALSE | V32: =INT(E32) -> 43450 | W32: =E32-V32 -> 0.84375 | X32: =C32-365*4-366 -> 41625 | Y32: =G32-365*4-366 -> 41601
A33: 1.87 | B33: Locked On | C33: 43536 | D33: =CHOOSE(WEEKDAY(C33,2),"Monday","Tuesday","Wednesday","Thursday","Friday","Saturday","Sunday") -> Tuesday | E33: 43535.868 | F33: 43536 | G33: =Devblogs!CR2 -> 43511 | H33: =Devblogs!CS2 -> Friday | I33: =_xludf.DAYS(G33,C32) -> #NAME? | J33: =_xludf.DAYS(C33,G33) -> #NAME? | K33: =C33-'Dev servers'!C27 -> 6 | L33: =C33-C32 -> 85 | M33: =C33=F33 -> TRUE | N33: =OR(C33+1=F33,C33=F33+1) -> FALSE | O33: =OR(C33+2=F33,C33=F33+2) -> FALSE | P33: =OR(C33+3=F33,C33=F33+3) -> FALSE | Q33: =OR(C33+4=F33,C33=F33+4) -> FALSE | R33: =OR(C33+5=F33,C33=F33+5) -> FALSE | S33: =OR(C33+6=F33,C33=F33+6) -> FALSE | T33: =OR(C33+7=F33,C33=F33+7) -> FALSE | U33: =OR(C33+8<=F33,C33>=F33+8) -> FALSE | V33: =INT(E33) -> 43535 | W33: =E33-V33 -> 0.86805556 | X33: =C33-365*5-366 -> 41345 | Y33: =G33-365*5-366 -> 41320
A34: 1.89 | B34: Imperial Navy | C34: 43614 | D34: =CHOOSE(WEEKDAY(C34,2),"Monday","Tuesday","Wednesday","Thursday","Friday","Saturday","Sunday") -> Wednesday | E34: 43613.794 | F34: 43613 | G34: =Devblogs!CO2 -> 43588 | H34: =Devblogs!CP2 -> Friday | I34: =_xludf.DAYS(G34,C33) -> #NAME? | J34: =_xludf.DAYS(C34,G34) -> #NAME? | K34: =C34-'Dev servers'!C29 -> 4 | L34: =C34-C33 -> 78 | M34: =C34=F34 -> FALSE | N34: =OR(C34+1=F34,C34=F34+1) -> TRUE | O34: =OR(C34+2=F34,C34=F34+2) -> FALSE | P34: =OR(C34+3=F34,C34=F34+3) -> FALSE | Q34: =OR(C34+4=F34,C34=F34+4) -> FALSE | R34: =OR(C34+5=F34,C34=F34+5) -> FALSE | S34: =OR(C34+6=F34,C34=F34+6) -> FALSE | T34: =OR(C34+7=F34,C34=F34+7) -> FALSE | U34: =OR(C34+8<=F34,C34>=F34+8) -> FALSE | V34: =INT(E34) -> 43613 | W34: =E34-V34 -> 0.79375 | X34: =C34-365*5-366 -> 41423 | Y34: =G34-365*5-366 -> 41397
A35: 1.91 | B35: Night Vision | C35: 43719 | D35: =CHOOSE(WEEKDAY(C35,2),"Monday","Tuesday","Wednesday","Thursday","Friday","Saturday","Sunday") -> Wednesday | E35: 43718.794 | F35: 43718 | G35: =Devblogs!CL2 -> 43690 | H35: =Devblogs!CM2 -> Tuesday | I35: =_xludf.DAYS(G35,C34) -> #NAME? | J35: =_xludf.DAYS(C35,G35) -> #NAME? | K35: =C35-'Dev servers'!C31 -> 6 | L35: =C35-C34 -> 105 | M35: =C35=F35 -> FALSE | N35: =OR(C35+1=F35,C35=F35+1) -> TRUE | O35: =OR(C35+2=F35,C35=F35+2) -> FALSE | P35: =OR(C35+3=F35,C35=F35+3) -> FALSE | Q35: =OR(C35+4=F35,C35=F35+4) -> FALSE | R35: =OR(C35+5=F35,C35=F35+5) -> FALSE | S35: =OR(C35+6=F35,C35=F35+6) -> FALSE | T35: =OR(C35+7=F35,C35=F35+7) -> FALSE | U35: =OR(C35+8<=F35,C35>=F35+8) -> FALSE | V35: =INT(E35) -> 43718 | W35: =E35-V35 -> 0.79375 | X35: =C35-365*5-366 -> 41528 | Y35: =G35-365*5-366 -> 41499
A36: 1.93 | B36: Shark Attack | C36: 43767 | D36: =CHOOSE(WEEKDAY(C36,2),"Monday","Tuesday","Wednesday","Thursday","Friday","Saturday","Sunday") -> Tuesday | E36: 43766.797 | F36: 43767 | G36: =Devblogs!CI2 -> 43749 | H36: =Devblogs!CJ2 -> Friday | I36: =_xludf.DAYS(G36,C35) -> #NAME? | J36: =_xludf.DAYS(C36,G36) -> #NAME? | K36: =C36-'Dev servers'!C32 -> 5 | L36: =C36-C35 -> 48 | M36: =C36=F36 -> TRUE | N36: =OR(C36+1=F36,C36=F36+1) -> FALSE | O36: =OR(C36+2=F36,C36=F36+2) -> FALSE | P36: =OR(C36+3=F36,C36=F36+3) -> FALSE | Q36: =OR(C36+4=F36,C36=F36+4) -> FALSE | R36: =OR(C36+5=F36,C36=F36+5) -> FALSE | S36: =OR(C36+6=F36,C36=F36+6) -> FALSE | T36: =OR(C36+7=F36,C36=F36+7) -> FALSE | U36: =OR(C36+8<=F36,C36>=F36+8) -> FALSE | V36: =INT(E36) -> 43766 | W36: =E36-V36 -> 0.79652778 | X36: =C36-365*5-366 -> 41576 | Y36: =G36-365*5-366 -> 41558
A37: 1.95 | B37: Northern Wind | C37: 43816 | D37: =CHOOSE(WEEKDAY(C37,2),"Monday","Tuesday","Wednesday","Thursday","Friday","Saturday","Sunday") -> Tuesday | E37: 43815.838 | F37: 43815 | G37: =Devblogs!CF2 -> 43797 | H37: =Devblogs!CG2 -> Thursday | I37: =_xludf.DAYS(G37,C36) -> #NAME? | J37: =_xludf.DAYS(C37,G37) -> #NAME? | K37: =C37-'Dev servers'!C33 -> 5 | L37: =C37-C36 -> 49 | M37: =C37=F37 -> FALSE | N37: =OR(C37+1=F37,C37=F37+1) -> TRUE | O37: =OR(C37+2=F37,C37=F37+2) -> FALSE | P37: =OR(C37+3=F37,C37=F37+3) -> FALSE | Q37: =OR(C37+4=F37,C37=F37+4) -> FALSE | R37: =OR(C37+5=F37,C37=F37+5) -> FALSE | S37: =OR(C37+6=F37,C37=F37+6) -> FALSE | T37: =OR(C37+7=F37,C37=F37+7) -> FALSE | U37: =OR(C37+8<=F37,C37>=F37+8) -> FALSE | V37: =INT(E37) -> 43815 | W37: =E37-V37 -> 0.83819444 | X37: =C37-365*5-366 -> 41625 | Y37: =G37-365*5-366 -> 41606
A38: 1.97 | B38: Viking Fury | C38: 43906 | D38: =CHOOSE(WEEKDAY(C38,2),"Monday","Tuesday","Wednesday","Thursday","Friday","Saturday","Sunday") -> Monday | E38: 43905.797 | F38: 43900 | G38: =Devblogs!CC2 -> 43881 | H38: =Devblogs!CD2 -> Thursday | I38: =_xludf.DAYS(G38,C37) -> #NAME? | J38: =_xludf.DAYS(C38,G38) -> #NAME? | K38: =C38-'Dev servers'!C35 -> 9 | L38: =C38-C37 -> 90 | M38: =C38=F38 -> FALSE | N38: =OR(C38+1=F38,C38=F38+1) -> FALSE | O38: =OR(C38+2=F38,C38=F38+2) -> FALSE | P38: =OR(C38+3=F38,C38=F38+3) -> FALSE | Q38: =OR(C38+4=F38,C38=F38+4) -> FALSE | R38: =OR(C38+5=F38,C38=F38+5) -> FALSE | S38: =OR(C38+6=F38,C38=F38+6) -> TRUE | T38: =OR(C38+7=F38,C38=F38+7) -> FALSE | U38: =OR(C38+8<=F38,C38>=F38+8) -> FALSE | V38: =INT(E38) -> 43905 | W38: =E38-V38 -> 0.79652778 | X38: =C38-365*5-366*2 -> 41349 | Y38: =G38-365*6-366 -> 41325
A39: 1.99 | B39: Starfighters | C39: 43977 | D39: =CHOOSE(WEEKDAY(C39,2),"Monday","Tuesday","Wednesday","Thursday","Friday","Saturday","Sunday") -> Tuesday | E39: 43976.795 | F39: 43983 | G39: =Devblogs!BZ2 -> 43956 | H39: =Devblogs!CA2 -> Tuesday | I39: =_xludf.DAYS(G39,C38) -> #NAME? | J39: =_xludf.DAYS(C39,G39) -> #NAME? | K39: =C39-'Dev servers'!C37 -> 5 | L39: =C39-C38 -> 71 | M39: =C39=F39 -> FALSE | N39: =OR(C39+1=F39,C39=F39+1) -> FALSE | O39: =OR(C39+2=F39,C39=F39+2) -> FALSE | P39: =OR(C39+3=F39,C39=F39+3) -> FALSE | Q39: =OR(C39+4=F39,C39=F39+4) -> FALSE | R39: =OR(C39+5=F39,C39=F39+5) -> FALSE | S39: =OR(C39+6=F39,C39=F39+6) -> TRUE | T39: =OR(C39+7=F39,C39=F39+7) -> FALSE | U39: =OR(C39+8<=F39,C39>=F39+8) -> FALSE | V39: =INT(E39) -> 43976 | W39: =E39-V39 -> 0.79513889 | X39: =C39-365*5-366*2 -> 41420 | Y39: =G39-365*5-366*2 -> 41399
A40: 1.101 | B40: Raining Fire | C40: 44076 | D40: =CHOOSE(WEEKDAY(C40,2),"Monday","Tuesday","Wednesday","Thursday","Friday","Saturday","Sunday") -> Wednesday | E40: 44075.793 | F40: 44082 | G40: =Devblogs!BW2 -> 44057 | H40: =Devblogs!BX2 -> Friday | I40: =_xludf.DAYS(G40,C39) -> #NAME? | J40: =_xludf.DAYS(C40,G40) -> #NAME? | K40: =C40-'Dev servers'!C39 -> 7 | L40: =C40-C39 -> 99 | M40: =C40=F40 -> FALSE | N40: =OR(C40+1=F40,C40=F40+1) -> FALSE | O40: =OR(C40+2=F40,C40=F40+2) -> FALSE | P40: =OR(C40+3=F40,C40=F40+3) -> FALSE | Q40: =OR(C40+4=F40,C40=F40+4) -> FALSE | R40: =OR(C40+5=F40,C40=F40+5) -> FALSE | S40: =OR(C40+6=F40,C40=F40+6) -> TRUE | T40: =OR(C40+7=F40,C40=F40+7) -> FALSE | U40: =OR(C40+8<=F40,C40>=F40+8) -> FALSE | V40: =INT(E40) -> 44075 | W40: =E40-V40 -> 0.79305556 | X40: =C40-365*5-366*2 -> 41519 | Y40: =G40-365*5-366*2 -> 41500
A41: 2.1 | B41: New Power | C41: 44152 | D41: =CHOOSE(WEEKDAY(C41,2),"Monday","Tuesday","Wednesday","Thursday","Friday","Saturday","Sunday") -> Tuesday | E41: 44151.83 | F41: 44150 | G41: =Devblogs!BT2 -> 44124 | H41: =Devblogs!BU2 -> Tuesday | I41: =_xludf.DAYS(G41,C40) -> #NAME? | J41: =_xludf.DAYS(C41,G41) -> #NAME? | K41: =C41-'Dev servers'!C41 -> 7 | L41: =C41-C40 -> 76 | M41: =C41=F41 -> FALSE | N41: =OR(C41+1=F41,C41=F41+1) -> FALSE | O41: =OR(C41+2=F41,C41=F41+2) -> TRUE | P41: =OR(C41+3=F41,C41=F41+3) -> FALSE | Q41: =OR(C41+4=F41,C41=F41+4) -> FALSE | R41: =OR(C41+5=F41,C41=F41+5) -> FALSE | S41: =OR(C41+6=F41,C41=F41+6) -> FALSE | T41: =OR(C41+7=F41,C41=F41+7) -> FALSE | U41: =OR(C41+8<=F41,C41>=F41+8) -> FALSE | V41: =INT(E41) -> 44151 | W41: =E41-V41 -> 0.82986111 | X41: =C41-365*5-366*2 -> 41595 | Y41: =G41-365*5-366*2 -> 41567
A42: 2.3 | B42: Hot Tracks | C42: 44183 | D42: =CHOOSE(WEEKDAY(C42,2),"Monday","Tuesday","Wednesday","Thursday","Friday","Saturday","Sunday") -> Friday | E42: 44181.835 | F42: 44182 | G42: =Devblogs!BQ2 -> 44172 | H42: =Devblogs!BR2 -> Monday | I42: =_xludf.DAYS(G42,C41) -> #NAME? | J42: =_xludf.DAYS(C42,G42) -> #NAME? | K42: =C42-'Dev servers'!C42 -> 6 | L42: =C42-C41 -> 31 | M42: =C42=F42 -> FALSE | N42: =OR(C42+1=F42,C42=F42+1) -> TRUE | O42: =OR(C42+2=F42,C42=F42+2) -> FALSE | P42: =OR(C42+3=F42,C42=F42+3) -> FALSE | Q42: =OR(C42+4=F42,C42=F42+4) -> FALSE | R42: =OR(C42+5=F42,C42=F42+5) -> FALSE | S42: =OR(C42+6=F42,C42=F42+6) -> FALSE | T42: =OR(C42+7=F42,C42=F42+7) -> FALSE | U42: =OR(C42+8<=F42,C42>=F42+8) -> FALSE | V42: =INT(E42) -> 44181 | W42: =E42-V42 -> 0.83541667 | X42: =C42-365*5-366*2 -> 41626 | Y42: =G42-365*5-366*2 -> 41615
A43: 2.5 | B43: Ixwa Strike | C43: 44265 | D43: =CHOOSE(WEEKDAY(C43,2),"Monday","Tuesday","Wednesday","Thursday","Friday","Saturday","Sunday") -> Wednesday | E43: 44264.794 | F43: 44265 | G43: =Devblogs!BN2 -> 44242 | H43: =Devblogs!BO2 -> Monday | I43: =_xludf.DAYS(G43,C42) -> #NAME? | J43: =_xludf.DAYS(C43,G43) -> #NAME? | K43: =C43-'Dev servers'!C44 -> 7 | L43: =C43-C42 -> 82 | M43: =C43=F43 -> TRUE | N43: =OR(C43+1=F43,C43=F43+1) -> FALSE | O43: =OR(C43+2=F43,C43=F43+2) -> FALSE | P43: =OR(C43+3=F43,C43=F43+3) -> FALSE | Q43: =OR(C43+4=F43,C43=F43+4) -> FALSE | R43: =OR(C43+5=F43,C43=F43+5) -> FALSE | S43: =OR(C43+6=F43,C43=F43+6) -> FALSE | T43: =OR(C43+7=F43,C43=F43+7) -> FALSE | U43: =OR(C43+8<=F43,C43>=F43+8) -> FALSE | V43: =INT(E43) -> 44264 | W43: =E43-V43 -> 0.79444444 | X43: =C43-365*6-366*2 -> 41343 | Y43: =G43-365*6-366*2 -> 41320
A44: 2.7 | B44: Red Skies | C44: 44349 | D44: =CHOOSE(WEEKDAY(C44,2),"Monday","Tuesday","Wednesday","Thursday","Friday","Saturday","Sunday") -> Wednesday | E44: 44348.835 | F44: 44349 | G44: =Devblogs!BK2 -> 44328 | H44: =Devblogs!BL2 -> Wednesday | I44: =_xludf.DAYS(G44,C43) -> #NAME? | J44: =_xludf.DAYS(C44,G44) -> #NAME? | K44: =C44-'Dev servers'!C46 -> 7 | L44: =C44-C43 -> 84 | M44: =C44=F44 -> TRUE | N44: =OR(C44+1=F44,C44=F44+1) -> FALSE | O44: =OR(C44+2=F44,C44=F44+2) -> FALSE | P44: =OR(C44+3=F44,C44=F44+3) -> FALSE | Q44: =OR(C44+4=F44,C44=F44+4) -> FALSE | R44: =OR(C44+5=F44,C44=F44+5) -> FALSE | S44: =OR(C44+6=F44,C44=F44+6) -> FALSE | T44: =OR(C44+7=F44,C44=F44+7) -> FALSE | U44: =OR(C44+8<=F44,C44>=F44+8) -> FALSE | V44: =INT(E44) -> 44348 | W44: =E44-V44 -> 0.83472222 | X44: =C44-365*6-366*2 -> 41427 | Y44: =G44-365*6-366*2 -> 41406
A45: 2.9 | B45: Direct Hit | C45: 44446 | D45: =CHOOSE(WEEKDAY(C45,2),"Monday","Tuesday","Wednesday","Thursday","Friday","Saturday","Sunday") -> Tuesday | E45: 44445.795 | F45: 44446 | G45: =Devblogs!BH2 -> 44426 | H45: =Devblogs!BI2 -> Wednesday | I45: =_xludf.DAYS(G45,C44) -> #NAME? | J45: =_xludf.DAYS(C45,G45) -> #NAME? | K45: =C45-'Dev servers'!C48 -> 6 | L45: =C45-C44 -> 97 | M45: =C45=F45 -> TRUE | N45: =OR(C45+1=F45,C45=F45+1) -> FALSE | O45: =OR(C45+2=F45,C45=F45+2) -> FALSE | P45: =OR(C45+3=F45,C45=F45+3) -> FALSE | Q45: =OR(C45+4=F45,C45=F45+4) -> FALSE | R45: =OR(C45+5=F45,C45=F45+5) -> FALSE | S45: =OR(C45+6=F45,C45=F45+6) -> FALSE | T45: =OR(C45+7=F45,C45=F45+7) -> FALSE | U45: =OR(C45+8<=F45,C45>=F45+8) -> FALSE | V45: =INT(E45) -> 44445 | W45: =E45-V45 -> 0.79513889 | X45: =C45-365*6-366*2 -> 41524 | Y45: =G45-365*6-366*2 -> 41504
A46: 2.11 | B46: Ground Breaking | C46: 44497 | D46: =CHOOSE(WEEKDAY(C46,2),"Monday","Tuesday","Wednesday","Thursday","Friday","Saturday","Sunday") -> Thursday | E46: 44496.794 | F46: 44495 | G46: =Devblogs!BE2 -> 44477 | H46: =Devblogs!BF2 -> Friday | I46: =_xludf.DAYS(G46,C45) -> #NAME? | J46: =_xludf.DAYS(C46,G46) -> #NAME? | K46: =C46-'Dev servers'!C51 -> 7 | L46: =C46-C45 -> 51 | M46: =C46=F46 -> FALSE | N46: =OR(C46+1=F46,C46=F46+1) -> FALSE | O46: =OR(C46+2=F46,C46=F46+2) -> TRUE | P46: =OR(C46+3=F46,C46=F46+3) -> FALSE | Q46: =OR(C46+4=F46,C46=F46+4) -> FALSE | R46: =OR(C46+5=F46,C46=F46+5) -> FALSE | S46: =OR(C46+6=F46,C46=F46+6) -> FALSE | T46: =OR(C46+7=F46,C46=F46+7) -> FALSE | U46: =OR(C46+8<=F46,C46>=F46+8) -> FALSE | V46: =INT(E46) -> 44496 | W46: =E46-V46 -> 0.79375 | X46: =C46-365*6-366*2 -> 41575 | Y46: =G46-365*6-366*2 -> 41555
A47: 2.13 | B47: Winged Lions | C47: 44544 | D47: =CHOOSE(WEEKDAY(C47,2),"Monday","Tuesday","Wednesday","Thursday","Friday","Saturday","Sunday") -> Tuesday | E47: 44543.795 | F47: 44547 | G47: =Devblogs!BB2 -> 44530 | H47: =Devblogs!BC2 -> Tuesday | I47: =_xludf.DAYS(G47,C46) -> #NAME? | J47: =_xludf.DAYS(C47,G47) -> #NAME? | K47: =C47-'Dev servers'!C53 -> 6 | L47: =C47-C46 -> 47 | M47: =C47=F47 -> FALSE | N47: =OR(C47+1=F47,C47=F47+1) -> FALSE | O47: =OR(C47+2=F47,C47=F47+2) -> FALSE | P47: =OR(C47+3=F47,C47=F47+3) -> TRUE | Q47: =OR(C47+4=F47,C47=F47+4) -> FALSE | R47: =OR(C47+5=F47,C47=F47+5) -> FALSE | S47: =OR(C47+6=F47,C47=F47+6) -> FALSE | T47: =OR(C47+7=F47,C47=F47+7) -> FALSE | U47: =OR(C47+8<=F47,C47>=F47+8) -> FALSE | V47: =INT(E47) -> 44543 | W47: =E47-V47 -> 0.79513889 | X47: =C47-365*6-366*2 -> 41622 | Y47: =G47-365*6-366*2 -> 41608
A48: 2.15 | B48: Wind of Change | C48: 44644 | D48: =CHOOSE(WEEKDAY(C48,2),"Monday","Tuesday","Wednesday","Thursday","Friday","Saturday","Sunday") -> Thursday | E48: 44643.858 | F48: 44642 | G48: =Devblogs!AY2 -> 44610 | H48: =Devblogs!AZ2 -> Friday | I48: =_xludf.DAYS(G48,C47) -> #NAME? | J48: =_xludf.DAYS(C48,G48) -> #NAME? | K48: =C48-'Dev servers'!C55 -> 8 | L48: =C48-C47 -> 100 | M48: =C48=F48 -> FALSE | N48: =OR(C48+1=F48,C48=F48+1) -> FALSE | O48: =OR(C48+2=F48,C48=F48+2) -> TRUE | P48: =OR(C48+3=F48,C48=F48+3) -> FALSE | Q48: =OR(C48+4=F48,C48=F48+4) -> FALSE | R48: =OR(C48+5=F48,C48=F48+5) -> FALSE | S48: =OR(C48+6=F48,C48=F48+6) -> FALSE | T48: =OR(C48+7=F48,C48=F48+7) -> FALSE | U48: =OR(C48+8<=F48,C48>=F48+8) -> FALSE | V48: =INT(E48) -> 44643 | W48: =E48-V48 -> 0.85763889 | X48: =C48-365*7-366*2 -> 41357 | Y48: =G48-365*7-366*2 -> 41323
A49: 2.17 | B49: Danger Zone | C49: 44727 | D49: =CHOOSE(WEEKDAY(C49,2),"Monday","Tuesday","Wednesday","Thursday","Friday","Saturday","Sunday") -> Wednesday | E49: 44726.792 | F49: 44719 | G49: =Devblogs!AV2 -> 44699 | H49: =Devblogs!AW2 -> Wednesday | I49: =_xludf.DAYS(G49,C48) -> #NAME? | J49: =_xludf.DAYS(C49,G49) -> #NAME? | K49: =C49-'Dev servers'!C57 -> 12 | L49: =C49-C48 -> 83 | M49: =C49=F49 -> FALSE | N49: =OR(C49+1=F49,C49=F49+1) -> FALSE | O49: =OR(C49+2=F49,C49=F49+2) -> FALSE | P49: =OR(C49+3=F49,C49=F49+3) -> FALSE | Q49: =OR(C49+4=F49,C49=F49+4) -> FALSE | R49: =OR(C49+5=F49,C49=F49+5) -> FALSE | S49: =OR(C49+6=F49,C49=F49+6) -> FALSE | T49: =OR(C49+7=F49,C49=F49+7) -> FALSE | U49: =OR(C49+8<=F49,C49>=F49+8) -> TRUE | V49: =INT(E49) -> 44726 | W49: =E49-V49 -> 0.79236111 | X49: =C49-365*7-366*2 -> 41440 | Y49: =G49-365*7-366*2 -> 41412
A50: 2.19 | B50: Drone Age | C50: 44818 | D50: =CHOOSE(WEEKDAY(C50,2),"Monday","Tuesday","Wednesday","Thursday","Friday","Saturday","Sunday") -> Wednesday | E50: 44817.794 | F50: 44810 | G50: =Devblogs!AS2 -> 44789 | H50: =Devblogs!AT2 -> Tuesday | I50: =_xludf.DAYS(G50,C49) -> #NAME? | J50: =_xludf.DAYS(C50,G50) -> #NAME? | K50: =C50-'Dev servers'!C58 -> 12 | L50: =C50-C49 -> 91 | M50: =C50=F50 -> FALSE | N50: =OR(C50+1=F50,C50=F50+1) -> FALSE | O50: =OR(C50+2=F50,C50=F50+2) -> FALSE | P50: =OR(C50+3=F50,C50=F50+3) -> FALSE | Q50: =OR(C50+4=F50,C50=F50+4) -> FALSE | R50: =OR(C50+5=F50,C50=F50+5) -> FALSE | S50: =OR(C50+6=F50,C50=F50+6) -> FALSE | T50: =OR(C50+7=F50,C50=F50+7) -> FALSE | U50: =OR(C50+8<=F50,C50>=F50+8) -> TRUE | V50: =INT(E50) -> 44817 | W50: =E50-V50 -> 0.79444444 | X50: =C50-365*7-366*2 -> 41531 | Y50: =G50-365*7-366*2 -> 41502
A51: 2.21 | B51: Fire and Ice | C51: 44860 | D51: =CHOOSE(WEEKDAY(C51,2),"Monday","Tuesday","Wednesday","Thursday","Friday","Saturday","Sunday") -> Wednesday | E51: 44859.792 | F51: 44866 | G51: =Devblogs!AP2 -> 44846 | H51: =Devblogs!AQ2 -> Wednesday | I51: =_xludf.DAYS(G51,C50) -> #NAME? | J51: =_xludf.DAYS(C51,G51) -> #NAME? | K51: =C51-'Dev servers'!C59 -> 12 | L51: =C51-C50 -> 42 | M51: =C51=F51 -> FALSE | N51: =OR(C51+1=F51,C51=F51+1) -> FALSE | O51: =OR(C51+2=F51,C51=F51+2) -> FALSE | P51: =OR(C51+3=F51,C51=F51+3) -> FALSE | Q51: =OR(C51+4=F51,C51=F51+4) -> FALSE | R51: =OR(C51+5=F51,C51=F51+5) -> FALSE | S51: =OR(C51+6=F51,C51=F51+6) -> TRUE | T51: =OR(C51+7=F51,C51=F51+7) -> FALSE | U51: =OR(C51+8<=F51,C51>=F51+8) -> FALSE | V51: =INT(E51) -> 44859 | W51: =E51-V51 -> 0.79166667 | X51: =C51-365*7-366*2 -> 41573 | Y51: =G51-365*7-366*2 -> 41559
A52: 2.23 | B52: Apex Predators | C52: 44915 | D52: =CHOOSE(WEEKDAY(C52,2),"Monday","Tuesday","Wednesday","Thursday","Friday","Saturday","Sunday") -> Tuesday | E52: 44914.793 | F52: 44913 | G52: =Devblogs!AM2 -> 44894 | H52: =Devblogs!AN2 -> Tuesday | I52: =_xludf.DAYS(G52,C51) -> #NAME? | J52: =_xludf.DAYS(C52,G52) -> #NAME? | K52: =C52-'Dev servers'!C60 -> 11 | L52: =C52-C51 -> 55 | M52: =C52=F52 -> FALSE | N52: =OR(C52+1=F52,C52=F52+1) -> FALSE | O52: =OR(C52+2=F52,C52=F52+2) -> TRUE | P52: =OR(C52+3=F52,C52=F52+3) -> FALSE | Q52: =OR(C52+4=F52,C52=F52+4) -> FALSE | R52: =OR(C52+5=F52,C52=F52+5) -> FALSE | S52: =OR(C52+6=F52,C52=F52+6) -> FALSE | T52: =OR(C52+7=F52,C52=F52+7) -> FALSE | U52: =OR(C52+8<=F52,C52>=F52+8) -> FALSE | V52: =INT(E52) -> 44914 | W52: =E52-V52 -> 0.79305556 | X52: =C52-365*7-366*2 -> 41628 | Y52: =G52-365*7-366*2 -> 41607
A53: 2.25 | B53: Sky Guardians | C53: 44992 | D53: =CHOOSE(WEEKDAY(C53,2),"Monday","Tuesday","Wednesday","Thursday","Friday","Saturday","Sunday") -> Tuesday | E53: 44991.793 | F53: 44992 | G53: =Devblogs!AJ2 -> 44967 | H53: =Devblogs!AK2 -> Friday | I53: =_xludf.DAYS(G53,C52) -> #NAME? | J53: =_xludf.DAYS(C53,G53) -> #NAME? | K53: =C53-'Dev servers'!C61 -> 10 | L53: =C53-C52 -> 77 | M53: =C53=F53 -> TRUE | N53: =OR(C53+1=F53,C53=F53+1) -> FALSE | O53: =OR(C53+2=F53,C53=F53+2) -> FALSE | P53: =OR(C53+3=F53,C53=F53+3) -> FALSE | Q53: =OR(C53+4=F53,C53=F53+4) -> FALSE | R53: =OR(C53+5=F53,C53=F53+5) -> FALSE | S53: =OR(C53+6=F53,C53=F53+6) -> FALSE | T53: =OR(C53+7=F53,C53=F53+7) -> FALSE | U53: =OR(C53+8<=F53,C53>=F53+8) -> FALSE | V53: =INT(E53) -> 44991 | W53: =E53-V53 -> 0.79305556 | X53: =C53-365*8-366*2 -> 41340 | Y53: =G53-365*8-366*2 -> 41315
A54: 2.27 | B54: La Royale | C54: 45091 | D54: =CHOOSE(WEEKDAY(C54,2),"Monday","Tuesday","Wednesday","Thursday","Friday","Saturday","Sunday") -> Wednesday | E54: 45090.876 | F54: 45083 | G54: =Devblogs!AG2 -> 45037 | H54: =Devblogs!AH2 -> Friday | I54: =_xludf.DAYS(G54,C53) -> #NAME? | J54: =_xludf.DAYS(C54,G54) -> #NAME? | K54: =C54-'Dev servers'!C63 -> 15 | L54: =C54-C53 -> 99 | M54: =C54=F54 -> FALSE | N54: =OR(C54+1=F54,C54=F54+1) -> FALSE | O54: =OR(C54+2=F54,C54=F54+2) -> FALSE | P54: =OR(C54+3=F54,C54=F54+3) -> FALSE | Q54: =OR(C54+4=F54,C54=F54+4) -> FALSE | R54: =OR(C54+5=F54,C54=F54+5) -> FALSE | S54: =OR(C54+6=F54,C54=F54+6) -> FALSE | T54: =OR(C54+7=F54,C54=F54+7) -> FALSE | U54: =OR(C54+8<=F54,C54>=F54+8) -> TRUE | V54: =INT(E54) -> 45090 | W54: =E54-V54 -> 0.87569444 | X54: =C54-365*8-366*2 -> 41439 | Y54: =G54-365*8-366*2 -> 41385
A55: 2.29 | B55: Sons of Attila | C55: 45188 | D55: =CHOOSE(WEEKDAY(C55,2),"Monday","Tuesday","Wednesday","Thursday","Friday","Saturday","Sunday") -> Tuesday | E55: 45187.794 | F55: 45188 | G55: =Devblogs!AD2 -> 45159 | H55: =Devblogs!AE2 -> Monday | I55: =_xludf.DAYS(G55,C54) -> #NAME? | J55: =_xludf.DAYS(C55,G55) -> #NAME? | K55: =C55-'Dev servers'!C65 -> 7 | L55: =C55-C54 -> 97 | M55: =C55=F55 -> TRUE | N55: =OR(C55+1=F55,C55=F55+1) -> FALSE | O55: =OR(C55+2=F55,C55=F55+2) -> FALSE | P55: =OR(C55+3=F55,C55=F55+3) -> FALSE | Q55: =OR(C55+4=F55,C55=F55+4) -> FALSE | R55: =OR(C55+5=F55,C55=F55+5) -> FALSE | S55: =OR(C55+6=F55,C55=F55+6) -> FALSE | T55: =OR(C55+7=F55,C55=F55+7) -> FALSE | U55: =OR(C55+8<=F55,C55>=F55+8) -> FALSE | V55: =INT(E55) -> 45187 | W55: =E55-V55 -> 0.79375 | X55: =C55-365*8-366*2 -> 41536 | Y55: =G55-365*8-366*2 -> 41507
A56: 2.31 | B56: Kings of Battle | C56: 45230 | D56: =CHOOSE(WEEKDAY(C56,2),"Monday","Tuesday","Wednesday","Thursday","Friday","Saturday","Sunday") -> Tuesday | E56: 45229.793 | F56: 45230 | G56: =Devblogs!AA2 -> 45212 | H56: =Devblogs!AB2 -> Friday | I56: =_xludf.DAYS(G56,C55) -> #NAME? | J56: =_xludf.DAYS(C56,G56) -> #NAME? | K56: =C56-'Dev servers'!C66 -> 11 | L56: =C56-C55 -> 42 | M56: =C56=F56 -> TRUE | N56: =OR(C56+1=F56,C56=F56+1) -> FALSE | O56: =OR(C56+2=F56,C56=F56+2) -> FALSE | P56: =OR(C56+3=F56,C56=F56+3) -> FALSE | Q56: =OR(C56+4=F56,C56=F56+4) -> FALSE | R56: =OR(C56+5=F56,C56=F56+5) -> FALSE | S56: =OR(C56+6=F56,C56=F56+6) -> FALSE | T56: =OR(C56+7=F56,C56=F56+7) -> FALSE | U56: =OR(C56+8<=F56,C56>=F56+8) -> FALSE | V56: =INT(E56) -> 45229 | W56: =E56-V56 -> 0.79305556 | X56: =C56-365*8-366*2 -> 41578 | Y56: =G56-365*8-366*2 -> 41560
A57: 2.33 | B57: Air Superiority | C57: 45274 | D57: =CHOOSE(WEEKDAY(C57,2),"Monday","Tuesday","Wednesday","Thursday","Friday","Saturday","Sunday") -> Thursday | E57: 45273.793 | F57: 45274 | G57: =Devblogs!X2 -> 45261 | H57: =Devblogs!Y2 -> Friday | I57: =_xludf.DAYS(G57,C56) -> #NAME? | J57: =_xludf.DAYS(C57,G57) -> #NAME? | K57: =C57-'Dev servers'!C67 -> 7 | L57: =C57-C56 -> 44 | M57: =C57=F57 -> TRUE | N57: =OR(C57+1=F57,C57=F57+1) -> FALSE | O57: =OR(C57+2=F57,C57=F57+2) -> FALSE | P57: =OR(C57+3=F57,C57=F57+3) -> FALSE | Q57: =OR(C57+4=F57,C57=F57+4) -> FALSE | R57: =OR(C57+5=F57,C57=F57+5) -> FALSE | S57: =OR(C57+6=F57,C57=F57+6) -> FALSE | T57: =OR(C57+7=F57,C57=F57+7) -> FALSE | U57: =OR(C57+8<=F57,C57>=F57+8) -> FALSE | V57: =INT(E57) -> 45273 | W57: =E57-V57 -> 0.79305556 | X57: =C57-365*8-366*2 -> 41622 | Y57: =G57-365*8-366*2 -> 41609
A58: 2.35 | B58: Alpha Strike | C58: 45364 | D58: =CHOOSE(WEEKDAY(C58,2),"Monday","Tuesday","Wednesday","Thursday","Friday","Saturday","Sunday") -> Wednesday | E58: 45363.796 | F58: 45363 | G58: =Devblogs!U2 -> 45344 | H58: =Devblogs!V2 -> Thursday | I58: =_xludf.DAYS(G58,C57) -> #NAME? | J58: =_xludf.DAYS(C58,G58) -> #NAME? | K58: =C58-'Dev servers'!C68 -> 12 | L58: =C58-C57 -> 90 | M58: =C58=F58 -> FALSE | N58: =OR(C58+1=F58,C58=F58+1) -> TRUE | O58: =OR(C58+2=F58,C58=F58+2) -> FALSE | P58: =OR(C58+3=F58,C58=F58+3) -> FALSE | Q58: =OR(C58+4=F58,C58=F58+4) -> FALSE | R58: =OR(C58+5=F58,C58=F58+5) -> FALSE | S58: =OR(C58+6=F58,C58=F58+6) -> FALSE | T58: =OR(C58+7=F58,C58=F58+7) -> FALSE | U58: =OR(C58+8<=F58,C58>=F58+8) -> FALSE | V58: =INT(E58) -> 45363 | W58: =E58-V58 -> 0.79583333 | X58: =C58-365*8-366*3 -> 41346 | Y58: =G58-365*9-366*2 -> 41327
A59: 2.37 | B59: Seek & Destroy | C59: 45462 | D59: =CHOOSE(WEEKDAY(C59,2),"Monday","Tuesday","Wednesday","Thursday","Friday","Saturday","Sunday") -> Wednesday | E59: 45461.792 | F59: 45447 | G59: =Devblogs!R2 -> 45436 | H59: =Devblogs!S2 -> Friday | I59: =_xludf.DAYS(G59,C58) -> #NAME? | J59: =_xludf.DAYS(C59,G59) -> #NAME? | K59: =C59-'Dev servers'!C69 -> 19 | L59: =C59-C58 -> 98 | M59: =C59=F59 -> FALSE | N59: =OR(C59+1=F59,C59=F59+1) -> FALSE | O59: =OR(C59+2=F59,C59=F59+2) -> FALSE | P59: =OR(C59+3=F59,C59=F59+3) -> FALSE | Q59: =OR(C59+4=F59,C59=F59+4) -> FALSE | R59: =OR(C59+5=F59,C59=F59+5) -> FALSE | S59: =OR(C59+6=F59,C59=F59+6) -> FALSE | T59: =OR(C59+7=F59,C59=F59+7) -> FALSE | U59: =OR(C59+8<=F59,C59>=F59+8) -> TRUE | V59: =INT(E59) -> 45461 | W59: =E59-V59 -> 0.79236111 | X59: =C59-365*8-366*3 -> 41444 | Y59: =G59-365*8-366*3 -> 41418
A60: 2.39 | B60: Dance of Dragons | C60: 45545 | D60: =CHOOSE(WEEKDAY(C60,2),"Monday","Tuesday","Wednesday","Thursday","Friday","Saturday","Sunday") -> Tuesday | E60: 45544.793 | F60: 45545 | G60: =Devblogs!O2 -> 45526 | H60: =Devblogs!P2 -> Thursday | I60: =_xludf.DAYS(G60,C59) -> #NAME? | J60: =_xludf.DAYS(C60,G60) -> #NAME? | K60: =C60-'Dev servers'!C70 -> 11 | L60: =C60-C59 -> 83 | M60: =C60=F60 -> TRUE | N60: =OR(C60+1=F60,C60=F60+1) -> FALSE | O60: =OR(C60+2=F60,C60=F60+2) -> FALSE | P60: =OR(C60+3=F60,C60=F60+3) -> FALSE | Q60: =OR(C60+4=F60,C60=F60+4) -> FALSE | R60: =OR(C60+5=F60,C60=F60+5) -> FALSE | S60: =OR(C60+6=F60,C60=F60+6) -> FALSE | T60: =OR(C60+7=F60,C60=F60+7) -> FALSE | U60: =OR(C60+8<=F60,C60>=F60+8) -> FALSE | V60: =INT(E60) -> 45544 | W60: =E60-V60 -> 0.79305556 | X60: =C60-365*8-366*3 -> 41527 | Y60: =G60-365*9-366*2 -> 41509
A61: 2.41 | B61: Firebirds | C61: 45615 | D61: =CHOOSE(WEEKDAY(C61,2),"Monday","Tuesday","Wednesday","Thursday","Friday","Saturday","Sunday") -> Tuesday | E61: 45614.794 | F61: 45601 | G61: =Devblogs!L2 -> 45580 | H61: =Devblogs!M2 -> Tuesday | I61: =_xludf.DAYS(G61,C60) -> #NAME? | J61: =_xludf.DAYS(C61,G61) -> #NAME? | K61: =C61-'Dev servers'!C71 -> 25 | L61: =C61-C60 -> 70 | M61: =C61=F61 -> FALSE | N61: =OR(C61+1=F61,C61=F61+1) -> FALSE | O61: =OR(C61+2=F61,C61=F61+2) -> FALSE | P61: =OR(C61+3=F61,C61=F61+3) -> FALSE | Q61: =OR(C61+4=F61,C61=F61+4) -> FALSE | R61: =OR(C61+5=F61,C61=F61+5) -> FALSE | S61: =OR(C61+6=F61,C61=F61+6) -> FALSE | T61: =OR(C61+7=F61,C61=F61+7) -> FALSE | U61: =OR(C61+8<=F61,C61>=F61+8) -> TRUE | V61: =INT(E61) -> 45614 | W61: =E61-V61 -> 0.79444444 | X61: =C61-365*8-366*3 -> 41597 | Y61: =G61-365*8-366*3 -> 41562
A62: 2.43 | B62: Storm Warning | C62: 45642 | D62: =CHOOSE(WEEKDAY(C62,2),"Monday","Tuesday","Wednesday","Thursday","Friday","Saturday","Sunday") -> Monday | E62: 45641.837 | F62: 45638 | G62: =Devblogs!I2 -> 45631 | H62: =Devblogs!J2 -> Thursday | I62: =_xludf.DAYS(G62,C61) -> #NAME? | J62: =_xludf.DAYS(C62,G62) -> #NAME? | K62: =C62-'Dev servers'!C72 -> 6 | L62: =C62-C61 -> 27 | M62: =C62=F62 -> FALSE | N62: =OR(C62+1=F62,C62=F62+1) -> FALSE | O62: =OR(C62+2=F62,C62=F62+2) -> FALSE | P62: =OR(C62+3=F62,C62=F62+3) -> FALSE | Q62: =OR(C62+4=F62,C62=F62+4) -> TRUE | R62: =OR(C62+5=F62,C62=F62+5) -> FALSE | S62: =OR(C62+6=F62,C62=F62+6) -> FALSE | T62: =OR(C62+7=F62,C62=F62+7) -> FALSE | U62: =OR(C62+8<=F62,C62>=F62+8) -> FALSE | V62: =INT(E62) -> 45641 | W62: =E62-V62 -> 0.83680556 | X62: =C62-365*8-366*3 -> 41624 | Y62: =G62-365*8-366*3 -> 41613
A63: 2.45 | G63: =Devblogs!F2 -> 45708 | H63: =Devblogs!G2 -> Thursday | I63: =_xludf.DAYS(G63,C62) -> #NAME? | M63: =C63=F63 -> TRUE | N63: =OR(C63+1=F63,C63=F63+1) -> FALSE | O63: =OR(C63+2=F63,C63=F63+2) -> FALSE | P63: =OR(C63+3=F63,C63=F63+3) -> FALSE | Q63: =OR(C63+4=F63,C63=F63+4) -> FALSE | R63: =OR(C63+5=F63,C63=F63+5) -> FALSE | S63: =OR(C63+6=F63,C63=F63+6) -> FALSE | T63: =OR(C63+7=F63,C63=F63+7) -> FALSE | U63: =OR(C63+8<=F63,C63>=F63+8) -> FALSE | V63: =INT(E63) -> 0 | W63: =E63-V63 -> 0 | X63: =C63-365*8-366*3 -> -4018 | Y63: =G63-365*8-366*3 -> 41690
B66: Release date day of week | F66: Predicted* announcement time: | H66: =FORECAST(E65,W5:W62,A5:A62) -> 0.79953328 | J66: Predicted* last dev server to release time: | L66: =FORECAST(K65,K18:K62,A18:A62) -> 16.395
B67: Monday: | C67: =COUNTIF(D3:D65,"Monday") -> 4 | D67: =C67/SUM($C$67:$C$73) -> 0.066666667
B68: Tuesday: | C68: =COUNTIF(D3:D65,"Tuesday") -> 25 | D68: =C68/SUM($C$67:$C$73) -> 0.41666667 | F68: Average first devblog date | J68: Predicted* first devblog date
B69: Wednesday: | C69: =COUNTIF(D3:D65,"Wednesday") -> 18 | D69: =C69/SUM($C$67:$C$73) -> 0.3 | F69: Feb-Mar updates | G69: =AVERAGE(Y13,Y18,Y23,Y28,Y33,Y38,Y43,Y48,Y53,Y58) -> 41316.8 | H69: =IF(M69>=0,M69,M69+365) -> #NAME? | J69: Feb-Mar updates | K69: =FORECAST(T79,O69:O78,T69:T78) -> 41327.933 | L69: =IF(N69>=0,N69,N69+365) -> #NAME? | M69: =_xludf.DAYS(G69,TODAY()-365*9-366*3) -> #NAME? | N69: =_xludf.DAYS(K69,TODAY()-365*9-366*3) -> #NAME? | O69: =Y13 -> 41307 | P69: =Y14 -> 41381 | Q69: =Y15 -> 41441 | R69: =Y16 -> 41491 | S69: =Y17 -> 41611 | T69: 2015
B70: Thursday: | C70: =COUNTIF(D3:D65,"Thursday") -> 12 | D70: =C70/SUM($C$67:$C$73) -> 0.2 | F70: May-Jun updates | G70: =AVERAGE(Y29,Y34,Y39,Y44,Y49,Y59) -> 41406.167 | H70: =IF(M70>=0,M70,M70+365) -> #NAME? | J70: May-Jun updates | K70: =FORECAST(T79,P71:P78,T71:T78) -> 41407.929 | L70: =IF(N70>=0,N70,N70+365) -> #NAME? | M70: =_xludf.DAYS(G70,TODAY()-365*9-366*3) -> #NAME? | N70: =_xludf.DAYS(K70,TODAY()-365*9-366*3) -> #NAME? | O70: =Y18 -> 41300 | P70: =Y19 -> 41356 | Q70: =Y20 -> 41461 | R70: =Y21 -> 41519 | S70: =Y22 -> 41588 | T70: 2016
B71: Friday: | C71: =COUNTIF(D3:D65,"Friday") -> 1 | D71: =C71/SUM($C$67:$C$73) -> 0.016666667 | F71: Aug-Sep updates | G71: =AVERAGE(Y25,Y30,Y35,Y40,Y45,Y50,Y55,Y60) -> 41504 | H71: =IF(M71>=0,M71,M71+365) -> #NAME? | J71: Aug-Sep updates | K71: =FORECAST(T79,Q71:Q78,T71:T78) -> 41506.571 | L71: =IF(N71>=0,N71,N71+365) -> #NAME? | M71: =_xludf.DAYS(G71,TODAY()-365*9-366*3) -> #NAME? | N71: =_xludf.DAYS(K71,TODAY()-365*9-366*3) -> #NAME? | O71: =Y23 -> 41319 | P71: =Y24 -> 41396 | Q71: =Y25 -> 41504 | R71: =Y26 -> 41558 | S71: =Y27 -> 41610 | T71: 2017
B72: Saturday: | C72: =COUNTIF(D3:D65,"Saturday") -> 0 | D72: =C72/SUM($C$67:$C$73) -> 0 | F72: Oct-Nov updates | G72: =AVERAGE(Y26,Y31,Y36,Y41,Y46,Y51,Y56) -> 41559 | H72: =IF(M72>=0,M72,M72+365) -> #NAME? | J72: Oct-Nov updates | K72: =FORECAST(T78,R71:R77,T71:T77) -> 41560.286 | L72: =IF(N72>=0,N72,N72+365) -> #NAME? | M72: =_xludf.DAYS(G72,TODAY()-365*9-366*3) -> #NAME? | N72: =_xludf.DAYS(K72,TODAY()-365*9-366*3) -> #NAME? | O72: =Y28 -> 41312 | P72: =Y29 -> 41405 | Q72: =Y30 -> 41507 | R72: =Y31 -> 41556 | S72: =Y32 -> 41601 | T72: 2018
B73: Sunday: | C73: =COUNTIF(D3:D65,"Sunday") -> 0 | D73: =C73/SUM($C$67:$C$73) -> 0 | F73: Dec updates | G73: =AVERAGE(Y17,Y22,Y27,Y32,Y37,Y42,Y47,Y52,Y57) -> 41606.111 | H73: =IF(M73>=0,M73,M73+365) -> #NAME? | J73: Dec updates | K73: =FORECAST(T78,S69:S77,T69:T77) -> 41611.028 | L73: =IF(N73>=0,N73,N73+365) -> #NAME? | M73: =_xludf.DAYS(G73,TODAY()-365*8-366*3) -> #NAME? | N73: =_xludf.DAYS(K73,TODAY()-365*8-366*3) -> #NAME? | O73: =Y33 -> 41320 | P73: =Y34 -> 41397 | Q73: =Y35 -> 41499 | R73: =Y36 -> 41558 | S73: =Y37 -> 41606 | T73: 2019
O74: =Y38 -> 41325 | P74: =Y39 -> 41399 | Q74: =Y40 -> 41500 | R74: =Y41 -> 41567 | S74: =Y42 -> 41615 | T74: 2020
B75: First devblog date day of week | F75: Average first devblog to release time | O75: =Y43 -> 41320 | P75: =Y44 -> 41406 | Q75: =Y45 -> 41504 | R75: =Y46 -> 41555 | S75: =Y47 -> 41608 | T75: 2021
B76: Monday: | C76: =COUNTIF(H3:H65,"Monday") -> 5 | D76: =C76/SUM($C$76:$C$82) -> 0.089285714 | F76: Feb-Mar updates | G76: =IF(M76>=0,M76,M76+365) -> #NAME? | M76: =AVERAGE(J13,J18,J23,J28,J33,J38,J43,J53,J58) -> #NAME? | O76: =Y48 -> 41323 | P76: =Y49 -> 41412 | Q76: =Y50 -> 41502 | R76: =Y51 -> 41559 | S76: =Y52 -> 41607 | T76: 2022
B77: Tuesday: | C77: =COUNTIF(H3:H65,"Tuesday") -> 13 | D77: =C77/SUM($C$76:$C$82) -> 0.23214286 | F77: May-Jun updates | G77: =IF(M77>=0,M77,M77+365) -> #NAME? | M77: =AVERAGE(J24,J29,J34,J39,J44,J49,J54,J59) -> #NAME? | O77: =Y53 -> 41315 | P77: =Y54 -> 41385 | Q77: =Y55 -> 41507 | R77: =Y56 -> 41560 | S77: =Y57 -> 41609 | T77: 2023
B78: Wednesday: | C78: =COUNTIF(H3:H65,"Wednesday") -> 10 | D78: =C78/SUM($C$76:$C$82) -> 0.17857143 | F78: Aug-Sep updates | G78: =IF(M78>=0,M78,M78+365) -> #NAME? | M78: =AVERAGE(J20,J25,J30,J35,J40,J45,J50,J55,J60) -> #NAME? | O78: =Y58 -> 41327 | P78: =Y59 -> 41418 | Q78: =Y60 -> 41509 | R78: =Y61 -> 41562 | S78: =Y62 -> 41613 | T78: 2024
B79: Thursday: | C79: =COUNTIF(H3:H65,"Thursday") -> 9 | D79: =C79/SUM($C$76:$C$82) -> 0.16071429 | F79: Oct-Nov updates | G79: =IF(M79>=0,M79,M79+365) -> #NAME? | M79: =AVERAGE(J21,J26,J31,J36,J41,J46,J51,J56,J61) -> #NAME? | T79: 2025
B80: Friday: | C80: =COUNTIF(H3:H65,"Friday") -> 18 | D80: =C80/SUM($C$76:$C$82) -> 0.32142857 | F80: Dec updates | G80: =IF(M80>=0,M80,M80+365) -> #NAME? | M80: =AVERAGE(J17,J27,J32,J37,J42,J47,J52,J57) -> #NAME?
B81: Saturday: | C81: =COUNTIF(H3:H65,"Saturday") -> 1 | D81: =C81/SUM($C$76:$C$82) -> 0.017857143
B82: Sunday: | C82: =COUNTIF(H3:H65,"Sunday") -> 0 | D82: =C82/SUM($C$76:$C$82) -> 0 | F82: Average release date | J82: Predicted* release date
F83: Feb-Mar updates | G83: =AVERAGE(X18,X23,X28,X33,X38,X43,X48,X53,X58) -> 41347.111 | H83: =IF(M83>=0,M83,M83+365) -> #NAME? | J83: Feb-Mar updates | K83: =FORECAST(T93,O84:O92,T84:T92) -> 41345.694 | L83: =IF(N83>=0,N83,N83+365) -> #NAME? | M83: =_xludf.DAYS(G83,TODAY()-365*9-366*3) -> #NAME? | N83: =_xludf.DAYS(K83,TODAY()-365*9-366*3) -> #NAME? | O83: =X13 -> 41329 | P83: =X14 -> 41394 | Q83: =X15 -> 41455 | R83: =X16 -> 41583 | S83: =X17 -> 41623 | T83: 2015
B84: Internal date in game files to release difference | F84: May-Jun updates | G84: =AVERAGE(X24,X29,X34,X39,X44,X49,X54,X59) -> 41431.125 | H84: =IF(M84>=0,M84,M84+365) -> #NAME? | J84: May-Jun updates | K84: =FORECAST(T93,P84:P92,T84:T92) -> 41440.611 | L84: =IF(N84>=0,N84,N84+365) -> #NAME? | M84: =_xludf.DAYS(G84,TODAY()-365*9-366*3) -> #NAME? | N84: =_xludf.DAYS(K84,TODAY()-365*9-366*3) -> #NAME? | O84: =X18 -> 41348 | P84: =X19 -> 41434 | Q84: =X20 -> 41489 | R84: =X21 -> 41546 | S84: =X22 -> 41628 | T84: 2016
B85: 0 day | C85: =COUNTIF(M25:M65,TRUE) -> 12 | D85: =C85/SUM($C$85:$C$93) -> 0.30769231 | F85: Aug-Sep updates | G85: =AVERAGE(X25,X30,X35,X40,X45,X50,X55,X60) -> 41529.5 | H85: =IF(M85>=0,M85,M85+365) -> #NAME? | J85: Aug-Sep updates | K85: =FORECAST(T93,Q85:Q92,T85:T92) -> 41527.25 | L85: =IF(N85>=0,N85,N85+365) -> #NAME? | M85: =_xludf.DAYS(G85,TODAY()-365*9-366*3) -> #NAME? | N85: =_xludf.DAYS(K85,TODAY()-365*9-366*3) -> #NAME? | O85: =X23 -> 41349 | P85: =X24 -> 41419 | Q85: =X25 -> 41535 | R85: =X26 -> 41579 | S85: =X27 -> 41627 | T85: 2017
B86: 1 days | C86: =COUNTIF(N25:N65,TRUE) -> 8 | D86: =C86/SUM($C$85:$C$93) -> 0.20512821 | F86: Oct-Nov updates | G86: =AVERAGE(X16,X21,X26,X31,X36,X41,X46,X51,X56) -> 41575 | H86: =IF(M86>=0,M86,M86+365) -> #NAME? | J86: Oct-Nov updates | K86: =FORECAST(T92,R83:R91,T83:T91) -> 41581.5 | L86: =IF(N86>=0,N86,N86+365) -> #NAME? | M86: =_xludf.DAYS(G86,TODAY()-365*9-366*3) -> #NAME? | N86: =_xludf.DAYS(K86,TODAY()-365*9-366*3) -> #NAME? | O86: =X28 -> 41347 | P86: =X29 -> 41437 | Q86: =X30 -> 41536 | R86: =X31 -> 41570 | S86: =X32 -> 41625 | T86: 2018
B87: 2 days | C87: =COUNTIF(O25:O65,TRUE) -> 4 | D87: =C87/SUM($C$85:$C$93) -> 0.1025641 | F87: Dec updates | G87: =AVERAGE(X8,X12,X17,X22,X27,X32,X37,X42,X47,X52,X57) -> 41625.091 | H87: =IF(M87>=0,M87,M87+365) -> #NAME? | J87: Dec updates | K87: =FORECAST(T92,S83:S91,T83:T91) -> 41624.028 | L87: =IF(N87>=0,N87,N87+365) -> #NAME? | M87: =_xludf.DAYS(G87,TODAY()-365*8-366*3) -> #NAME? | N87: =_xludf.DAYS(K87,TODAY()-365*8-366*3) -> #NAME? | O87: =X33 -> 41345 | P87: =X34 -> 41423 | Q87: =X35 -> 41528 | R87: =X36 -> 41576 | S87: =X37 -> 41625 | T87: 2019
B88: 3 days | C88: =COUNTIF(P25:P65,TRUE) -> 1 | D88: =C88/SUM($C$85:$C$93) -> 0.025641026 | O88: =X38 -> 41349 | P88: =X39 -> 41420 | Q88: =X40 -> 41519 | R88: =X41 -> 41595 | S88: =X42 -> 41626 | T88: 2020
B89: 4 days | C89: =COUNTIF(Q25:Q65,TRUE) -> 2 | D89: =C89/SUM($C$85:$C$93) -> 0.051282051 | F89: Average previous update release to first devblog time | O89: =X43 -> 41343 | P89: =X44 -> 41427 | Q89: =X45 -> 41524 | R89: =X46 -> 41575 | S89: =X47 -> 41622 | T89: 2021
B90: 5 days | C90: =COUNTIF(R25:R65,TRUE) -> 1 | D90: =C90/SUM($C$85:$C$93) -> 0.025641026 | F90: Feb-Mar updates | H90: =IF(M90>=0,M90,M90+365) -> #NAME? | M90: =AVERAGE(I23,I33,I38,I43,I48,I53,I58) -> #NAME? | O90: =X48 -> 41357 | P90: =X49 -> 41440 | Q90: =X50 -> 41531 | R90: =X51 -> 41573 | S90: =X52 -> 41628 | T90: 2022
B91: 6 days | C91: =COUNTIF(S25:S65,TRUE) -> 5 | D91: =C91/SUM($C$85:$C$93) -> 0.12820513 | F91: May-Jun updates | H91: =IF(M91>=0,M91,M91+365) -> #NAME? | M91: =AVERAGE(I14,I29,I34,I39,I44,I49,I54,I59) -> #NAME? | O91: =X53 -> 41340 | P91: =X54 -> 41439 | Q91: =X55 -> 41536 | R91: =X56 -> 41578 | S91: =X57 -> 41622 | T91: 2023
B92: 7 days | C92: =COUNTIF(T25:T65,TRUE) -> 0 | D92: =C92/SUM($C$85:$C$93) -> 0 | F92: Aug-Sep updates | H92: =IF(M92>=0,M92,M92+365) -> #NAME? | M92: =AVERAGE(I25,I30,I35,I40,I45,I50,I55,I60) -> #NAME? | O92: =X58 -> 41346 | P92: =X59 -> 41444 | Q92: =X60 -> 41527 | R92: =X61 -> 41597 | T92: 2024
B93: 7+ days | C93: =COUNTIF(U25:U65,TRUE) -> 6 | D93: =C93/SUM($C$85:$C$93) -> 0.15384615 | F93: Oct-Nov updates | H93: =IF(M93>=0,M93,M93+365) -> #NAME? | M93: =AVERAGE(I16,I21,I26,I31,I36,I41,I46,I51,I56,I61) -> #NAME? | T93: 2025
F94: Dec updates | H94: =IF(M94>=0,M94,M94+365) -> #NAME? | K94: *: with linear regression | M94: =AVERAGE(I17,I22,I27,I32,I37,I42,I47,I52,I57) -> #NAME?

Sheet Custom Loadouts
A1: Custom loadouts | C1: A-10A early | P1: A-10A late | AC1: MiG-23MLA | AJ1: Su-22UM3K | AU1: J8B | BE1: F-104S/ASA | BR1: Mirage F1 C | CB1: Kfir C.2
C2: max load – 7257 kg | J2: max imbalance – 1000 kg | P2: max load – 7257 kg | W2: max imbalance – 1000 kg | AC2: max load – 2000 kg | AG2: max imbalance – 500 kg | AJ2: max load – 3000 kg | AP2: max imbalance – 700 kg | AU2: max load – 4500 kg | AZ2: max imbalance – 1000 kg | BE2: max load – 3400 kg | BL2: max imbalance – 500 kg | BR2: max load – 3000 kg | BW2: max imbalance – 500 kg | CB2: max load – 4295 kg | CG2: max imbalance – 1100 kg
C3: max left load – 4500 kg | J3: max right load – 4500 kg | P3: max left load – 4500 kg | W3: max right load – 4500 kg | AC3: max left load – 500 kg | AG3: max right load – 500 kg | AJ3: max left load – 1500 kg | AP3: max right load – 1500 kg | AU3: max left load – 1500 kg | AZ3: max right load – 1500 kg | BE3: max left load – 2200 kg | BL3: max right load – 2200 kg | BR3: max left load – 1500 kg | BW3: max right load – 1500 kg | CB3: max left load – 1500 kg | CG3: max right load – 1500 kg
C4: slot | D4: 0 | E4: 1 | F4: 2 | G4: 3 | H4: 4 | I4: 5 | J4: 6 | K4: 7 | L4: 8 | M4: 9 | N4: 10 | P4: slot | Q4: 0 | R4: 1 | S4: 2 | T4: 3 | U4: 4 | V4: 5 | W4: 6 | X4: 7 | Y4: 8 | Z4: 9 | AA4: 10 | AC4: slot | AD4: 0 | AE4: 1 | AF4: 2 | AG4: 3 | AH4: 4 | AJ4: slot | AK4: 0 | AL4: 1 | AM4: 2 | AN4: 3 | AO4: 4 | AP4: 5 | AQ4: 6 | AR4: 7 | AS4: 8 | AU4: slot | AV4: 0 | AW4: 1 | AX4: 2 | AY4: 3 | AZ4: 4 | BA4: 5 | BB4: 6 | BC4: 7 | BE4: slot | BF4: 0 | BG4: 1 | BH4: 2 | BI4: 3 | BJ4: 4 | BK4: 5 | BL4: 6 | BM4: 7 | BN4: 8 | BO4: 9 | BP4: 10 | BR4: slot | BS4: 0 | BT4: 1 | BU4: 2 | BV4: 3 | BW4: 4 | BX4: 5 | BY4: 6 | BZ4: 7 | CB4: slot | CC4: 0 | CD4: 1 | CE4: 2 | CF4: 3 | CG4: 4 | CH4: 5 | CI4: 6 | CJ4: 7
A5: List of aircraft: | C5: exempt from imbalance calculations? | D5: Yes | H5: Yes | I5: Yes | J5: Yes | K5: Yes | P5: exempt from imbalance calculations? | Q5: Yes | U5: Yes | V5: Yes | W5: Yes | X5: Yes | AC5: exempt from imbalance calculations? | AD5: Yes | AF5: Yes | AG5: Yes | AJ5: exempt from imbalance calculations? | AK5: Yes | AO5: Yes | AP5: Yes | AU5: exempt from imbalance calculations? | AV5: Yes | AZ5: Yes | BE5: exempt from imbalance calculations? | BF5: Yes | BJ5: Yes | BK5: Yes | BL5: Yes | BM5: Yes | BR5: exempt from imbalance calculations? | BS5: Yes | BW5: Yes | CB5: exempt from imbalance calculations? | CC5: Yes
A6: US | C6: Cannons | D6: GAU-8/A | P6: Cannons | Q6: GAU-8/A | AC6: Cannons | AD6: GSh-23L | AE6: GSh-23L | AH6: GSh-23L | AJ6: Cannons | AK6: NR-30 | AU6: Cannons | AV6: Model 23-3 | BE6: Cannons and missile control systems (AAMs in bold require this) | BF6: empty | BK6: M61 | BR6: Cannons | BS6: DEFA 553 | BV6: DEFA 553 | BX6: DEFA 553 | CB6: Cannons | CC6: DEFA 552A
A7: A-10A early | D7: (866 kg) | Q7: (866 kg) | AD7: (155 kg) | AE7: (155 kg) | AH7: (155 kg) | AK7: (66.5 kg) | AV7: (155 kg) | BK7: (650 kg) | BS7: (150 kg) | BV7: (150 kg) | BX7: (150 kg) | CC7: (150 kg)
A8: A-10A late | D8: GAU-8/A + CM | Q8: GAU-8/A + CM | AD8: GSh-23L + CM | AK8: NR-30 + CM | AV8: Model 23-3 + CM | BF8: CM | BS8: DEFA 553 + CM | CC8: DEFA 552A + CM
A9: F-4C | D9: (866 kg) | Q9: (866 kg) | AD9: (155 kg) | AK9: (66.5 kg) | AV9: (155 kg) | BK9: Aspide control | BS9: (150 kg) | CC9: (150 kg)
A10: F-4E | I10: M61 | J10: M61 | P10: Rockets | S10: 7x Hydra 70 (M247) | T10: 7x Hydra 70 (M247) | U10: 7x Hydra 70 (M247) | X10: 7x Hydra 70 (M247) | Y10: 7x Hydra 70 (M247) | Z10: 7x Hydra 70 (M247) | AC10: Rockets | AE10: 16x S-5K | AF10: 16x S-5K | AG10: 16x S-5K | AH10: 16x S-5K | AN10: GSh-23L | AQ10: GSh-23L | AU10: Rockets | AW10: 7x Model 90-1 HEAT | AX10: 7x Model 90-1 HEAT | BB10: 7x Model 90-1 HEAT | BC10: 7x Model 90-1 HEAT | BK10: (20 kg) | BR10: Rockets | BU10: 18x SNEB Type 23 | BV10: 18x SNEB Type 23 | BX10: 18x SNEB Type 23 | BY10: 18x SNEB Type 23 | CE10: M61 | CI10: M61
A11: F-4J | I11: (650 kg) | J11: (650 kg) | S11: (71.12 kg) | T11: (71.12 kg) | U11: (71.12 kg) | X11: (71.12 kg) | Y11: (71.12 kg) | Z11: (71.12 kg) | AE11: (58.24 kg) | AF11: (58.24 kg) | AG11: (58.24 kg) | AH11: (58.24 kg) | AN11: (155 kg) | AQ11: (155 kg) | AW11: (102.2 kg) | AX11: (102.2 kg) | BB11: (102.2 kg) | BC11: (102.2 kg) | BE11: Rockets | BH11: 19x 2.75-inch FFAR Mk. 4 | BI11: 19x 2.75-inch FFAR Mk. 4 | BN11: 19x 2.75-inch FFAR Mk. 4 | BO11: 19x 2.75-inch FFAR Mk. 4 | BU11: (90.9 kg) | BV11: (90.9 kg) | BX11: (90.9 kg) | BY11: (90.9 kg) | CE11: (650 kg) | CI11: (650 kg)
A12: F-14A (early) | C12: Rockets | F12: 7x Hydra 70 (M247) | G12: 7x Hydra 70 (M247) | H12: 7x Hydra 70 (M247) | K12: 7x Hydra 70 (M247) | L12: 7x Hydra 70 (M247) | M12: 7x Hydra 70 (M247) | T12: 21x Hydra 70 (M247) | U12: 21x Hydra 70 (M247) | X12: 21x Hydra 70 (M247) | Y12: 21x Hydra 70 (M247) | AE12: 32x S-5K | AH12: 32x S-5K | AJ12: Rockets | AL12: 7x S-3K | AO12: 7x S-3K | AP12: 7x S-3K | AS12: 7x S-3K | AU12: Bombs | AX12: 1x 500 lbs Mk. 82 | BB12: 1x 500 lbs Mk. 82 | BH12: (154.28 kg) | BI12: (154.28 kg) | BN12: (154.28 kg) | BO12: (154.28 kg) | BU12: 36x SNEB Type 23 | BV12: 36x SNEB Type 23 | BX12: 36x SNEB Type 23 | BY12: 36x SNEB Type 23 | CB12: Rockets | CE12: 38x 2.75-inch FFAR Mk. 4 | CI12: 38x 2.75-inch FFAR Mk. 4
F13: (71.12 kg) | G13: (71.12 kg) | H13: (71.12 kg) | K13: (71.12 kg) | L13: (71.12 kg) | M13: (71.12 kg) | T13: (213.36 kg) | U13: (213.36 kg) | X13: (213.36 kg) | Y13: (213.36 kg) | AE13: (116.48 kg) | AH13: (116.48 kg) | AL13: (164.5 kg) | AO13: (164.5 kg) | AP13: (164.5 kg) | AS13: (164.5 kg) | AX13: (240.9 kg) | BB13: (240.9 kg) | BH13: 4x 5-inch FFAR Mk. 32 Mod. 0 | BO13: 4x 5-inch FFAR Mk. 32 Mod. 0 | BU13: (181.8 kg) | BV13: (181.8 kg) | BX13: (181.8 kg) | BY13: (181.8 kg) | CE13: (308.56 kg) | CI13: (308.56 kg)
A14: GER | G14: 21x Hydra 70 (M247) | H14: 21x Hydra 70 (M247) | K14: 21x Hydra 70 (M247) | L14: 21x Hydra 70 (M247) | P14: Bombs | R14: 1x 500 lbs Mk. 82 | S14: 1x 500 lbs Mk. 82 | T14: 1x 500 lbs Mk. 82 | U14: 1x 500 lbs Mk. 82 | V14: 1x 500 lbs Mk. 82 | W14: 1x 500 lbs Mk. 82 | X14: 1x 500 lbs Mk. 82 | Y14: 1x 500 lbs Mk. 82 | Z14: 1x 500 lbs Mk. 82 | AA14: 1x 500 lbs Mk. 82 | AE14: 20x S-8KO | AH14: 20x S-8KO | AL14: 32x S-5K | AN14: 32x S-5K | AQ14: 32x S-5K | AS14: 32x S-5K | AZ14: 6x 500 lbs Mk. 82 | BH14: (227.2 kg) | BO14: (227.2 kg) | BR14: Bombs | BU14: 1x 250 kg SAMP Type 25 | BV14: 1x 250 kg SAMP Type 25 | BW14: 1x 250 kg SAMP Type 25 | BX14: 1x 250 kg SAMP Type 25 | BY14: 1x 250 kg SAMP Type 25 | CE14: 8x 5-inch FFAR Mk. 32 Mod. 0 | CI14: 8x 5-inch FFAR Mk. 32 Mod. 0
A15: F-4F (early) | G15: (213.36 kg) | H15: (213.36 kg) | K15: (213.36 kg) | L15: (213.36 kg) | R15: (240.9 kg) | S15: (240.9 kg) | T15: (240.9 kg) | U15: (240.9 kg) | V15: (240.9 kg) | W15: (240.9 kg) | X15: (240.9 kg) | Y15: (240.9 kg) | Z15: (240.9 kg) | AA15: (240.9 kg) | AE15: (226 kg) | AH15: (226 kg) | AL15: (116.48 kg) | AN15: (116.48 kg) | AQ15: (116.48 kg) | AS15: (116.48 kg) | AZ15: (1445.4 kg) | BE15: Bombs | BH15: 1x 500 lbs Mk. 82 | BI15: 1x 500 lbs Mk. 82 | BJ15: 1x 500 lbs Mk. 82 | BM15: 1x 500 lbs Mk. 82 | BN15: 1x 500 lbs Mk. 82 | BO15: 1x 500 lbs Mk. 82 | BU15: (247 kg) | BV15: (247 kg) | BW15: (247 kg) | BX15: (247 kg) | BY15: (247 kg) | CE15: (454.4 kg) | CI15: (454.4 kg)
A16: F-4F (late) | C16: Bombs | E16: 1x 500 lbs Mk. 82 | F16: 1x 500 lbs Mk. 82 | G16: 1x 500 lbs Mk. 82 | H16: 1x 500 lbs Mk. 82 | I16: 1x 500 lbs Mk. 82 | J16: 1x 500 lbs Mk. 82 | K16: 1x 500 lbs Mk. 82 | L16: 1x 500 lbs Mk. 82 | M16: 1x 500 lbs Mk. 82 | N16: 1x 500 lbs Mk. 82 | T16: 3x 500 lbs Mk. 82 | U16: 3x 500 lbs Mk. 82 | X16: 3x 500 lbs Mk. 82 | Y16: 3x 500 lbs Mk. 82 | AE16: 1x S-24B | AF16: 1x S-24B | AG16: 1x S-24B | AH16: 1x S-24B | AL16: 20x S-8KO | AN16: 20x S-8KO | AQ16: 20x S-8KO | AS16: 20x S-8KO | AU16: AAM | AX16: 1x PL5B | AY16: 1x PL5B (stock) | BA16: 1x PL5B (stock) | BB16: 1x PL5B | BH16: (240.9 kg) | BI16: (240.9 kg) | BJ16: (240.9 kg) | BM16: (240.9 kg) | BN16: (240.9 kg) | BO16: (240.9 kg) | BU16: 1x 500 lbs Mk. 82 | BV16: 1x 500 lbs Mk. 82 | BW16: 1x 500 lbs Mk. 82 | BX16: 1x 500 lbs Mk. 82 | BY16: 1x 500 lbs Mk. 82 | CB16: Bombs | CE16: 2x 500 lbs Mk. 82 | CF16: 2x 500 lbs Mk. 82 | CH16: 2x 500 lbs Mk. 82 | CI16: 2x 500 lbs Mk. 82
A17: MiG-23MF | E17: (240.9 kg) | F17: (240.9 kg) | G17: (240.9 kg) | H17: (240.9 kg) | I17: (240.9 kg) | J17: (240.9 kg) | K17: (240.9 kg) | L17: (240.9 kg) | M17: (240.9 kg) | N17: (240.9 kg) | T17: (722.7 kg) | U17: (722.7 kg) | X17: (722.7 kg) | Y17: (722.7 kg) | AE17: (235 kg) | AF17: (235 kg) | AG17: (235 kg) | AH17: (235 kg) | AL17: (226 kg) | AN17: (226 kg) | AQ17: (226 kg) | AS17: (226 kg) | AX17: (84 kg) | AY17: (84 kg) | BA17: (84 kg) | BB17: (84 kg) | BH17: 1x 750 lbs M117 | BI17: 1x 750 lbs M117 | BJ17: 1x 750 lbs M117 | BM17: 1x 750 lbs M117 | BN17: 1x 750 lbs M117 | BO17: 1x 750 lbs M117 | BU17: (250 kg) | BV17: (250 kg) | BW17: (250 kg) | BX17: (250 kg) | BY17: (250 kg) | CE17: (481.8 kg) | CF17: (481.8 kg) | CH17: (481.8 kg) | CI17: (481.8 kg)
A18: MiG-23MLA | G18: 3x 500 lbs Mk. 82 | H18: 3x 500 lbs Mk. 82 | K18: 3x 500 lbs Mk. 82 | L18: 3x 500 lbs Mk. 82 | T18: 1x 2000 lbs Mk. 84 | U18: 1x 2000 lbs Mk. 84 | V18: 1x 2000 lbs Mk. 84 | W18: 1x 2000 lbs Mk. 84 | X18: 1x 2000 lbs Mk. 84 | Y18: 1x 2000 lbs Mk. 84 | AC18: Bombs | AE18: 4x 100 kg OFAB-100-120 | AF18: 4x 100 kg OFAB-100-120 | AG18: 4x 100 kg OFAB-100-120 | AH18: 4x 100 kg OFAB-100-120 | AL18: 1x S-24B | AN18: 1x S-24B | AO18: 1x S-24B | AP18: 1x S-24B | AQ18: 1x S-24B | AS18: 1x S-24B | AX18: 1x Aspide-1A | BB18: 1x Aspide-1A | BH18: (362.42 kg) | BI18: (362.42 kg) | BJ18: (362.42 kg) | BM18: (362.42 kg) | BN18: (362.42 kg) | BO18: (362.42 kg) | BU18: 1x 400 kg SAMP Type 21 | BV18: 1x 400 kg SAMP Type 21 | BW18: 1x 400 kg SAMP Type 21 | BX18: 1x 400 kg SAMP Type 21 | BY18: 1x 400 kg SAMP Type 21 | CE18: 3x 500 lbs Mk. 82 | CI18: 3x 500 lbs Mk. 82
A19: Su-22UM3K | G19: (722.7 kg) | H19: (722.7 kg) | K19: (722.7 kg) | L19: (722.7 kg) | T19: (893.6 kg) | U19: (893.6 kg) | V19: (893.6 kg) | W19: (893.6 kg) | X19: (893.6 kg) | Y19: (893.6 kg) | AE19: (456 kg) | AF19: (456 kg) | AG19: (456 kg) | AH19: (456 kg) | AL19: (235 kg) | AN19: (235 kg) | AO19: (235 kg) | AP19: (235 kg) | AQ19: (235 kg) | AS19: (235 kg) | AX19: (230 kg) | BB19: (230 kg) | BI19: 1x 1000 lbs Mk. 83 | BN19: 1x 1000 lbs Mk. 83 | BU19: (400 kg) | BV19: (400 kg) | BW19: (400 kg) | BX19: (400 kg) | BY19: (400 kg) | CE19: (722.7 kg) | CI19: (722.7 kg)
G20: 1x 2000 lbs Mk. 84 | H20: 1x 2000 lbs Mk. 84 | I20: 1x 2000 lbs Mk. 84 | J20: 1x 2000 lbs Mk. 84 | K20: 1x 2000 lbs Mk. 84 | L20: 1x 2000 lbs Mk. 84 | P20: AGM | T20: 3x AGM-65D | Y20: 3x AGM-65D | AE20: 1x 250 kg FAB-250-M62 | AF20: 1x 250 kg FAB-250-M62 | AG20: 1x 250 kg FAB-250-M62 | AH20: 1x 250 kg FAB-250-M62 | AL20: 1x S-25O | AS20: 1x S-25O | BI20: (446.8 kg) | BN20: (446.8 kg) | BU20: 1x 1000 lbs Mk. 83 | BV20: 1x 1000 lbs Mk. 83 | BW20: 1x 1000 lbs Mk. 83 | BX20: 1x 1000 lbs Mk. 83 | BY20: 1x 1000 lbs Mk. 83 | CG20: 5x 500 lbs Mk. 82
A21: USSR | G21: (893.6 kg) | H21: (893.6 kg) | I21: (893.6 kg) | J21: (893.6 kg) | K21: (893.6 kg) | L21: (893.6 kg) | T21: (680.4 kg) | Y21: (680.4 kg) | AE21: (227 kg) | AF21: (227 kg) | AG21: (227 kg) | AH21: (227 kg) | AL21: (370 kg) | AS21: (370 kg) | BL21: 1x 2000 lbs Mk. 84 | BU21: (500 kg) | BV21: (500 kg) | BW21: (500 kg) | BX21: (500 kg) | BY21: (500 kg) | CG21: (1204.5 kg)
A22: MiG-23M | C22: GBU | G22: 1x GBU-8/B | H22: 1x GBU-8/B | K22: 1x GBU-8/B | L22: 1x GBU-8/B | P22: AAM | R22: 1x AIM-9L (stock) | AA22: 1x AIM-9L (stock) | AE22: 1x 500 kg FAB-500-M62 | AH22: 1x 500 kg FAB-500-M62 | AJ22: Bombs | AN22: 1x 100 kg OFAB-100-120 | AQ22: 1x 100 kg OFAB-100-120 | BL22: (893.6 kg) | BV22: 1x 2000 lbs Mk. 84 | BW22: 1x 2000 lbs Mk. 84 | BX22: 1x 2000 lbs Mk. 84 | CE22: 2x 750 lbs M117 | CF22: 2x 750 lbs M117 | CH22: 2x 750 lbs M117 | CI22: 2x 750 lbs M117
A23: MiG-23MLD | G23: (1027 kg) | H23: (1027 kg) | K23: (1027 kg) | L23: (1027 kg) | R23: (84.46 kg) | AA23: (84.46 kg) | AE23: (508.3 kg) | AH23: (508.3 kg) | AN23: (114 kg) | AQ23: (114 kg) | BE23: AAM | BG23: 1x AIM-9L (stock) | BH23: 1x AIM-9L | BO23: 1x AIM-9L | BP23: 1x AIM-9L (stock) | BV23: (1000 kg) | BW23: (1000 kg) | BX23: (1000 kg) | CE23: (724.84 kg) | CF23: (724.84 kg) | CH23: (724.84 kg) | CI23: (724.84 kg)
A24: MiG-27K | C24: AGM | G24: 3x AGM-65B | L24: 3x AGM-65B | R24: 2x AIM-9L | AA24: 2x AIM-9L | AC24: TGP (AGMs in bold require this) | AG24: 1x Delta-NG | AO24: 4x 100 kg OFAB-100-120 | AP24: 4x 100 kg OFAB-100-120 | BG24: (84.46 kg) | BH24: (84.46 kg) | BO24: (84.46 kg) | BP24: (84.46 kg) | BR24: AAM | BV24: 1x R530E | BW24: 1x R530E | BX24: 1x R530E | CE24: 2x 1000 lbs Mk. 83 | CF24: 2x 1000 lbs Mk. 83 | CH24: 2x 1000 lbs Mk. 83 | CI24: 2x 1000 lbs Mk. 83
A25: MiG-27M | G25: (621 kg) | L25: (621 kg) | R25: (168.92 kg) | AA25: (168.92 kg) | AG25: (20 kg) | AO25: (456 kg) | AP25: (456 kg) | BH25: 1x Aspide-1A | BO25: 1x Aspide-1A | BV25: (193.5 kg) | BW25: (193.5 kg) | BX25: (193.5 kg) | CE25: (893.6 kg) | CF25: (893.6 kg) | CH25: (893.6 kg) | CI25: (893.6 kg)
A26: Su-17M4 | C26: AAM | E26: 1x AIM-9L | N26: 1x AIM-9L | AC26: AGM | AE26: 1x Kh-23M | AF26: 1x R-13M1 | AG26: 1x R-13M1 | AH26: 1x Kh-23M | AL26: 5x 100 kg OFAB-100-120 | AS26: 5x 100 kg OFAB-100-120 | BH26: (230 kg) | BO26: (230 kg) | BT26: 1x R550 Magic 1 (stock) | BZ26: 1x R550 Magic 1 (stock) | CE26: 1x 2000 lbs Mk. 84 | CI26: 1x 2000 lbs Mk. 84
E27: (84.46 kg) | N27: (84.46 kg) | AE27: (289 kg) | AH27: (289 kg) | AL27: (570 kg) | AS27: (570 kg) | BT27: (89 kg) | BZ27: (89 kg) | CE27: (893.6 kg) | CI27: (893.6 kg)
A28: UK | AC28: AAM | AE28: 1x R-13M1 (stock) | AF28: 1x R-13M1 | AG28: 1x R-13M1 | AH28: 1x R-13M1 (stock) | AL28: 1x 250 kg OFAB-250sv | AN28: 1x 250 kg OFAB-250sv | AQ28: 1x 250 kg OFAB-250sv | AS28: 1x 250 kg OFAB-250sv | BT28: 1x R550 Magic 2 | BZ28: 1x R550 Magic 2 | CB28: AAM | CD28: 1x Shafrir 2 (stock) | CJ28: 1x Shafrir 2 (stock)
A29: Phantom FG. 1 | AE29: (90.6 kg) | AF29: (90.6 kg) | AG29: (90.6 kg) | AH29: (90.6 kg) | AL29: (250 kg) | AN29: (250 kg) | AQ29: (250 kg) | AS29: (250 kg) | BT29: (89 kg) | BZ29: (89 kg) | CD29: (93 kg) | CJ29: (93 kg)
A30: Phantom FGR. 2 | AE30: 1x R-60 | AF30: 2x R-60 | AG30: 2x R-60 | AH30: 1x R-60 | AO30: 3x 250 kg OFAB-250sv | AP30: 3x 250 kg OFAB-250sv | BV30: 1x R530 | BW30: 1x R530 | BX30: 1x R530 | CD30: 1x AIM-9D (stock) | CJ30: 1x AIM-9D (stock)
AE31: (44 kg) | AF31: (88 kg) | AG31: (88 kg) | AH31: (44 kg) | AO31: (750 kg) | AP31: (750 kg) | BV31: (193.5 kg) | BW31: (193.5 kg) | BX31: (193.5 kg) | CD31: (88.45 kg) | CJ31: (88.45 kg)
A32: JP | AE32: 1x R-23R | AH32: 1x R-23R | AL32: 1x 500 kg FAB-500-M62 | AS32: 1x 500 kg FAB-500-M62 | BV32: 1x Super 530F | BX32: 1x Super 530F | CD32: 1x AIM-9G | CJ32: 1x AIM-9G
A33: F-4EJ | AE33: (223 kg) | AH33: (223 kg) | AL33: (508.3 kg) | AS33: (508.3 kg) | BV33: (245 kg) | BX33: (245 kg) | CD33: (88.45 kg) | CJ33: (88.45 kg)
A34: F-4EJ Kai | AE34: 1x R-23T | AH34: 1x R-23T | AO34: 2x 500 kg FAB-500-M62 | AP34: 2x 500 kg FAB-500-M62
AE35: (215 kg) | AH35: (215 kg) | AO35: (1016.6 kg) | AP35: (1016.6 kg)
A36: CN | AE36: 1x R-24R | AH36: 1x R-24R | AJ36: TGP (AGMs in bold require this) | AQ36: 1x Delta-NG
A37: J8B | AE37: (244 kg) | AH37: (244 kg) | AQ37: (20 kg)
AE38: 1x R-24T | AH38: 1x R-24T | AJ38: AGM | AL38: 1x S-25L | AS38: 1x S-25L
A39: IT | AE39: (237 kg) | AH39: (237 kg) | AL39: (410 kg) | AS39: (410 kg)
A40: F-104S/ASA | AL40: 1x Kh-23M | AS40: 1x Kh-23M
AL41: (289 kg) | AS41: (289 kg)
A42: FR | AL42: 1x Kh-25ML | AO42: 1x Kh-25ML | AP42: 1x Kh-25ML | AS42: 1x Kh-25ML
A43: Milan 01 | AL43: (297 kg) | AO43: (297 kg) | AP43: (297 kg) | AS43: (297 kg)
A44: Mirage F1 C | AO44: 1x Kh-29L | AP44: 1x Kh-29L
AO45: (657 kg) | AP45: (657 kg)
A46: SWE | AJ46: AAM | AM46: 1x R-60 (stock) | AR46: 1x R-60 (stock)
AM47: (44 kg) | AR47: (44 kg)
A48: ISR | AN48: 2x R-60 | AQ48: 2x R-60
A49: Kfir C.2 | AN49: (88 kg) | AQ49: (88 kg)

Sheet Leaks
A1: Leaks
A2: Version | B2: Name | C2: Date | D2: Day | E2: First devblog to leak | F2: Leak to release | G2: Image links
A3: =Updates!A55 -> 2.29 | B3: =Updates!B55 -> Sons of Attila | C3: 45160 | D3: =CHOOSE(WEEKDAY(C3,2),"Monday","Tuesday","Wednesday","Thursday","Friday","Saturday","Sunday") -> Tuesday | E3: =_xludf.DAYS(C3,Devblogs!AD2) -> #NAME? | F3: =_xludf.DAYS(Updates!C55,C3) -> #NAME? | G3: [Image]
A4: =Updates!A56 -> 2.31 | B4: =Updates!B56 -> Kings of Battle | C4: 45209 | D4: =CHOOSE(WEEKDAY(C4,2),"Monday","Tuesday","Wednesday","Thursday","Friday","Saturday","Sunday") -> Tuesday | E4: =_xludf.DAYS(C4,Devblogs!AA2) -> #NAME? | F4: =_xludf.DAYS(Updates!C56,C4) -> #NAME? | G4: [Image]
A5: =Updates!A57 -> 2.33 | B5: =Updates!B57 -> Air Superiority | C5: 45254 | D5: =CHOOSE(WEEKDAY(C5,2),"Monday","Tuesday","Wednesday","Thursday","Friday","Saturday","Sunday") -> Friday | E5: =_xludf.DAYS(C5,Devblogs!X2) -> #NAME? | F5: =_xludf.DAYS(Updates!C57,C5) -> #NAME? | G5: [Image]
A6: =Updates!A58 -> 2.35 | B6: =Updates!B58 -> Alpha Strike | C6: 45344 | D6: =CHOOSE(WEEKDAY(C6,2),"Monday","Tuesday","Wednesday","Thursday","Friday","Saturday","Sunday") -> Thursday | E6: =_xludf.DAYS(C6,Devblogs!U2) -> #NAME? | F6: =_xludf.DAYS(Updates!C58,C6) -> #NAME? | G6: [Image]
A7: =Updates!A59 -> 2.37 | B7: =Updates!B59 -> Seek & Destroy | C7: 45416 | D7: =CHOOSE(WEEKDAY(C7,2),"Monday","Tuesday","Wednesday","Thursday","Friday","Saturday","Sunday") -> Saturday | E7: =_xludf.DAYS(C7,Devblogs!R2) -> #NAME? | F7: =_xludf.DAYS(Updates!C59,C7) -> #NAME? | G7: [Image]
A8: =Updates!A60 -> 2.39 | B8: =Updates!B60 -> Dance of Dragons | C8: 45515 | D8: =CHOOSE(WEEKDAY(C8,2),"Monday","Tuesday","Wednesday","Thursday","Friday","Saturday","Sunday") -> Sunday | E8: =_xludf.DAYS(C8,Devblogs!O2) -> #NAME? | F8: =_xludf.DAYS(Updates!C60,C8) -> #NAME? | G8: [Image]
A9: =Updates!A61 -> 2.41 | B9: =Updates!B61 -> Firebirds | C9: 45583 | D9: =CHOOSE(WEEKDAY(C9,2),"Monday","Tuesday","Wednesday","Thursday","Friday","Saturday","Sunday") -> Friday | E9: =_xludf.DAYS(C9,Devblogs!L2) -> #NAME? | F9: =IF(_xludf.DAYS(Updates!C61,C9)>-1,_xludf.DAYS(Updates!C61,C9),0) -> #NAME? | G9: [Image]
A10: =Updates!A62 -> 2.43 | B10: =Updates!B62 -> Storm Warning | C10: 45623 | D10: =CHOOSE(WEEKDAY(C10,2),"Monday","Tuesday","Wednesday","Thursday","Friday","Saturday","Sunday") -> Wednesday | E10: =_xludf.DAYS(C10,Devblogs!I2) -> #NAME? | F10: =IF(_xludf.DAYS(Updates!C62,C10)>-1,_xludf.DAYS(Updates!C62,C10),0) -> #NAME? | G10: [Image]
A11: =Updates!A63 -> 2.45 | B11: =Updates!B63 -> 0 | C11: 45708 | D11: =CHOOSE(WEEKDAY(C11,2),"Monday","Tuesday","Wednesday","Thursday","Friday","Saturday","Sunday") -> Thursday | E11: =_xludf.DAYS(C11,Devblogs!F2) -> #NAME? | F11: =IF(_xludf.DAYS(Updates!C63,C11)>-1,_xludf.DAYS(Updates!C63,C11),0) -> #NAME? | G11: [Image]

Sheet Teasers
A1: Teasers
A2: Version | B2: Name | C2: Date | D2: Time (UTC) | E2: Day | F2: First devblog to teaser | G2: Number of devblogs until teaser*
A3: =Updates!A41 -> 2.1 | B3: =Updates!B41 -> New Power | C3: 44127 | D3: 0.54166667 | E3: =CHOOSE(WEEKDAY(C3,2),"Monday","Tuesday","Wednesday","Thursday","Friday","Saturday","Sunday") -> Friday | F3: =_xludf.DAYS(C3,Devblogs!BT2) -> #NAME? | G3: =IF(COUNTIF(Devblogs!BT2:BT45,"<"&C3)=COUNTIF(Devblogs!BT2:BT45,"<="&C3),COUNTIF(Devblogs!BT2:BT45,"<"&C3),CONCATENATE(COUNTIF(Devblogs!BT2:BT45,"<"&C3), " - ",COUNTIF(Devblogs!BT2:BT45,"<="&C3))) -> 3
A4: =Updates!A43 -> 2.5 | B4: =Updates!B43 -> Ixwa Strike | C4: 44245 | D4: 0.625 | E4: =CHOOSE(WEEKDAY(C4,2),"Monday","Tuesday","Wednesday","Thursday","Friday","Saturday","Sunday") -> Thursday | F4: =_xludf.DAYS(C4,Devblogs!BN2) -> #NAME? | G4: =IF(COUNTIF(Devblogs!BN2:BN45,"<"&C4)=COUNTIF(Devblogs!BN2:BN45,"<="&C4),COUNTIF(Devblogs!BN2:BN45,"<"&C4),CONCATENATE(COUNTIF(Devblogs!BN2:BN45,"<"&C4), " - ",COUNTIF(Devblogs!BN2:BN45,"<="&C4))) -> 3 - 5
A5: =Updates!A44 -> 2.7 | B5: =Updates!B44 -> Red Skies | C5: 44336 | D5: 0.58333333 | E5: =CHOOSE(WEEKDAY(C5,2),"Monday","Tuesday","Wednesday","Thursday","Friday","Saturday","Sunday") -> Thursday | F5: =_xludf.DAYS(C5,Devblogs!BK2) -> #NAME? | G5: =IF(COUNTIF(Devblogs!BK2:BK45,"<"&C5)=COUNTIF(Devblogs!BK2:BK45,"<="&C5),COUNTIF(Devblogs!BK2:BK45,"<"&C5),CONCATENATE(COUNTIF(Devblogs!BK2:BK45,"<"&C5), " - ",COUNTIF(Devblogs!BK2:BK45,"<="&C5))) -> 5 - 6
A6: =Updates!A45 -> 2.9 | B6: =Updates!B45 -> Direct Hit | C6: 44432 | D6: 0.75 | E6: =CHOOSE(WEEKDAY(C6,2),"Monday","Tuesday","Wednesday","Thursday","Friday","Saturday","Sunday") -> Tuesday | F6: =_xludf.DAYS(C6,Devblogs!BH2) -> #NAME? | G6: =IF(COUNTIF(Devblogs!BH2:BH45,"<"&C6)=COUNTIF(Devblogs!BH2:BH45,"<="&C6),COUNTIF(Devblogs!BH2:BH45,"<"&C6),CONCATENATE(COUNTIF(Devblogs!BH2:BH45,"<"&C6), " - ",COUNTIF(Devblogs!BH2:BH45,"<="&C6))) -> 4 - 5
A7: =Updates!A46 -> 2.11 | B7: =Updates!B46 -> Ground Breaking | C7: 44481 | D7: 0.66666667 | E7: =CHOOSE(WEEKDAY(C7,2),"Monday","Tuesday","Wednesday","Thursday","Friday","Saturday","Sunday") -> Tuesday | F7: =_xludf.DAYS(C7,Devblogs!BE2) -> #NAME? | G7: =IF(COUNTIF(Devblogs!BE2:BE45,"<"&C7)=COUNTIF(Devblogs!BE2:BE45,"<="&C7),COUNTIF(Devblogs!BE2:BE45,"<"&C7),CONCATENATE(COUNTIF(Devblogs!BE2:BE45,"<"&C7), " - ",COUNTIF(Devblogs!BE2:BE45,"<="&C7))) -> 2 - 3
A8: =Updates!A47 -> 2.13 | B8: =Updates!B47 -> Winged Lions | C8: 44532 | D8: 0.66666667 | E8: =CHOOSE(WEEKDAY(C8,2),"Monday","Tuesday","Wednesday","Thursday","Friday","Saturday","Sunday") -> Thursday | F8: =_xludf.DAYS(C8,Devblogs!BB2) -> #NAME? | G8: =IF(COUNTIF(Devblogs!BB2:BB45,"<"&C8)=COUNTIF(Devblogs!BB2:BB45,"<="&C8),COUNTIF(Devblogs!BB2:BB45,"<"&C8),CONCATENATE(COUNTIF(Devblogs!BB2:BB45,"<"&C8), " - ",COUNTIF(Devblogs!BB2:BB45,"<="&C8))) -> 3 - 5
A9: =Updates!A48 -> 2.15 | B9: =Updates!B48 -> Wind of Change | C9: 44630 | D9: 0.625 | E9: =CHOOSE(WEEKDAY(C9,2),"Monday","Tuesday","Wednesday","Thursday","Friday","Saturday","Sunday") -> Thursday | F9: =_xludf.DAYS(C9,Devblogs!AY2) -> #NAME? | G9: =IF(COUNTIF(Devblogs!AY2:AY45,"<"&C9)=COUNTIF(Devblogs!AY2:AY45,"<="&C9),COUNTIF(Devblogs!AY2:AY45,"<"&C9),CONCATENATE(COUNTIF(Devblogs!AY2:AY45,"<"&C9), " - ",COUNTIF(Devblogs!AY2:AY45,"<="&C9))) -> 4 - 6
A10: =Updates!A49 -> 2.17 | B10: =Updates!B49 -> Danger Zone | C10: 44707 | D10: 0.66666667 | E10: =CHOOSE(WEEKDAY(C10,2),"Monday","Tuesday","Wednesday","Thursday","Friday","Saturday","Sunday") -> Thursday | F10: =_xludf.DAYS(C10,Devblogs!AV2) -> #NAME? | G10: =IF(COUNTIF(Devblogs!AV2:AV45,"<"&C10)=COUNTIF(Devblogs!AV2:AV45,"<="&C10),COUNTIF(Devblogs!AV2:AV45,"<"&C10),CONCATENATE(COUNTIF(Devblogs!AV2:AV45,"<"&C10), " - ",COUNTIF(Devblogs!AV2:AV45,"<="&C10))) -> 6 - 8
A11: =CONCATENATE(Updates!A50," #1") -> 2.19 #1 | B11: =Updates!B50 -> Drone Age | C11: 44802 | D11: 0.6875 | E11: =CHOOSE(WEEKDAY(C11,2),"Monday","Tuesday","Wednesday","Thursday","Friday","Saturday","Sunday") -> Monday | F11: =_xludf.DAYS(C11,Devblogs!AS2) -> #NAME? | G11: =IF(COUNTIF(Devblogs!AS2:AS45,"<"&C11)=COUNTIF(Devblogs!AS2:AS45,"<="&C11),COUNTIF(Devblogs!AS2:AS45,"<"&C11),CONCATENATE(COUNTIF(Devblogs!AS2:AS45,"<"&C11), " - ",COUNTIF(Devblogs!AS2:AS45,"<="&C11))) -> 8 - 9
A12: =CONCATENATE(Updates!A50," #2") -> 2.19 #2 | C12: 44805 | D12: 0.81944444 | E12: =CHOOSE(WEEKDAY(C12,2),"Monday","Tuesday","Wednesday","Thursday","Friday","Saturday","Sunday") -> Thursday | F12: =_xludf.DAYS(C12,Devblogs!AS2) -> #NAME? | G12: =IF(COUNTIF(Devblogs!AS2:AS45,"<"&C12)=COUNTIF(Devblogs!AS2:AS45,"<="&C12),COUNTIF(Devblogs!AS2:AS45,"<"&C12),CONCATENATE(COUNTIF(Devblogs!AS2:AS45,"<"&C12), " - ",COUNTIF(Devblogs!AS2:AS45,"<="&C12))) -> 12
A13: =Updates!A51 -> 2.21 | B13: =Updates!B51 -> Fire and Ice | C13: 44847 | D13: 0.68611111 | E13: =CHOOSE(WEEKDAY(C13,2),"Monday","Tuesday","Wednesday","Thursday","Friday","Saturday","Sunday") -> Thursday | F13: =_xludf.DAYS(C13,Devblogs!AP2) -> #NAME? | G13: =IF(COUNTIF(Devblogs!AP2:AP45,"<"&C13)=COUNTIF(Devblogs!AP2:AP45,"<="&C13),COUNTIF(Devblogs!AP2:AP45,"<"&C13),CONCATENATE(COUNTIF(Devblogs!AP2:AP45,"<"&C13), " - ",COUNTIF(Devblogs!AP2:AP45,"<="&C13))) -> 1 - 2
A14: =Updates!A52 -> 2.23 | B14: =Updates!B52 -> Apex Predators | C14: 44903 | D14: 0.79513889 | E14: =CHOOSE(WEEKDAY(C14,2),"Monday","Tuesday","Wednesday","Thursday","Friday","Saturday","Sunday") -> Thursday | F14: =_xludf.DAYS(C14,Devblogs!AM2) -> #NAME? | G14: =IF(COUNTIF(Devblogs!AM2:AM45,"<"&C14)=COUNTIF(Devblogs!AM2:AM45,"<="&C14),COUNTIF(Devblogs!AM2:AM45,"<"&C14),CONCATENATE(COUNTIF(Devblogs!AM2:AM45,"<"&C14), " - ",COUNTIF(Devblogs!AM2:AM45,"<="&C14))) -> 5 - 6
A15: =Updates!A53 -> 2.25 | B15: =Updates!B53 -> Sky Guardians | C15: 44980 | D15: 0.72916667 | E15: =CHOOSE(WEEKDAY(C15,2),"Monday","Tuesday","Wednesday","Thursday","Friday","Saturday","Sunday") -> Thursday | F15: =IF(_xludf.DAYS(C15,Devblogs!AJ2)>-1,_xludf.DAYS(C15,Devblogs!AJ2),0) -> #NAME? | G15: =IF(COUNTIF(Devblogs!AJ2:AJ45,"<"&C15)=COUNTIF(Devblogs!AJ2:AJ45,"<="&C15),COUNTIF(Devblogs!AJ2:AJ45,"<"&C15),CONCATENATE(COUNTIF(Devblogs!AJ2:AJ45,"<"&C15), " - ",COUNTIF(Devblogs!AJ2:AJ45,"<="&C15))) -> 9
A16: =Updates!A54 -> 2.27 | B16: =Updates!B54 -> La Royale | C16: 45064 | D16: 0.70833333 | E16: =CHOOSE(WEEKDAY(C16,2),"Monday","Tuesday","Wednesday","Thursday","Friday","Saturday","Sunday") -> Thursday | F16: =IF(_xludf.DAYS(C16,Devblogs!AG2)>-1,_xludf.DAYS(C16,Devblogs!AG2),0) -> #NAME? | G16: =IF(COUNTIF(Devblogs!AG2:AG45,"<"&C16)=COUNTIF(Devblogs!AG2:AG45,"<="&C16),COUNTIF(Devblogs!AG2:AG45,"<"&C16),CONCATENATE(COUNTIF(Devblogs!AG2:AG45,"<"&C16), " - ",COUNTIF(Devblogs!AG2:AG45,"<="&C16))) -> 11 - 12
A17: =Updates!A55 -> 2.29 | B17: =Updates!B55 -> Sons of Attila | C17: 45169 | D17: 0.79166667 | E17: =CHOOSE(WEEKDAY(C17,2),"Monday","Tuesday","Wednesday","Thursday","Friday","Saturday","Sunday") -> Thursday | F17: =IF(_xludf.DAYS(C17,Devblogs!AD2)>-1,_xludf.DAYS(C17,Devblogs!AD2),0) -> #NAME? | G17: =IF(COUNTIF(Devblogs!AD2:AD45,"<"&C17)=COUNTIF(Devblogs!AD2:AD45,"<="&C17),COUNTIF(Devblogs!AD2:AD45,"<"&C17),CONCATENATE(COUNTIF(Devblogs!AD2:AD45,"<"&C17), " - ",COUNTIF(Devblogs!AD2:AD45,"<="&C17))) -> 8 - 9
A18: =Updates!A56 -> 2.31 | B18: =Updates!B56 -> Kings of Battle | C18: 45218 | D18: 0.82361111 | E18: =CHOOSE(WEEKDAY(C18,2),"Monday","Tuesday","Wednesday","Thursday","Friday","Saturday","Sunday") -> Thursday | F18: =IF(_xludf.DAYS(C18,Devblogs!AA2)>-1,_xludf.DAYS(C18,Devblogs!AA2),0) -> #NAME? | G18: =IF(COUNTIF(Devblogs!AA2:AA45,"<"&C18)=COUNTIF(Devblogs!AA2:AA45,"<="&C18),COUNTIF(Devblogs!AA2:AA45,"<"&C18),CONCATENATE(COUNTIF(Devblogs!AA2:AA45,"<"&C18), " - ",COUNTIF(Devblogs!AA2:AA45,"<="&C18))) -> 2
A19: =Updates!A57 -> 2.33 | B19: =Updates!B57 -> Air Superiority | C19: 45266 | D19: 0.90347222 | E19: =CHOOSE(WEEKDAY(C19,2),"Monday","Tuesday","Wednesday","Thursday","Friday","Saturday","Sunday") -> Wednesday | F19: =IF(_xludf.DAYS(C19,Devblogs!X2)>-1,_xludf.DAYS(C19,Devblogs!X2),0) -> #NAME? | G19: =IF(COUNTIF(Devblogs!X2:X45,"<"&C19)=COUNTIF(Devblogs!X2:X45,"<="&C19),COUNTIF(Devblogs!X2:X45,"<"&C19),CONCATENATE(COUNTIF(Devblogs!X2:X45,"<"&C19), " - ",COUNTIF(Devblogs!X2:X45,"<="&C19))) -> 3 - 4
A20: =Updates!A58 -> 2.35 | B20: =Updates!B58 -> Alpha Strike | C20: 45351 | D20: 0.72361111 | E20: =CHOOSE(WEEKDAY(C20,2),"Monday","Tuesday","Wednesday","Thursday","Friday","Saturday","Sunday") -> Thursday | F20: =IF(_xludf.DAYS(C20,Devblogs!U2)>-1,_xludf.DAYS(C20,Devblogs!U2),0) -> #NAME? | G20: =IF(COUNTIF(Devblogs!U2:U45,"<"&C20)=COUNTIF(Devblogs!U2:U45,"<="&C20),COUNTIF(Devblogs!U2:U45,"<"&C20),CONCATENATE(COUNTIF(Devblogs!U2:U45,"<"&C20), " - ",COUNTIF(Devblogs!U2:U45,"<="&C20))) -> 4 - 5
A21: =Updates!A59 -> 2.37 | B21: =Updates!B59 -> Seek & Destroy | C21: 45442 | D21: 0.77430556 | E21: =CHOOSE(WEEKDAY(C21,2),"Monday","Tuesday","Wednesday","Thursday","Friday","Saturday","Sunday") -> Thursday | F21: =IF(_xludf.DAYS(C21,Devblogs!R$2)>-1,_xludf.DAYS(C21,Devblogs!R$2),0) -> #NAME? | G21: =IF(COUNTIF(Devblogs!R$2:R$45,"<"&C21)=COUNTIF(Devblogs!R$2:R$45,"<="&C21),COUNTIF(Devblogs!R$2:R$45,"<"&C21),CONCATENATE(COUNTIF(Devblogs!R$2:R$45,"<"&C21), " - ",COUNTIF(Devblogs!R$2:R$45,"<="&C21))) -> 6 - 7
A22: =Updates!A60 -> 2.39 | B22: =Updates!B60 -> Dance of Dragons | C22: 45533 | D22: 0.81805556 | E22: =CHOOSE(WEEKDAY(C22,2),"Monday","Tuesday","Wednesday","Thursday","Friday","Saturday","Sunday") -> Thursday | F22: =IF(_xludf.DAYS(C22,Devblogs!O$2)>-1,_xludf.DAYS(C22,Devblogs!O$2),0) -> #NAME? | G22: =IF(COUNTIF(Devblogs!O$2:O$45,"<"&C22)=COUNTIF(Devblogs!O$2:O$45,"<="&C22),COUNTIF(Devblogs!O$2:O$45,"<"&C22),CONCATENATE(COUNTIF(Devblogs!O$2:O$45,"<"&C22), " - ",COUNTIF(Devblogs!O$2:O$45,"<="&C22))) -> 4
A23: =Updates!A61 -> 2.41 | B23: =Updates!B61 -> Firebirds | C23: 45589 | D23: 0.72152778 | E23: =CHOOSE(WEEKDAY(C23,2),"Monday","Tuesday","Wednesday","Thursday","Friday","Saturday","Sunday") -> Thursday | F23: =IF(_xludf.DAYS(C23,Devblogs!L$2)>-1,_xludf.DAYS(C23,Devblogs!L$2),0) -> #NAME? | G23: =IF(COUNTIF(Devblogs!L$2:L$45,"<"&C23)=COUNTIF(Devblogs!L$2:L$45,"<="&C23),COUNTIF(Devblogs!L$2:L$45,"<"&C23),CONCATENATE(COUNTIF(Devblogs!L$2:L$45,"<"&C23), " - ",COUNTIF(Devblogs!L$2:L$45,"<="&C23))) -> 5 - 6
A24: =Updates!A62 -> 2.43 | B24: =Updates!B62 -> Storm Warning | C24: 45635 | D24: 0.70138889 | E24: =CHOOSE(WEEKDAY(C24,2),"Monday","Tuesday","Wednesday","Thursday","Friday","Saturday","Sunday") -> Monday | F24: =IF(_xludf.DAYS(C24,Devblogs!I$2)>-1,_xludf.DAYS(C24,Devblogs!I$2),0) -> #NAME? | G24: =IF(COUNTIF(Devblogs!I$2:I$45,"<"&C24)=COUNTIF(Devblogs!I$2:I$45,"<="&C24),COUNTIF(Devblogs!I$2:I$45,"<"&C24),CONCATENATE(COUNTIF(Devblogs!I$2:I$45,"<"&C24), " - ",COUNTIF(Devblogs!I$2:I$45,"<="&C24))) -> 2 - 4
A25: =Updates!A63 -> 2.45 | B25: =Updates!B63 -> 0 | F25: =IF(_xludf.DAYS(C25,Devblogs!L$2)>-1,_xludf.DAYS(C25,Devblogs!L$2),0) -> #NAME? | G25: =IF(COUNTIF(Devblogs!L$2:L$45,"<"&C25)=COUNTIF(Devblogs!L$2:L$45,"<="&C25),COUNTIF(Devblogs!L$2:L$45,"<"&C25),CONCATENATE(COUNTIF(Devblogs!L$2:L$45,"<"&C25), " - ",COUNTIF(Devblogs!L$2:L$45,"<="&C25))) -> 0
B28: Release date day of week | F28: Average release time: | G28: =AVERAGE(D3:D27) -> 0.71856061
B29: Monday: | C29: =COUNTIF(E3:E27,"Monday") -> 2 | D29: =C29/SUM($C$29:$C$35) -> 0.090909091
B30: Tuesday: | C30: =COUNTIF(E3:E27,"Tuesday") -> 2 | D30: =C30/SUM($C$29:$C$35) -> 0.090909091
B31: Wednesday: | C31: =COUNTIF(E3:E27,"Wednesday") -> 1 | D31: =C31/SUM($C$29:$C$35) -> 0.045454545
B32: Thursday: | C32: =COUNTIF(E3:E27,"Thursday") -> 16 | D32: =C32/SUM($C$29:$C$35) -> 0.72727273
B33: Friday: | C33: =COUNTIF(E3:E27,"Friday") -> 1 | D33: =C33/SUM($C$29:$C$35) -> 0.045454545
B34: Saturday: | C34: =COUNTIF(E3:E27,"Saturday") -> 0 | D34: =C34/SUM($C$29:$C$35) -> 0 | G34: *: discrepancy is due to the inclusion of same day devblogs
B35: Sunday: | C35: =COUNTIF(E3:E27,"Sunday") -> 0 | D35: =C35/SUM($C$29:$C$35) -> 0

Sheet Dev streams
A1: Dev streams
A2: Version | B2: Name | C2: Date | D2: Day | E2: First devblog to stream | F2: Number of devblogs until stream*
A3: =Updates!A33 -> 1.87 | B3: =Updates!B33 -> Locked On | C3: 43523 | D3: =CHOOSE(WEEKDAY(C3,2),"Monday","Tuesday","Wednesday","Thursday","Friday","Saturday","Sunday") -> Wednesday | E3: =_xludf.DAYS(C3,Devblogs!CR2) -> #NAME? | F3: =IF(COUNTIF(Devblogs!CR2:CR45,"<"&C3)=COUNTIF(Devblogs!CR2:CR45,"<="&C3),COUNTIF(Devblogs!CR2:CR45,"<"&C3),CONCATENATE(COUNTIF(Devblogs!CR2:CR45,"<"&C3), " - ",COUNTIF(Devblogs!CR2:CR45,"<="&C3))) -> 9 - 10
A4: =Updates!A34 -> 1.89 | B4: =Updates!B34 -> Imperial Navy | C4: 43602 | D4: =CHOOSE(WEEKDAY(C4,2),"Monday","Tuesday","Wednesday","Thursday","Friday","Saturday","Sunday") -> Friday | E4: =_xludf.DAYS(C4,Devblogs!CO2) -> #NAME? | F4: =IF(COUNTIF(Devblogs!CO2:CO45,"<"&C4)=COUNTIF(Devblogs!CO2:CO45,"<="&C4),COUNTIF(Devblogs!CO2:CO45,"<"&C4),CONCATENATE(COUNTIF(Devblogs!CO2:CO45,"<"&C4), " - ",COUNTIF(Devblogs!CO2:CO45,"<="&C4))) -> 10 - 12
A5: =Updates!A35 -> 1.91 | B5: =Updates!B35 -> Night Vision | C5: 43707 | D5: =CHOOSE(WEEKDAY(C5,2),"Monday","Tuesday","Wednesday","Thursday","Friday","Saturday","Sunday") -> Friday | E5: =_xludf.DAYS(C5,Devblogs!CL2) -> #NAME? | F5: =IF(COUNTIF(Devblogs!CL2:CL45,"<"&C5)=COUNTIF(Devblogs!CL2:CL45,"<="&C5),COUNTIF(Devblogs!CL2:CL45,"<"&C5),CONCATENATE(COUNTIF(Devblogs!CL2:CL45,"<"&C5), " - ",COUNTIF(Devblogs!CL2:CL45,"<="&C5))) -> 15 - 16
A6: =Updates!A36 -> 1.93 | B6: =Updates!B36 -> Shark Attack | C6: 43762 | D6: =CHOOSE(WEEKDAY(C6,2),"Monday","Tuesday","Wednesday","Thursday","Friday","Saturday","Sunday") -> Thursday | E6: =_xludf.DAYS(C6,Devblogs!CI2) -> #NAME? | F6: =IF(COUNTIF(Devblogs!CI2:CI45,"<"&C6)=COUNTIF(Devblogs!CI2:CI45,"<="&C6),COUNTIF(Devblogs!CI2:CI45,"<"&C6),CONCATENATE(COUNTIF(Devblogs!CI2:CI45,"<"&C6), " - ",COUNTIF(Devblogs!CI2:CI45,"<="&C6))) -> 8 - 10
A7: =Updates!A37 -> 1.95 | B7: =Updates!B37 -> Northern Wind | C7: 43811 | D7: =CHOOSE(WEEKDAY(C7,2),"Monday","Tuesday","Wednesday","Thursday","Friday","Saturday","Sunday") -> Thursday | E7: =_xludf.DAYS(C7,Devblogs!CF2) -> #NAME? | F7: =IF(COUNTIF(Devblogs!CF2:CF45,"<"&C7)=COUNTIF(Devblogs!CF2:CF45,"<="&C7),COUNTIF(Devblogs!CF2:CF45,"<"&C7),CONCATENATE(COUNTIF(Devblogs!CF2:CF45,"<"&C7), " - ",COUNTIF(Devblogs!CF2:CF45,"<="&C7))) -> 13 - 14
A8: =Updates!A38 -> 1.97 | B8: =Updates!B38 -> Viking Fury | C8: 43893 | D8: =CHOOSE(WEEKDAY(C8,2),"Monday","Tuesday","Wednesday","Thursday","Friday","Saturday","Sunday") -> Tuesday | E8: =_xludf.DAYS(C8,Devblogs!CC2) -> #NAME? | F8: =IF(COUNTIF(Devblogs!CC2:CC45,"<"&C8)=COUNTIF(Devblogs!CC2:CC45,"<="&C8),COUNTIF(Devblogs!CC2:CC45,"<"&C8),CONCATENATE(COUNTIF(Devblogs!CC2:CC45,"<"&C8), " - ",COUNTIF(Devblogs!CC2:CC45,"<="&C8))) -> 13 - 14
A9: =Updates!A39 -> 1.99 | B9: =Updates!B39 -> Starfighters | C9: 43966 | D9: =CHOOSE(WEEKDAY(C9,2),"Monday","Tuesday","Wednesday","Thursday","Friday","Saturday","Sunday") -> Friday | E9: =_xludf.DAYS(C9,Devblogs!BZ2) -> #NAME? | F9: =IF(COUNTIF(Devblogs!BZ2:BZ45,"<"&C9)=COUNTIF(Devblogs!BZ2:BZ45,"<="&C9),COUNTIF(Devblogs!BZ2:BZ45,"<"&C9),CONCATENATE(COUNTIF(Devblogs!BZ2:BZ45,"<"&C9), " - ",COUNTIF(Devblogs!BZ2:BZ45,"<="&C9))) -> 8 - 10
A10: =Updates!A40 -> 1.101 | B10: =Updates!B40 -> Raining Fire | C10: 44064 | D10: =CHOOSE(WEEKDAY(C10,2),"Monday","Tuesday","Wednesday","Thursday","Friday","Saturday","Sunday") -> Friday | E10: =_xludf.DAYS(C10,Devblogs!BW2) -> #NAME? | F10: =IF(COUNTIF(Devblogs!BW2:BW45,"<"&C10)=COUNTIF(Devblogs!BW2:BW45,"<="&C10),COUNTIF(Devblogs!BW2:BW45,"<"&C10),CONCATENATE(COUNTIF(Devblogs!BW2:BW45,"<"&C10), " - ",COUNTIF(Devblogs!BW2:BW45,"<="&C10))) -> 5
A11: =Updates!A41 -> 2.1 | B11: =Updates!B41 -> New Power | C11: 44134 | D11: =CHOOSE(WEEKDAY(C11,2),"Monday","Tuesday","Wednesday","Thursday","Friday","Saturday","Sunday") -> Friday | E11: =_xludf.DAYS(C11,Devblogs!BT2) -> #NAME? | F11: =IF(COUNTIF(Devblogs!BT2:BT45,"<"&C11)=COUNTIF(Devblogs!BT2:BT45,"<="&C11),COUNTIF(Devblogs!BT2:BT45,"<"&C11),CONCATENATE(COUNTIF(Devblogs!BT2:BT45,"<"&C11), " - ",COUNTIF(Devblogs!BT2:BT45,"<="&C11))) -> 10 - 11
A12: =Updates!A42 -> 2.3 | B12: =Updates!B42 -> Hot Tracks | C12: 44176 | D12: =CHOOSE(WEEKDAY(C12,2),"Monday","Tuesday","Wednesday","Thursday","Friday","Saturday","Sunday") -> Friday | E12: =_xludf.DAYS(C12,Devblogs!BQ2) -> #NAME? | F12: =IF(COUNTIF(Devblogs!BQ2:BQ45,"<"&C12)=COUNTIF(Devblogs!BQ2:BQ45,"<="&C12),COUNTIF(Devblogs!BQ2:BQ45,"<"&C12),CONCATENATE(COUNTIF(Devblogs!BQ2:BQ45,"<"&C12), " - ",COUNTIF(Devblogs!BQ2:BQ45,"<="&C12))) -> 4 - 5
A13: =Updates!A43 -> 2.5 | B13: =Updates!B43 -> Ixwa Strike | C13: 44247 | D13: =CHOOSE(WEEKDAY(C13,2),"Monday","Tuesday","Wednesday","Thursday","Friday","Saturday","Sunday") -> Saturday | E13: =_xludf.DAYS(C13,Devblogs!BN2) -> #NAME? | F13: =IF(COUNTIF(Devblogs!BN2:BN45,"<"&C13)=COUNTIF(Devblogs!BN2:BN45,"<="&C13),COUNTIF(Devblogs!BN2:BN45,"<"&C13),CONCATENATE(COUNTIF(Devblogs!BN2:BN45,"<"&C13), " - ",COUNTIF(Devblogs!BN2:BN45,"<="&C13))) -> 6
A14: =Updates!A44 -> 2.7 | B14: =Updates!B44 -> Red Skies | C14: 44337 | D14: =CHOOSE(WEEKDAY(C14,2),"Monday","Tuesday","Wednesday","Thursday","Friday","Saturday","Sunday") -> Friday | E14: =_xludf.DAYS(C14,Devblogs!BK2) -> #NAME? | F14: =IF(COUNTIF(Devblogs!BK2:BK45,"<"&C14)=COUNTIF(Devblogs!BK2:BK45,"<="&C14),COUNTIF(Devblogs!BK2:BK45,"<"&C14),CONCATENATE(COUNTIF(Devblogs!BK2:BK45,"<"&C14), " - ",COUNTIF(Devblogs!BK2:BK45,"<="&C14))) -> 6 - 8
A15: =Updates!A45 -> 2.9 | B15: =Updates!B45 -> Direct Hit | C15: 44435 | D15: =CHOOSE(WEEKDAY(C15,2),"Monday","Tuesday","Wednesday","Thursday","Friday","Saturday","Sunday") -> Friday | E15: =_xludf.DAYS(C15,Devblogs!BH2) -> #NAME? | F15: =IF(COUNTIF(Devblogs!BH2:BH45,"<"&C15)=COUNTIF(Devblogs!BH2:BH45,"<="&C15),COUNTIF(Devblogs!BH2:BH45,"<"&C15),CONCATENATE(COUNTIF(Devblogs!BH2:BH45,"<"&C15), " - ",COUNTIF(Devblogs!BH2:BH45,"<="&C15))) -> 8 - 9
A16: =Updates!A46 -> 2.11 | B16: =Updates!B46 -> Ground Breaking | C16: 44484 | D16: =CHOOSE(WEEKDAY(C16,2),"Monday","Tuesday","Wednesday","Thursday","Friday","Saturday","Sunday") -> Friday | E16: =_xludf.DAYS(C16,Devblogs!BE2) -> #NAME? | F16: =IF(COUNTIF(Devblogs!BE2:BE45,"<"&C16)=COUNTIF(Devblogs!BE2:BE45,"<="&C16),COUNTIF(Devblogs!BE2:BE45,"<"&C16),CONCATENATE(COUNTIF(Devblogs!BE2:BE45,"<"&C16), " - ",COUNTIF(Devblogs!BE2:BE45,"<="&C16))) -> 5 - 7
A17: =Updates!A47 -> 2.13 | B17: =Updates!B47 -> Winged Lions | C17: 44533 | D17: =CHOOSE(WEEKDAY(C17,2),"Monday","Tuesday","Wednesday","Thursday","Friday","Saturday","Sunday") -> Friday | E17: =_xludf.DAYS(C17,Devblogs!BB2) -> #NAME? | F17: =IF(COUNTIF(Devblogs!BB2:BB45,"<"&C17)=COUNTIF(Devblogs!BB2:BB45,"<="&C17),COUNTIF(Devblogs!BB2:BB45,"<"&C17),CONCATENATE(COUNTIF(Devblogs!BB2:BB45,"<"&C17), " - ",COUNTIF(Devblogs!BB2:BB45,"<="&C17))) -> 5 - 7
A18: =Updates!A48 -> 2.15 | B18: =Updates!B48 -> Wind of Change | C18: 44631 | D18: =CHOOSE(WEEKDAY(C18,2),"Monday","Tuesday","Wednesday","Thursday","Friday","Saturday","Sunday") -> Friday | E18: =_xludf.DAYS(C18,Devblogs!AY2) -> #NAME? | F18: =IF(COUNTIF(Devblogs!AY2:AY45,"<"&C18)=COUNTIF(Devblogs!AY2:AY45,"<="&C18),COUNTIF(Devblogs!AY2:AY45,"<"&C18),CONCATENATE(COUNTIF(Devblogs!AY2:AY45,"<"&C18), " - ",COUNTIF(Devblogs!AY2:AY45,"<="&C18))) -> 6 - 8
A19: =Updates!A49 -> 2.17 | B19: =Updates!B49 -> Danger Zone | C19: 44708 | D19: =CHOOSE(WEEKDAY(C19,2),"Monday","Tuesday","Wednesday","Thursday","Friday","Saturday","Sunday") -> Friday | E19: =_xludf.DAYS(C19,Devblogs!AV2) -> #NAME? | F19: =IF(COUNTIF(Devblogs!AV2:AV45,"<"&C19)=COUNTIF(Devblogs!AV2:AV45,"<="&C19),COUNTIF(Devblogs!AV2:AV45,"<"&C19),CONCATENATE(COUNTIF(Devblogs!AV2:AV45,"<"&C19), " - ",COUNTIF(Devblogs!AV2:AV45,"<="&C19))) -> 8 - 9
A20: =Updates!A50 -> 2.19 | B20: =Updates!B50 -> Drone Age | C20: 44806 | D20: =CHOOSE(WEEKDAY(C20,2),"Monday","Tuesday","Wednesday","Thursday","Friday","Saturday","Sunday") -> Friday | E20: =_xludf.DAYS(C20,Devblogs!AS2) -> #NAME? | F20: =IF(COUNTIF(Devblogs!AS2:AS45,"<"&C20)=COUNTIF(Devblogs!AS2:AS45,"<="&C20),COUNTIF(Devblogs!AS2:AS45,"<"&C20),CONCATENATE(COUNTIF(Devblogs!AS2:AS45,"<"&C20), " - ",COUNTIF(Devblogs!AS2:AS45,"<="&C20))) -> 12 - 14
A21: =Updates!A51 -> 2.21 | B21: =Updates!B51 -> Fire and Ice | C21: 44848 | D21: =CHOOSE(WEEKDAY(C21,2),"Monday","Tuesday","Wednesday","Thursday","Friday","Saturday","Sunday") -> Friday | E21: =_xludf.DAYS(C21,Devblogs!AP2) -> #NAME? | F21: =IF(COUNTIF(Devblogs!AP2:AP45,"<"&C21)=COUNTIF(Devblogs!AP2:AP45,"<="&C21),COUNTIF(Devblogs!AP2:AP45,"<"&C21),CONCATENATE(COUNTIF(Devblogs!AP2:AP45,"<"&C21), " - ",COUNTIF(Devblogs!AP2:AP45,"<="&C21))) -> 2 - 4
A22: =Updates!A52 -> 2.23 | B22: =Updates!B52 -> Apex Predators | C22: 44904 | D22: =CHOOSE(WEEKDAY(C22,2),"Monday","Tuesday","Wednesday","Thursday","Friday","Saturday","Sunday") -> Friday | E22: =_xludf.DAYS(C22,Devblogs!AM2) -> #NAME? | F22: =IF(COUNTIF(Devblogs!AM2:AM45,"<"&C22)=COUNTIF(Devblogs!AM2:AM45,"<="&C22),COUNTIF(Devblogs!AM2:AM45,"<"&C22),CONCATENATE(COUNTIF(Devblogs!AM2:AM45,"<"&C22), " - ",COUNTIF(Devblogs!AM2:AM45,"<="&C22))) -> 6 - 8
A23: =Updates!A53 -> 2.25 | B23: =Updates!B53 -> Sky Guardians | C23: 44982 | D23: =CHOOSE(WEEKDAY(C23,2),"Monday","Tuesday","Wednesday","Thursday","Friday","Saturday","Sunday") -> Saturday | E23: =IF(_xludf.DAYS(C23,Devblogs!AJ2)>-1,_xludf.DAYS(C23,Devblogs!AJ2),0) -> #NAME? | F23: =IF(COUNTIF(Devblogs!AJ2:AJ45,"<"&C23)=COUNTIF(Devblogs!AJ2:AJ45,"<="&C23),COUNTIF(Devblogs!AJ2:AJ45,"<"&C23),CONCATENATE(COUNTIF(Devblogs!AJ2:AJ45,"<"&C23), " - ",COUNTIF(Devblogs!AJ2:AJ45,"<="&C23))) -> 11
A24: =Updates!A54 -> 2.27 | B24: =Updates!B54 -> La Royale | C24: 45065 | D24: =CHOOSE(WEEKDAY(C24,2),"Monday","Tuesday","Wednesday","Thursday","Friday","Saturday","Sunday") -> Friday | E24: =IF(_xludf.DAYS(C24,Devblogs!AG2)>-1,_xludf.DAYS(C24,Devblogs!AG2),0) -> #NAME? | F24: =IF(COUNTIF(Devblogs!AG2:AG45,"<"&C24)=COUNTIF(Devblogs!AG2:AG45,"<="&C24),COUNTIF(Devblogs!AG2:AG45,"<"&C24),CONCATENATE(COUNTIF(Devblogs!AG2:AG45,"<"&C24), " - ",COUNTIF(Devblogs!AG2:AG45,"<="&C24))) -> 12
A25: =Updates!A55 -> 2.29 | B25: =Updates!B55 -> Sons of Attila | C25: 45170 | D25: =CHOOSE(WEEKDAY(C25,2),"Monday","Tuesday","Wednesday","Thursday","Friday","Saturday","Sunday") -> Friday | E25: =IF(_xludf.DAYS(C25,Devblogs!AD2)>-1,_xludf.DAYS(C25,Devblogs!AD2),0) -> #NAME? | F25: =IF(COUNTIF(Devblogs!AD2:AD45,"<"&C25)=COUNTIF(Devblogs!AD2:AD45,"<="&C25),COUNTIF(Devblogs!AD2:AD45,"<"&C25),CONCATENATE(COUNTIF(Devblogs!AD2:AD45,"<"&C25), " - ",COUNTIF(Devblogs!AD2:AD45,"<="&C25))) -> 9 - 12
A26: =Updates!A56 -> 2.31 | B26: =Updates!B56 -> Kings of Battle | C26: 45219 | D26: =CHOOSE(WEEKDAY(C26,2),"Monday","Tuesday","Wednesday","Thursday","Friday","Saturday","Sunday") -> Friday | E26: =IF(_xludf.DAYS(C26,Devblogs!AA2)>-1,_xludf.DAYS(C26,Devblogs!AA2),0) -> #NAME? | F26: =IF(COUNTIF(Devblogs!AA2:AA45,"<"&C26)=COUNTIF(Devblogs!AA2:AA45,"<="&C26),COUNTIF(Devblogs!AA2:AA45,"<"&C26),CONCATENATE(COUNTIF(Devblogs!AA2:AA45,"<"&C26), " - ",COUNTIF(Devblogs!AA2:AA45,"<="&C26))) -> 2 - 3
A27: =Updates!A57 -> 2.33 | B27: =Updates!B57 -> Air Superiority | C27: 45267 | D27: =CHOOSE(WEEKDAY(C27,2),"Monday","Tuesday","Wednesday","Thursday","Friday","Saturday","Sunday") -> Thursday | E27: =IF(_xludf.DAYS(C27,Devblogs!X2)>-1,_xludf.DAYS(C27,Devblogs!X2),0) -> #NAME? | F27: =IF(COUNTIF(Devblogs!X2:X45,"<"&C27)=COUNTIF(Devblogs!X2:X45,"<="&C27),COUNTIF(Devblogs!X2:X45,"<"&C27),CONCATENATE(COUNTIF(Devblogs!X2:X45,"<"&C27), " - ",COUNTIF(Devblogs!X2:X45,"<="&C27))) -> 4 - 6
A28: =Updates!A58 -> 2.35 | B28: =Updates!B58 -> Alpha Strike | C28: 45352 | D28: =CHOOSE(WEEKDAY(C28,2),"Monday","Tuesday","Wednesday","Thursday","Friday","Saturday","Sunday") -> Friday | E28: =IF(_xludf.DAYS(C28,Devblogs!U2)>-1,_xludf.DAYS(C28,Devblogs!U2),0) -> #NAME? | F28: =IF(COUNTIF(Devblogs!U2:U45,"<"&C28)=COUNTIF(Devblogs!U2:U45,"<="&C28),COUNTIF(Devblogs!U2:U45,"<"&C28),CONCATENATE(COUNTIF(Devblogs!U2:U45,"<"&C28), " - ",COUNTIF(Devblogs!U2:U45,"<="&C28))) -> 5 - 7
A29: =Updates!A59 -> 2.37 | B29: =Updates!B59 -> Seek & Destroy | C29: 45443 | D29: =CHOOSE(WEEKDAY(C29,2),"Monday","Tuesday","Wednesday","Thursday","Friday","Saturday","Sunday") -> Friday | E29: =IF(_xludf.DAYS(C29,Devblogs!R$2)>-1,_xludf.DAYS(C29,Devblogs!R$2),0) -> #NAME? | F29: =IF(COUNTIF(Devblogs!R$2:R$45,"<"&C29)=COUNTIF(Devblogs!R$2:R$45,"<="&C29),COUNTIF(Devblogs!R$2:R$45,"<"&C29),CONCATENATE(COUNTIF(Devblogs!R$2:R$45,"<"&C29), " - ",COUNTIF(Devblogs!R$2:R$45,"<="&C29))) -> 7 - 10
A30: =Updates!A60 -> 2.39 | B30: =Updates!B60 -> Dance of Dragons | C30: 45534 | D30: =CHOOSE(WEEKDAY(C30,2),"Monday","Tuesday","Wednesday","Thursday","Friday","Saturday","Sunday") -> Friday | E30: =IF(_xludf.DAYS(C30,Devblogs!O$2)>-1,_xludf.DAYS(C30,Devblogs!O$2),0) -> #NAME? | F30: =IF(COUNTIF(Devblogs!O$2:O$45,"<"&C30)=COUNTIF(Devblogs!O$2:O$45,"<="&C30),COUNTIF(Devblogs!O$2:O$45,"<"&C30),CONCATENATE(COUNTIF(Devblogs!O$2:O$45,"<"&C30), " - ",COUNTIF(Devblogs!O$2:O$45,"<="&C30))) -> 4 - 7
A31: =Updates!A61 -> 2.41 | B31: =Updates!B61 -> Firebirds | C31: 45590 | D31: =CHOOSE(WEEKDAY(C31,2),"Monday","Tuesday","Wednesday","Thursday","Friday","Saturday","Sunday") -> Friday | E31: =IF(_xludf.DAYS(C31,Devblogs!L$2)>-1,_xludf.DAYS(C31,Devblogs!L$2),0) -> #NAME? | F31: =IF(COUNTIF(Devblogs!L$2:L$45,"<"&C31)=COUNTIF(Devblogs!L$2:L$45,"<="&C31),COUNTIF(Devblogs!L$2:L$45,"<"&C31),CONCATENATE(COUNTIF(Devblogs!L$2:L$45,"<"&C31), " - ",COUNTIF(Devblogs!L$2:L$45,"<="&C31))) -> 6 - 8
A32: =Updates!A62 -> 2.43 | B32: =Updates!B62 -> Storm Warning | C32: 45636 | D32: =CHOOSE(WEEKDAY(C32,2),"Monday","Tuesday","Wednesday","Thursday","Friday","Saturday","Sunday") -> Tuesday | E32: =IF(_xludf.DAYS(C32,Devblogs!I$2)>-1,_xludf.DAYS(C32,Devblogs!I$2),0) -> #NAME? | F32: =IF(COUNTIF(Devblogs!I$2:I$45,"<"&C32)=COUNTIF(Devblogs!I$2:I$45,"<="&C32),COUNTIF(Devblogs!I$2:I$45,"<"&C32),CONCATENATE(COUNTIF(Devblogs!I$2:I$45,"<"&C32), " - ",COUNTIF(Devblogs!I$2:I$45,"<="&C32))) -> 4 - 5
A33: =Updates!A63 -> 2.45 | B33: =Updates!B63 -> 0 | E33: =IF(_xludf.DAYS(C33,Devblogs!L$2)>-1,_xludf.DAYS(C33,Devblogs!L$2),0) -> #NAME? | F33: =IF(COUNTIF(Devblogs!L$2:L$45,"<"&C33)=COUNTIF(Devblogs!L$2:L$45,"<="&C33),COUNTIF(Devblogs!L$2:L$45,"<"&C33),CONCATENATE(COUNTIF(Devblogs!L$2:L$45,"<"&C33), " - ",COUNTIF(Devblogs!L$2:L$45,"<="&C33))) -> 0
B36: Release date day of week
B37: Monday: | C37: =COUNTIF(D3:D35,"Monday") -> 0 | D37: =C37/SUM($C$37:$C$43) -> 0
B38: Tuesday: | C38: =COUNTIF(D3:D35,"Tuesday") -> 2 | D38: =C38/SUM($C$37:$C$43) -> 0.066666667
B39: Wednesday: | C39: =COUNTIF(D3:D35,"Wednesday") -> 1 | D39: =C39/SUM($C$37:$C$43) -> 0.033333333
B40: Thursday: | C40: =COUNTIF(D3:D35,"Thursday") -> 3 | D40: =C40/SUM($C$37:$C$43) -> 0.1
B41: Friday: | C41: =COUNTIF(D3:D35,"Friday") -> 22 | D41: =C41/SUM($C$37:$C$43) -> 0.73333333
B42: Saturday: | C42: =COUNTIF(D3:D35,"Saturday") -> 2 | D42: =C42/SUM($C$37:$C$43) -> 0.066666667 | F42: *: discrepancy is due to the inclusion of same day devblogs
B43: Sunday: | C43: =COUNTIF(D3:D35,"Sunday") -> 0 | D43: =C43/SUM($C$37:$C$43) -> 0

Sheet Dev servers
A1: Dev servers
A2: Version | B2: Name | C2: Date | D2: Start time (UTC) | E2: Announcement time (UTC) | F2: Day | G2: Days between 1&2(&3) | H2: First devblog to first dev server | I2: Number of devblogs until first dev server*
A3: =Updates!A18 -> 1.57 | B3: =Updates!B18 -> Battle March | C3: 42437 | D3: 0.54166667 | E3: 0.54930556 | F3: =CHOOSE(WEEKDAY(C3,2),"Monday","Tuesday","Wednesday","Thursday","Friday","Saturday","Sunday") -> Tuesday | G3: - | H3: =_xludf.DAYS(C3,Devblogs!EK2) -> #NAME? | I3: =IF(COUNTIF(Devblogs!EK2:EK45,"<"&C3)=COUNTIF(Devblogs!EK2:EK45,"<="&C3),COUNTIF(Devblogs!EK2:EK45,"<"&C3),CONCATENATE(COUNTIF(Devblogs!EK2:EK45,"<"&C3), " - ",COUNTIF(Devblogs!EK2:EK45,"<="&C3))) -> 19
A4: =CONCATENATE(Updates!A19," #1") -> 1.59 #1 | B4: =Updates!B19 -> Flaming Arrows | C4: 42516 | D4: 0.79166667 | E4: 0.80069444 | F4: =CHOOSE(WEEKDAY(C4,2),"Monday","Tuesday","Wednesday","Thursday","Friday","Saturday","Sunday") -> Thursday | G4: =C5-C4 -> 4 | H4: =_xludf.DAYS(C4,Devblogs!EH2) -> #NAME? | I4: =IF(COUNTIF(Devblogs!EH2:EH45,"<"&C4)=COUNTIF(Devblogs!EH2:EH45,"<="&C4),COUNTIF(Devblogs!EH2:EH45,"<"&C4),CONCATENATE(COUNTIF(Devblogs!EH2:EH45,"<"&C4), " - ",COUNTIF(Devblogs!EH2:EH45,"<="&C4))) -> 15 - 17
A5: =CONCATENATE(Updates!A19," #2") -> 1.59 #2 | C5: 42520 | D5: 0.83333333 | E5: 0.78472222 | F5: =CHOOSE(WEEKDAY(C5,2),"Monday","Tuesday","Wednesday","Thursday","Friday","Saturday","Sunday") -> Monday
A6: =Updates!A20 -> 1.61 | B6: =Updates!B20 -> Road to Glory | C6: 42581 | D6: 0.83333333 | E6: 0.71388889 | F6: =CHOOSE(WEEKDAY(C6,2),"Monday","Tuesday","Wednesday","Thursday","Friday","Saturday","Sunday") -> Saturday | G6: - | H6: =_xludf.DAYS(C6,Devblogs!EE2) -> #NAME? | I6: =IF(COUNTIF(Devblogs!EE2:EE45,"<"&C6)=COUNTIF(Devblogs!EE2:EE45,"<="&C6),COUNTIF(Devblogs!EE2:EE45,"<"&C6),CONCATENATE(COUNTIF(Devblogs!EE2:EE45,"<"&C6), " - ",COUNTIF(Devblogs!EE2:EE45,"<="&C6))) -> 10
A7: =Updates!A21 -> 1.63 | B7: =Updates!B21 -> Desert Hunters | C7: 42628 | D7: 0.83333333 | E7: 0.78472222 | F7: =CHOOSE(WEEKDAY(C7,2),"Monday","Tuesday","Wednesday","Thursday","Friday","Saturday","Sunday") -> Thursday | G7: - | H7: =_xludf.DAYS(C7,Devblogs!EB2) -> #NAME? | I7: =IF(COUNTIF(Devblogs!EB2:EB45,"<"&C7)=COUNTIF(Devblogs!EB2:EB45,"<="&C7),COUNTIF(Devblogs!EB2:EB45,"<"&C7),CONCATENATE(COUNTIF(Devblogs!EB2:EB45,"<"&C7), " - ",COUNTIF(Devblogs!EB2:EB45,"<="&C7))) -> 10 - 11
A8: =Updates!A22 -> 1.65 | B8: =Updates!B22 -> Way of the Samurai | C8: 42714 | D8: 0.79166667 | E8: 0.71736111 | F8: =CHOOSE(WEEKDAY(C8,2),"Monday","Tuesday","Wednesday","Thursday","Friday","Saturday","Sunday") -> Saturday | G8: - | H8: =_xludf.DAYS(C8,Devblogs!DY2) -> #NAME? | I8: =IF(COUNTIF(Devblogs!DY2:DY45,"<"&C8)=COUNTIF(Devblogs!DY2:DY45,"<="&C8),COUNTIF(Devblogs!DY2:DY45,"<"&C8),CONCATENATE(COUNTIF(Devblogs!DY2:DY45,"<"&C8), " - ",COUNTIF(Devblogs!DY2:DY45,"<="&C8))) -> 18 - 19
A9: =Updates!A23 -> 1.67 | B9: =Updates!B23 -> Assault | C9: 42805 | D9: 0.79166667 | E9: 0.79375 | F9: =CHOOSE(WEEKDAY(C9,2),"Monday","Tuesday","Wednesday","Thursday","Friday","Saturday","Sunday") -> Saturday | G9: - | H9: =_xludf.DAYS(C9,Devblogs!DV2) -> #NAME? | I9: =IF(COUNTIF(Devblogs!DV2:DV45,"<"&C9)=COUNTIF(Devblogs!DV2:DV45,"<="&C9),COUNTIF(Devblogs!DV2:DV45,"<"&C9),CONCATENATE(COUNTIF(Devblogs!DV2:DV45,"<"&C9), " - ",COUNTIF(Devblogs!DV2:DV45,"<="&C9))) -> 18
A10: =Updates!A24 -> 1.69 | B10: =Updates!B24 -> Regia Aeronautica | C10: 42873 | D10: 0.83333333 | E10: 0.82777778 | F10: =CHOOSE(WEEKDAY(C10,2),"Monday","Tuesday","Wednesday","Thursday","Friday","Saturday","Sunday") -> Thursday | G10: - | H10: =_xludf.DAYS(C10,Devblogs!DS2) -> #NAME? | I10: =IF(COUNTIF(Devblogs!DS2:DS45,"<"&C10)=COUNTIF(Devblogs!DS2:DS45,"<="&C10),COUNTIF(Devblogs!DS2:DS45,"<"&C10),CONCATENATE(COUNTIF(Devblogs!DS2:DS45,"<"&C10), " - ",COUNTIF(Devblogs!DS2:DS45,"<="&C10))) -> 9 - 11
A11: =CONCATENATE(Updates!A25," #1") -> 1.71 #1 | B11: =Updates!B25 -> New E.R.A. | C11: 42979 | D11: 0.83333333 | E11: 0.81111111 | F11: =CHOOSE(WEEKDAY(C11,2),"Monday","Tuesday","Wednesday","Thursday","Friday","Saturday","Sunday") -> Friday | G11: =C12-C11 -> 13 | H11: =_xludf.DAYS(C11,Devblogs!DP2) -> #NAME? | I11: =IF(COUNTIF(Devblogs!DP2:DP45,"<"&C11)=COUNTIF(Devblogs!DP2:DP45,"<="&C11),COUNTIF(Devblogs!DP2:DP45,"<"&C11),CONCATENATE(COUNTIF(Devblogs!DP2:DP45,"<"&C11), " - ",COUNTIF(Devblogs!DP2:DP45,"<="&C11))) -> 13 - 15
A12: =CONCATENATE(Updates!A25," #2") -> 1.71 #2 | C12: 42992 | D12: 0.83333333 | E12: 0.80486111 | F12: =CHOOSE(WEEKDAY(C12,2),"Monday","Tuesday","Wednesday","Thursday","Friday","Saturday","Sunday") -> Thursday
A13: =Updates!A26 -> 1.73 | B13: =Updates!B26 -> Vive la France | C13: 43036 | D13: 0.79166667 | E13: 0.64722222 | F13: =CHOOSE(WEEKDAY(C13,2),"Monday","Tuesday","Wednesday","Thursday","Friday","Saturday","Sunday") -> Saturday | G13: - | H13: =_xludf.DAYS(C13,Devblogs!DM2) -> #NAME? | I13: =IF(COUNTIF(Devblogs!DM2:DM45,"<"&C13)=COUNTIF(Devblogs!DM2:DM45,"<="&C13),COUNTIF(Devblogs!DM2:DM45,"<"&C13),CONCATENATE(COUNTIF(Devblogs!DM2:DM45,"<"&C13), " - ",COUNTIF(Devblogs!DM2:DM45,"<="&C13))) -> 7
A14: =CONCATENATE(Updates!A27," #1") -> 1.75 #1 | B14: =Updates!B27 -> La Résistance | C14: 43082 | D14: 0.79166667 | E14: 0.78611111 | F14: =CHOOSE(WEEKDAY(C14,2),"Monday","Tuesday","Wednesday","Thursday","Friday","Saturday","Sunday") -> Wednesday | G14: =C15-C14 -> 3 | H14: =_xludf.DAYS(C14,Devblogs!DJ2) -> #NAME? | I14: =IF(COUNTIF(Devblogs!DJ2:DJ45,"<"&C14)=COUNTIF(Devblogs!DJ2:DJ45,"<="&C14),COUNTIF(Devblogs!DJ2:DJ45,"<"&C14),CONCATENATE(COUNTIF(Devblogs!DJ2:DJ45,"<"&C14), " - ",COUNTIF(Devblogs!DJ2:DJ45,"<="&C14))) -> 9 - 11
A15: =CONCATENATE(Updates!A27," #2") -> 1.75 #2 | C15: 43085 | D15: 0.79166667 | E15: 0.79166667 | F15: =CHOOSE(WEEKDAY(C15,2),"Monday","Tuesday","Wednesday","Thursday","Friday","Saturday","Sunday") -> Saturday
A16: =CONCATENATE(Updates!A28," #1") -> 1.77 #1 | B16: =Updates!B28 -> Advancing Storm | C16: 43163 | D16: 0.66666667 | E16: 0.60694444 | F16: =CHOOSE(WEEKDAY(C16,2),"Monday","Tuesday","Wednesday","Thursday","Friday","Saturday","Sunday") -> Sunday | G16: =C17-C16 -> 6 | H16: =_xludf.DAYS(C16,Devblogs!DG2) -> #NAME? | I16: =IF(COUNTIF(Devblogs!DG2:DG45,"<"&C16)=COUNTIF(Devblogs!DG2:DG45,"<="&C16),COUNTIF(Devblogs!DG2:DG45,"<"&C16),CONCATENATE(COUNTIF(Devblogs!DG2:DG45,"<"&C16), " - ",COUNTIF(Devblogs!DG2:DG45,"<="&C16))) -> 18
A17: =CONCATENATE(Updates!A28," #2") -> 1.77 #2 | C17: 43169 | D17: 0.54166667 | E17: 0.54444444 | F17: =CHOOSE(WEEKDAY(C17,2),"Monday","Tuesday","Wednesday","Thursday","Friday","Saturday","Sunday") -> Saturday
A18: =CONCATENATE(Updates!A29," #1") -> 1.79 #1 | B18: =Updates!B29 -> Project X | C18: 43253 | D18: 0.8125 | E18: 0.79930556 | F18: =CHOOSE(WEEKDAY(C18,2),"Monday","Tuesday","Wednesday","Thursday","Friday","Saturday","Sunday") -> Saturday | G18: =C19-C18 -> 7 | H18: =_xludf.DAYS(C18,Devblogs!DD2) -> #NAME? | I18: =IF(COUNTIF(Devblogs!DD2:DD45,"<"&C18)=COUNTIF(Devblogs!DD2:DD45,"<="&C18),COUNTIF(Devblogs!DD2:DD45,"<"&C18),CONCATENATE(COUNTIF(Devblogs!DD2:DD45,"<"&C18), " - ",COUNTIF(Devblogs!DD2:DD45,"<="&C18))) -> 14 - 15
A19: =CONCATENATE(Updates!A29," #2") -> 1.79 #2 | C19: 43260 | D19: 0.79166667 | E19: 0.74444444 | F19: =CHOOSE(WEEKDAY(C19,2),"Monday","Tuesday","Wednesday","Thursday","Friday","Saturday","Sunday") -> Saturday
A20: =CONCATENATE(Updates!A30," #1") -> 1.81 #1 | B20: =Updates!B30 -> The Valkyries | C20: 43348 | D20: 0.83333333 | E20: 0.83819444 | F20: =CHOOSE(WEEKDAY(C20,2),"Monday","Tuesday","Wednesday","Thursday","Friday","Saturday","Sunday") -> Wednesday | G20: - | H20: =_xludf.DAYS(C20,Devblogs!DA2) -> #NAME? | I20: =IF(COUNTIF(Devblogs!DA2:DA45,"<"&C20)=COUNTIF(Devblogs!DA2:DA45,"<="&C20),COUNTIF(Devblogs!DA2:DA45,"<"&C20),CONCATENATE(COUNTIF(Devblogs!DA2:DA45,"<"&C20), " - ",COUNTIF(Devblogs!DA2:DA45,"<="&C20))) -> 13 - 14
A21: =CONCATENATE(Updates!A30," #2") -> 1.81 #2 | C21: 43351 | D21: 0.75 | E21: 0.74166667 | F21: =CHOOSE(WEEKDAY(C21,2),"Monday","Tuesday","Wednesday","Thursday","Friday","Saturday","Sunday") -> Saturday | G21: =C21-C20 -> 3
A22: =CONCATENATE(Updates!A30," #3") -> 1.81 #3 | C22: 43358 | D22: 0.75 | E22: 0.74930556 | F22: =CHOOSE(WEEKDAY(C22,2),"Monday","Tuesday","Wednesday","Thursday","Friday","Saturday","Sunday") -> Saturday | G22: =C22-C21 -> 7
A23: =Updates!A31 -> 1.83 | B23: =Updates!B31 -> Masters of the Sea | C23: 43389 | D23: 0.8125 | E23: 0.77569444 | F23: =CHOOSE(WEEKDAY(C23,2),"Monday","Tuesday","Wednesday","Thursday","Friday","Saturday","Sunday") -> Tuesday | G23: - | H23: =_xludf.DAYS(C23,Devblogs!CX2) -> #NAME? | I23: =IF(COUNTIF(Devblogs!CX2:CX45,"<"&C23)=COUNTIF(Devblogs!CX2:CX45,"<="&C23),COUNTIF(Devblogs!CX2:CX45,"<"&C23),CONCATENATE(COUNTIF(Devblogs!CX2:CX45,"<"&C23), " - ",COUNTIF(Devblogs!CX2:CX45,"<="&C23))) -> 5 - 6
A24: =CONCATENATE(Updates!A32," #1") -> 1.85 #1 | B24: =Updates!B32 -> Supersonic | C24: 43444 | D24: 0.875 | E24: 0.87291667 | F24: =CHOOSE(WEEKDAY(C24,2),"Monday","Tuesday","Wednesday","Thursday","Friday","Saturday","Sunday") -> Monday | G24: =C25-C24 -> 3 | H24: =_xludf.DAYS(C24,Devblogs!CU2) -> #NAME? | I24: =IF(COUNTIF(Devblogs!CU2:CU45,"<"&C24)=COUNTIF(Devblogs!CU2:CU45,"<="&C24),COUNTIF(Devblogs!CU2:CU45,"<"&C24),CONCATENATE(COUNTIF(Devblogs!CU2:CU45,"<"&C24), " - ",COUNTIF(Devblogs!CU2:CU45,"<="&C24))) -> 11
A25: =CONCATENATE(Updates!A32," #2") -> 1.85 #2 | C25: 43447 | D25: 0.8125 | E25: 0.81041667 | F25: =CHOOSE(WEEKDAY(C25,2),"Monday","Tuesday","Wednesday","Thursday","Friday","Saturday","Sunday") -> Thursday
A26: =CONCATENATE(Updates!A33," #1") -> 1.87 #1 | B26: =Updates!B33 -> Locked On | C26: 43526 | D26: 0.79166667 | E26: 0.75069444 | F26: =CHOOSE(WEEKDAY(C26,2),"Monday","Tuesday","Wednesday","Thursday","Friday","Saturday","Sunday") -> Saturday | G26: =C27-C26 -> 4 | H26: =_xludf.DAYS(C26,Devblogs!CR2) -> #NAME? | I26: =IF(COUNTIF(Devblogs!CR2:CR45,"<"&C26)=COUNTIF(Devblogs!CR2:CR45,"<="&C26),COUNTIF(Devblogs!CR2:CR45,"<"&C26),CONCATENATE(COUNTIF(Devblogs!CR2:CR45,"<"&C26), " - ",COUNTIF(Devblogs!CR2:CR45,"<="&C26))) -> 14 - 16
A27: =CONCATENATE(Updates!A33," #2") -> 1.87 #2 | C27: 43530 | D27: 0.79166667 | E27: 0.78541667 | F27: =CHOOSE(WEEKDAY(C27,2),"Monday","Tuesday","Wednesday","Thursday","Friday","Saturday","Sunday") -> Wednesday
A28: =CONCATENATE(Updates!A34," #1") -> 1.89 #1 | B28: =Updates!B34 -> Imperial Navy | C28: 43603 | D28: 0.79166667 | E28: 0.75347222 | F28: =CHOOSE(WEEKDAY(C28,2),"Monday","Tuesday","Wednesday","Thursday","Friday","Saturday","Sunday") -> Saturday | G28: =C29-C28 -> 7 | H28: =_xludf.DAYS(C28,Devblogs!CO2) -> #NAME? | I28: =IF(COUNTIF(Devblogs!CO2:CO45,"<"&C28)=COUNTIF(Devblogs!CO2:CO45,"<="&C28),COUNTIF(Devblogs!CO2:CO45,"<"&C28),CONCATENATE(COUNTIF(Devblogs!CO2:CO45,"<"&C28), " - ",COUNTIF(Devblogs!CO2:CO45,"<="&C28))) -> 12
A29: =CONCATENATE(Updates!A34," #2") -> 1.89 #2 | C29: 43610 | D29: 0.79166667 | E29: 0.75208333 | F29: =CHOOSE(WEEKDAY(C29,2),"Monday","Tuesday","Wednesday","Thursday","Friday","Saturday","Sunday") -> Saturday
A30: =CONCATENATE(Updates!A35," #1") -> 1.91 #1 | B30: =Updates!B35 -> Night Vision | C30: 43708 | D30: 0.79166667 | E30: 0.74444444 | F30: =CHOOSE(WEEKDAY(C30,2),"Monday","Tuesday","Wednesday","Thursday","Friday","Saturday","Sunday") -> Saturday | G30: =C31-C30 -> 5 | H30: =_xludf.DAYS(C30,Devblogs!CL2) -> #NAME? | I30: =IF(COUNTIF(Devblogs!CL2:CL45,"<"&C30)=COUNTIF(Devblogs!CL2:CL45,"<="&C30),COUNTIF(Devblogs!CL2:CL45,"<"&C30),CONCATENATE(COUNTIF(Devblogs!CL2:CL45,"<"&C30), " - ",COUNTIF(Devblogs!CL2:CL45,"<="&C30))) -> 16
A31: =CONCATENATE(Updates!A35," #2") -> 1.91 #2 | C31: 43713 | D31: 0.79166667 | E31: 0.76458333 | F31: =CHOOSE(WEEKDAY(C31,2),"Monday","Tuesday","Wednesday","Thursday","Friday","Saturday","Sunday") -> Thursday
A32: =Updates!A36 -> 1.93 | B32: =Updates!B36 -> Shark Attack | C32: 43762 | D32: 0.79166667 | E32: 0.73888889 | F32: =CHOOSE(WEEKDAY(C32,2),"Monday","Tuesday","Wednesday","Thursday","Friday","Saturday","Sunday") -> Thursday | G32: - | H32: =_xludf.DAYS(C32,Devblogs!CI2) -> #NAME? | I32: =IF(COUNTIF(Devblogs!CI2:CI45,"<"&C32)=COUNTIF(Devblogs!CI2:CI45,"<="&C32),COUNTIF(Devblogs!CI2:CI45,"<"&C32),CONCATENATE(COUNTIF(Devblogs!CI2:CI45,"<"&C32), " - ",COUNTIF(Devblogs!CI2:CI45,"<="&C32))) -> 8 - 10
A33: =Updates!A37 -> 1.95 | B33: =Updates!B37 -> Northern Wind | C33: 43811 | D33: 0.79166667 | E33: 0.76597222 | F33: =CHOOSE(WEEKDAY(C33,2),"Monday","Tuesday","Wednesday","Thursday","Friday","Saturday","Sunday") -> Thursday | G33: - | H33: =_xludf.DAYS(C33,Devblogs!CF2) -> #NAME? | I33: =IF(COUNTIF(Devblogs!CF2:CF45,"<"&C33)=COUNTIF(Devblogs!CF2:CF45,"<="&C33),COUNTIF(Devblogs!CF2:CF45,"<"&C33),CONCATENATE(COUNTIF(Devblogs!CF2:CF45,"<"&C33), " - ",COUNTIF(Devblogs!CF2:CF45,"<="&C33))) -> 13 - 14
A34: =CONCATENATE(Updates!A38," #1") -> 1.97 #1 | B34: =Updates!B38 -> Viking Fury | C34: 43893 | D34: 0.79166667 | E34: 0.75972222 | F34: =CHOOSE(WEEKDAY(C34,2),"Monday","Tuesday","Wednesday","Thursday","Friday","Saturday","Sunday") -> Tuesday | G34: =C35-C34 -> 4 | H34: =_xludf.DAYS(C34,Devblogs!CC2) -> #NAME? | I34: =IF(COUNTIF(Devblogs!CC2:CC45,"<"&C34)=COUNTIF(Devblogs!CC2:CC45,"<="&C34),COUNTIF(Devblogs!CC2:CC45,"<"&C34),CONCATENATE(COUNTIF(Devblogs!CC2:CC45,"<"&C34), " - ",COUNTIF(Devblogs!CC2:CC45,"<="&C34))) -> 13 - 14
A35: =CONCATENATE(Updates!A38," #2") -> 1.97 #2 | C35: 43897 | D35: 0.79166667 | E35: 0.69513889 | F35: =CHOOSE(WEEKDAY(C35,2),"Monday","Tuesday","Wednesday","Thursday","Friday","Saturday","Sunday") -> Saturday
A36: =CONCATENATE(Updates!A39," #1") -> 1.99 #1 | B36: =Updates!B39 -> Starfighters | C36: 43967 | D36: 0.79166667 | E36: 0.70625 | F36: =CHOOSE(WEEKDAY(C36,2),"Monday","Tuesday","Wednesday","Thursday","Friday","Saturday","Sunday") -> Saturday | G36: =C37-C36 -> 5 | H36: =_xludf.DAYS(C36,Devblogs!BZ2) -> #NAME? | I36: =IF(COUNTIF(Devblogs!BZ2:BZ45,"<"&C36)=COUNTIF(Devblogs!BZ2:BZ45,"<="&C36),COUNTIF(Devblogs!BZ2:BZ45,"<"&C36),CONCATENATE(COUNTIF(Devblogs!BZ2:BZ45,"<"&C36), " - ",COUNTIF(Devblogs!BZ2:BZ45,"<="&C36))) -> 10 - 11
A37: =CONCATENATE(Updates!A39," #2") -> 1.99 #2 | C37: 43972 | D37: 0.79166667 | E37: 0.74305556 | F37: =CHOOSE(WEEKDAY(C37,2),"Monday","Tuesday","Wednesday","Thursday","Friday","Saturday","Sunday") -> Thursday
A38: =CONCATENATE(Updates!A40," #1") -> 1.101 #1 | B38: =Updates!B40 -> Raining Fire | C38: 44065 | D38: 0.79166667 | E38: 0.79791667 | F38: =CHOOSE(WEEKDAY(C38,2),"Monday","Tuesday","Wednesday","Thursday","Friday","Saturday","Sunday") -> Saturday | G38: =C39-C38 -> 4 | H38: =_xludf.DAYS(C38,Devblogs!BW2) -> #NAME? | I38: =IF(COUNTIF(Devblogs!BW2:BW45,"<"&C38)=COUNTIF(Devblogs!BW2:BW45,"<="&C38),COUNTIF(Devblogs!BW2:BW45,"<"&C38),CONCATENATE(COUNTIF(Devblogs!BW2:BW45,"<"&C38), " - ",COUNTIF(Devblogs!BW2:BW45,"<="&C38))) -> 5
A39: =CONCATENATE(Updates!A40," #2") -> 1.101 #2 | C39: 44069 | D39: 0.79166667 | E39: 0.76111111 | F39: =CHOOSE(WEEKDAY(C39,2),"Monday","Tuesday","Wednesday","Thursday","Friday","Saturday","Sunday") -> Wednesday
A40: =CONCATENATE(Updates!A41," #1") -> 2.1 #1 | B40: =Updates!B41 -> New Power | C40: 44138 | D40: 0.8125 | E40: 0.80138889 | F40: =CHOOSE(WEEKDAY(C40,2),"Monday","Tuesday","Wednesday","Thursday","Friday","Saturday","Sunday") -> Tuesday | G40: =C41-C40 -> 7 | H40: =_xludf.DAYS(C40,Devblogs!BT2) -> #NAME? | I40: =IF(COUNTIF(Devblogs!BT2:BT45,"<"&C40)=COUNTIF(Devblogs!BT2:BT45,"<="&C40),COUNTIF(Devblogs!BT2:BT45,"<"&C40),CONCATENATE(COUNTIF(Devblogs!BT2:BT45,"<"&C40), " - ",COUNTIF(Devblogs!BT2:BT45,"<="&C40))) -> 13 - 14
A41: =CONCATENATE(Updates!A41," #2") -> 2.1 #2 | C41: 44145 | D41: 0.79166667 | E41: 0.76111111 | F41: =CHOOSE(WEEKDAY(C41,2),"Monday","Tuesday","Wednesday","Thursday","Friday","Saturday","Sunday") -> Tuesday
A42: =Updates!A42 -> 2.3 | B42: =Updates!B42 -> Hot Tracks | C42: 44177 | D42: 0.83333333 | E42: 0.7375 | F42: =CHOOSE(WEEKDAY(C42,2),"Monday","Tuesday","Wednesday","Thursday","Friday","Saturday","Sunday") -> Saturday | G42: - | H42: =_xludf.DAYS(C42,Devblogs!BQ2) -> #NAME? | I42: =IF(COUNTIF(Devblogs!BQ2:BQ45,"<"&C42)=COUNTIF(Devblogs!BQ2:BQ45,"<="&C42),COUNTIF(Devblogs!BQ2:BQ45,"<"&C42),CONCATENATE(COUNTIF(Devblogs!BQ2:BQ45,"<"&C42), " - ",COUNTIF(Devblogs!BQ2:BQ45,"<="&C42))) -> 5 - 6
A43: =CONCATENATE(Updates!A43," #1") -> 2.5 #1 | B43: =Updates!B43 -> Ixwa Strike | C43: 44248 | D43: 0.79166667 | E43: 0.72916667 | F43: =CHOOSE(WEEKDAY(C43,2),"Monday","Tuesday","Wednesday","Thursday","Friday","Saturday","Sunday") -> Sunday | G43: =C44-C43 -> 10 | H43: =_xludf.DAYS(C43,Devblogs!BN2) -> #NAME? | I43: =IF(COUNTIF(Devblogs!BN2:BN45,"<"&C43)=COUNTIF(Devblogs!BN2:BN45,"<="&C43),COUNTIF(Devblogs!BN2:BN45,"<"&C43),CONCATENATE(COUNTIF(Devblogs!BN2:BN45,"<"&C43), " - ",COUNTIF(Devblogs!BN2:BN45,"<="&C43))) -> 6
A44: =CONCATENATE(Updates!A43," #2") -> 2.5 #2 | C44: 44258 | D44: 0.79166667 | E44: 0.79930556 | F44: =CHOOSE(WEEKDAY(C44,2),"Monday","Tuesday","Wednesday","Thursday","Friday","Saturday","Sunday") -> Wednesday
A45: =CONCATENATE(Updates!A44," #1") -> 2.7 #1 | B45: =Updates!B44 -> Red Skies | C45: 44338 | D45: 0.79166667 | E45: 0.75416667 | F45: =CHOOSE(WEEKDAY(C45,2),"Monday","Tuesday","Wednesday","Thursday","Friday","Saturday","Sunday") -> Saturday | G45: =C46-C45 -> 4 | H45: =_xludf.DAYS(C45,Devblogs!BK2) -> #NAME? | I45: =IF(COUNTIF(Devblogs!BK2:BK45,"<"&C45)=COUNTIF(Devblogs!BK2:BK45,"<="&C45),COUNTIF(Devblogs!BK2:BK45,"<"&C45),CONCATENATE(COUNTIF(Devblogs!BK2:BK45,"<"&C45), " - ",COUNTIF(Devblogs!BK2:BK45,"<="&C45))) -> 8
A46: =CONCATENATE(Updates!A44," #2") -> 2.7 #2 | C46: 44342 | D46: 0.875 | E46: 0.82430556 | F46: =CHOOSE(WEEKDAY(C46,2),"Monday","Tuesday","Wednesday","Thursday","Friday","Saturday","Sunday") -> Wednesday
A47: =CONCATENATE(Updates!A45," #1") -> 2.9 #1 | B47: =Updates!B45 -> Direct Hit | C47: 44436 | D47: 0.70833333 | E47: 0.69513889 | F47: =CHOOSE(WEEKDAY(C47,2),"Monday","Tuesday","Wednesday","Thursday","Friday","Saturday","Sunday") -> Saturday | G47: =C48-C47 -> 4 | H47: =_xludf.DAYS(C47,Devblogs!BH2) -> #NAME? | I47: =IF(COUNTIF(Devblogs!BH2:BH45,"<"&C47)=COUNTIF(Devblogs!BH2:BH45,"<="&C47),COUNTIF(Devblogs!BH2:BH45,"<"&C47),CONCATENATE(COUNTIF(Devblogs!BH2:BH45,"<"&C47), " - ",COUNTIF(Devblogs!BH2:BH45,"<="&C47))) -> 9
A48: =CONCATENATE(Updates!A45," #2") -> 2.9 #2 | C48: 44440 | D48: 0.54166667 | E48: 0.54930556 | F48: =CHOOSE(WEEKDAY(C48,2),"Monday","Tuesday","Wednesday","Thursday","Friday","Saturday","Sunday") -> Wednesday
A49: =CONCATENATE(Updates!A46," #1") -> 2.11 #1 | B49: =Updates!B46 -> Ground Breaking | C49: 44484 | D49: 0.66666667 | E49: 0.72361111 | F49: =CHOOSE(WEEKDAY(C49,2),"Monday","Tuesday","Wednesday","Thursday","Friday","Saturday","Sunday") -> Friday | G49: - | H49: =_xludf.DAYS(C49,Devblogs!BE2) -> #NAME? | I49: =IF(COUNTIF(Devblogs!BE2:BE45,"<"&C49)=COUNTIF(Devblogs!BE2:BE45,"<="&C49),COUNTIF(Devblogs!BE2:BE45,"<"&C49),CONCATENATE(COUNTIF(Devblogs!BE2:BE45,"<"&C49), " - ",COUNTIF(Devblogs!BE2:BE45,"<="&C49))) -> 5 - 7
A50: =CONCATENATE(Updates!A46," #2") -> 2.11 #2 | C50: 44489 | D50: 0.45833333 | E50: 0.47152778 | F50: =CHOOSE(WEEKDAY(C50,2),"Monday","Tuesday","Wednesday","Thursday","Friday","Saturday","Sunday") -> Wednesday | G50: =C50-C49 -> 5
A51: =CONCATENATE(Updates!A46," #3") -> 2.11 #3 | C51: 44490 | D51: 0.75 | E51: 0.75972222 | F51: =CHOOSE(WEEKDAY(C51,2),"Monday","Tuesday","Wednesday","Thursday","Friday","Saturday","Sunday") -> Thursday | G51: =C51-C50 -> 1
A52: =CONCATENATE(Updates!A47," #1") -> 2.13 #1 | B52: =Updates!B47 -> Winged Lions | C52: 44533 | D52: 0.66666667 | E52: 0.67152778 | F52: =CHOOSE(WEEKDAY(C52,2),"Monday","Tuesday","Wednesday","Thursday","Friday","Saturday","Sunday") -> Friday | G52: =C53-C52 -> 5 | H52: =_xludf.DAYS(C52,Devblogs!BB2) -> #NAME? | I52: =IF(COUNTIF(Devblogs!BB2:BB45,"<"&C52)=COUNTIF(Devblogs!BB2:BB45,"<="&C52),COUNTIF(Devblogs!BB2:BB45,"<"&C52),CONCATENATE(COUNTIF(Devblogs!BB2:BB45,"<"&C52), " - ",COUNTIF(Devblogs!BB2:BB45,"<="&C52))) -> 5 - 7
A53: =CONCATENATE(Updates!A47," #2") -> 2.13 #2 | C53: 44538 | D53: 0.5 | E53: 0.50138889 | F53: =CHOOSE(WEEKDAY(C53,2),"Monday","Tuesday","Wednesday","Thursday","Friday","Saturday","Sunday") -> Wednesday
A54: =CONCATENATE(Updates!A48," #1") -> 2.15 #1 | B54: =Updates!B48 -> Wind of Change | C54: 44631 | D54: 0.66666667 | E54: 0.67013889 | F54: =CHOOSE(WEEKDAY(C54,2),"Monday","Tuesday","Wednesday","Thursday","Friday","Saturday","Sunday") -> Friday | G54: =C55-C54 -> 5 | H54: =_xludf.DAYS(C54,Devblogs!AY2) -> #NAME? | I54: =IF(COUNTIF(Devblogs!AY2:AY45,"<"&C54)=COUNTIF(Devblogs!AY2:AY45,"<="&C54),COUNTIF(Devblogs!AY2:AY45,"<"&C54),CONCATENATE(COUNTIF(Devblogs!AY2:AY45,"<"&C54), " - ",COUNTIF(Devblogs!AY2:AY45,"<="&C54))) -> 6 - 8
A55: =CONCATENATE(Updates!A48," #2") -> 2.15 #2 | C55: 44636 | D55: 0.66666667 | E55: 0.69027778 | F55: =CHOOSE(WEEKDAY(C55,2),"Monday","Tuesday","Wednesday","Thursday","Friday","Saturday","Sunday") -> Wednesday
A56: =CONCATENATE(Updates!A49," #1") -> 2.17 #1 | B56: =Updates!B49 -> Danger Zone | C56: 44708 | D56: 0.75 | E56: 0.75833333 | F56: =CHOOSE(WEEKDAY(C56,2),"Monday","Tuesday","Wednesday","Thursday","Friday","Saturday","Sunday") -> Friday | G56: =C57-C56 -> 7 | H56: =_xludf.DAYS(C56,Devblogs!AV2) -> #NAME? | I56: =IF(COUNTIF(Devblogs!AV2:AV45,"<"&C56)=COUNTIF(Devblogs!AV2:AV45,"<="&C56),COUNTIF(Devblogs!AV2:AV45,"<"&C56),CONCATENATE(COUNTIF(Devblogs!AV2:AV45,"<"&C56), " - ",COUNTIF(Devblogs!AV2:AV45,"<="&C56))) -> 8 - 9
A57: =CONCATENATE(Updates!A49," #2") -> 2.17 #2 | C57: 44715 | D57: 0.66666667 | E57: 0.66736111 | F57: =CHOOSE(WEEKDAY(C57,2),"Monday","Tuesday","Wednesday","Thursday","Friday","Saturday","Sunday") -> Friday
A58: =Updates!A50 -> 2.19 | B58: =Updates!B50 -> Drone Age | C58: 44806 | D58: 0.75 | E58: 0.75555556 | F58: =CHOOSE(WEEKDAY(C58,2),"Monday","Tuesday","Wednesday","Thursday","Friday","Saturday","Sunday") -> Friday | G58: - | H58: =_xludf.DAYS(C58,Devblogs!AS2) -> #NAME? | I58: =IF(COUNTIF(Devblogs!AS2:AS45,"<"&C58)=COUNTIF(Devblogs!AS2:AS45,"<="&C58),COUNTIF(Devblogs!AS2:AS45,"<"&C58),CONCATENATE(COUNTIF(Devblogs!AS2:AS45,"<"&C58), " - ",COUNTIF(Devblogs!AS2:AS45,"<="&C58))) -> 12 - 14
A59: =Updates!A51 -> 2.21 | B59: =Updates!B51 -> Fire and Ice | C59: 44848 | D59: 0.70833333 | E59: 0.72361111 | F59: =CHOOSE(WEEKDAY(C59,2),"Monday","Tuesday","Wednesday","Thursday","Friday","Saturday","Sunday") -> Friday | G59: - | H59: =_xludf.DAYS(C59,Devblogs!AP2) -> #NAME? | I59: =IF(COUNTIF(Devblogs!AP2:AP45,"<"&C59)=COUNTIF(Devblogs!AP2:AP45,"<="&C59),COUNTIF(Devblogs!AP2:AP45,"<"&C59),CONCATENATE(COUNTIF(Devblogs!AP2:AP45,"<"&C59), " - ",COUNTIF(Devblogs!AP2:AP45,"<="&C59))) -> 2 - 4
A60: =Updates!A52 -> 2.23 | B60: =Updates!B52 -> Apex Predators | C60: 44904 | D60: 0.66666667 | E60: 0.67291667 | F60: =CHOOSE(WEEKDAY(C60,2),"Monday","Tuesday","Wednesday","Thursday","Friday","Saturday","Sunday") -> Friday | G60: - | H60: =_xludf.DAYS(C60,Devblogs!AM2) -> #NAME? | I60: =IF(COUNTIF(Devblogs!AM2:AM45,"<"&C60)=COUNTIF(Devblogs!AM2:AM45,"<="&C60),COUNTIF(Devblogs!AM2:AM45,"<"&C60),CONCATENATE(COUNTIF(Devblogs!AM2:AM45,"<"&C60), " - ",COUNTIF(Devblogs!AM2:AM45,"<="&C60))) -> 6 - 8
A61: =Updates!A53 -> 2.25 | B61: =Updates!B53 -> Sky Guardians | C61: 44982 | D61: 0.625 | E61: 0.67916667 | F61: =CHOOSE(WEEKDAY(C61,2),"Monday","Tuesday","Wednesday","Thursday","Friday","Saturday","Sunday") -> Saturday | G61: - | H61: =IF(_xludf.DAYS(C61,Devblogs!AJ2)>-1,_xludf.DAYS(C61,Devblogs!AJ2),0) -> #NAME? | I61: =IF(COUNTIF(Devblogs!AJ2:AJ45,"<"&C61)=COUNTIF(Devblogs!AJ2:AJ45,"<="&C61),COUNTIF(Devblogs!AJ2:AJ45,"<"&C61),CONCATENATE(COUNTIF(Devblogs!AJ2:AJ45,"<"&C61), " - ",COUNTIF(Devblogs!AJ2:AJ45,"<="&C61))) -> 11
A62: =CONCATENATE(Updates!A54," #1") -> 2.27 #1 | B62: =Updates!B54 -> La Royale | C62: 45065 | D62: 0.625 | E62: 0.67986111 | F62: =CHOOSE(WEEKDAY(C62,2),"Monday","Tuesday","Wednesday","Thursday","Friday","Saturday","Sunday") -> Friday | G62: =C63-C62 -> 11 | H62: =_xludf.DAYS(C62,Devblogs!AG2) -> #NAME? | I62: =IF(COUNTIF(Devblogs!AG2:AG45,"<"&C62)=COUNTIF(Devblogs!AG2:AG45,"<="&C62),COUNTIF(Devblogs!AG2:AG45,"<"&C62),CONCATENATE(COUNTIF(Devblogs!AG2:AG45,"<"&C62), " - ",COUNTIF(Devblogs!AG2:AG45,"<="&C62))) -> 12
A63: =CONCATENATE(Updates!A54," #2") -> 2.27 #2 | C63: 45076 | D63: 0.625 | E63: 0.5625 | F63: =CHOOSE(WEEKDAY(C63,2),"Monday","Tuesday","Wednesday","Thursday","Friday","Saturday","Sunday") -> Tuesday
A64: =CONCATENATE(Updates!A55," #1") -> 2.29 #1 | B64: =Updates!B55 -> Sons of Attila | C64: 45170 | D64: 0.66666667 | E64: 0.69583333 | F64: =CHOOSE(WEEKDAY(C64,2),"Monday","Tuesday","Wednesday","Thursday","Friday","Saturday","Sunday") -> Friday | G64: =C65-C64 -> 11 | H64: =_xludf.DAYS(C64,Devblogs!AD2) -> #NAME? | I64: =IF(COUNTIF(Devblogs!AD2:AD45,"<"&C64)=COUNTIF(Devblogs!AD2:AD45,"<="&C64),COUNTIF(Devblogs!AD2:AD45,"<"&C64),CONCATENATE(COUNTIF(Devblogs!AD2:AD45,"<"&C64), " - ",COUNTIF(Devblogs!AD2:AD45,"<="&C64))) -> 9 - 12
A65: =CONCATENATE(Updates!A55," #2") -> 2.29 #2 | C65: 45181 | D65: 0.625 | E65: 0.61666667 | F65: =CHOOSE(WEEKDAY(C65,2),"Monday","Tuesday","Wednesday","Thursday","Friday","Saturday","Sunday") -> Tuesday
A66: =Updates!A56 -> 2.31 | B66: =Updates!B56 -> Kings of Battle | C66: 45219 | D66: 0.625 | E66: 0.62708333 | F66: =CHOOSE(WEEKDAY(C66,2),"Monday","Tuesday","Wednesday","Thursday","Friday","Saturday","Sunday") -> Friday | G66: - | H66: =_xludf.DAYS(C66,Devblogs!AA2) -> #NAME? | I66: =IF(COUNTIF(Devblogs!AA2:AA45,"<"&C66)=COUNTIF(Devblogs!AA2:AA45,"<="&C66),COUNTIF(Devblogs!AA2:AA45,"<"&C66),CONCATENATE(COUNTIF(Devblogs!AA2:AA45,"<"&C66), " - ",COUNTIF(Devblogs!AA2:AA45,"<="&C66))) -> 2 - 3
A67: =Updates!A57 -> 2.33 | B67: =Updates!B57 -> Air Superiority | C67: 45267 | D67: 0.6875 | E67: 0.6875 | F67: =CHOOSE(WEEKDAY(C67,2),"Monday","Tuesday","Wednesday","Thursday","Friday","Saturday","Sunday") -> Thursday | G67: - | H67: =IF(_xludf.DAYS(C67,Devblogs!X2)>-1,_xludf.DAYS(C67,Devblogs!X2),0) -> #NAME? | I67: =IF(COUNTIF(Devblogs!X2:X45,"<"&C67)=COUNTIF(Devblogs!X2:X45,"<="&C67),COUNTIF(Devblogs!X2:X45,"<"&C67),CONCATENATE(COUNTIF(Devblogs!X2:X45,"<"&C67), " - ",COUNTIF(Devblogs!X2:X45,"<="&C67))) -> 4 - 6
A68: =Updates!A58 -> 2.35 | B68: =Updates!B58 -> Alpha Strike | C68: 45352 | D68: 0.67708333 | E68: 0.67777778 | F68: =CHOOSE(WEEKDAY(C68,2),"Monday","Tuesday","Wednesday","Thursday","Friday","Saturday","Sunday") -> Friday | G68: - | H68: =_xludf.DAYS(C68,Devblogs!U2) -> #NAME? | I68: =IF(COUNTIF(Devblogs!U2:U45,"<"&C68)=COUNTIF(Devblogs!U2:U45,"<="&C68),COUNTIF(Devblogs!U2:U45,"<"&C68),CONCATENATE(COUNTIF(Devblogs!U2:U45,"<"&C68), " - ",COUNTIF(Devblogs!U2:U45,"<="&C68))) -> 5 - 7
A69: =Updates!A59 -> 2.37 | B69: =Updates!B59 -> Seek & Destroy | C69: 45443 | D69: 0.70833333 | E69: - | F69: =CHOOSE(WEEKDAY(C69,2),"Monday","Tuesday","Wednesday","Thursday","Friday","Saturday","Sunday") -> Friday | G69: - | H69: =_xludf.DAYS(C69,Devblogs!R2) -> #NAME? | I69: =IF(COUNTIF(Devblogs!R$2:R$45,"<"&C69)=COUNTIF(Devblogs!R$2:R$45,"<="&C69),COUNTIF(Devblogs!R$2:R$45,"<"&C69),CONCATENATE(COUNTIF(Devblogs!R$2:R$45,"<"&C69), " - ",COUNTIF(Devblogs!R$2:R$45,"<="&C69))) -> 7 - 10
A70: =Updates!A60 -> 2.39 | B70: =Updates!B60 -> Dance of Dragons | C70: 45534 | D70: 0.66666667 | E70: - | F70: =CHOOSE(WEEKDAY(C70,2),"Monday","Tuesday","Wednesday","Thursday","Friday","Saturday","Sunday") -> Friday | G70: - | H70: =IF(_xludf.DAYS(C70,Devblogs!O$2)>-1,_xludf.DAYS(C70,Devblogs!O$2),0) -> #NAME? | I70: =IF(COUNTIF(Devblogs!O$2:O$45,"<"&C70)=COUNTIF(Devblogs!O$2:O$45,"<="&C70),COUNTIF(Devblogs!O$2:O$45,"<"&C70),CONCATENATE(COUNTIF(Devblogs!O$2:O$45,"<"&C70), " - ",COUNTIF(Devblogs!O$2:O$45,"<="&C70))) -> 4 - 7
A71: =Updates!A61 -> 2.41 | B71: =Updates!B61 -> Firebirds | C71: 45590 | D71: 0.79166667 | E71: - | F71: =CHOOSE(WEEKDAY(C71,2),"Monday","Tuesday","Wednesday","Thursday","Friday","Saturday","Sunday") -> Friday | G71: - | H71: =IF(_xludf.DAYS(C71,Devblogs!L$2)>-1,_xludf.DAYS(C71,Devblogs!L$2),0) -> #NAME? | I71: =IF(COUNTIF(Devblogs!L$2:L$45,"<"&C71)=COUNTIF(Devblogs!L$2:L$45,"<="&C71),COUNTIF(Devblogs!L$2:L$45,"<"&C71),CONCATENATE(COUNTIF(Devblogs!L$2:L$45,"<"&C71), " - ",COUNTIF(Devblogs!L$2:L$45,"<="&C71))) -> 6 - 8
A72: =Updates!A62 -> 2.43 | B72: =Updates!B62 -> Storm Warning | C72: 45636 | D72: 0.625 | E72: - | F72: =CHOOSE(WEEKDAY(C72,2),"Monday","Tuesday","Wednesday","Thursday","Friday","Saturday","Sunday") -> Tuesday | G72: - | H72: =IF(_xludf.DAYS(C72,Devblogs!I$2)>-1,_xludf.DAYS(C72,Devblogs!I$2),0) -> #NAME? | I72: =IF(COUNTIF(Devblogs!I$2:I$45,"<"&C72)=COUNTIF(Devblogs!I$2:I$45,"<="&C72),COUNTIF(Devblogs!I$2:I$45,"<"&C72),CONCATENATE(COUNTIF(Devblogs!I$2:I$45,"<"&C72), " - ",COUNTIF(Devblogs!I$2:I$45,"<="&C72))) -> 4 - 5
A73: =Updates!A63 -> 2.45 | B73: =Updates!B63 -> 0 | H73: =IF(_xludf.DAYS(C73,Devblogs!L$2)>-1,_xludf.DAYS(C73,Devblogs!L$2),0) -> #NAME? | I73: =IF(COUNTIF(Devblogs!L$2:L$45,"<"&C73)=COUNTIF(Devblogs!L$2:L$45,"<="&C73),COUNTIF(Devblogs!L$2:L$45,"<"&C73),CONCATENATE(COUNTIF(Devblogs!L$2:L$45,"<"&C73), " - ",COUNTIF(Devblogs!L$2:L$45,"<="&C73))) -> 0
B76: First dev servers | F76: Average start time | G76: =AVERAGE(D3:D75) -> 0.74032738
B77: Monday: | C77: 1 | D77: =C77/SUM($C$77:$C$83) -> 0.024390244 | F77: Average announcement time | G77: =AVERAGE(E3:E75) -> 0.72362163
B78: Tuesday: | C78: 3 | D78: =C78/SUM($C$77:$C$83) -> 0.073170732
B79: Wednesday: | C79: 2 | D79: =C79/SUM($C$77:$C$83) -> 0.048780488
B80: Thursday: | C80: 6 | D80: =C80/SUM($C$77:$C$83) -> 0.14634146 | I80: *: discrepancy is due to the inclusion of same day devblogs
B81: Friday: | C81: 13 | D81: =C81/SUM($C$77:$C$83) -> 0.31707317
B82: Saturday: | C82: 14 | D82: =C82/SUM($C$77:$C$83) -> 0.34146341
B83: Sunday: | C83: 2 | D83: =C83/SUM($C$77:$C$83) -> 0.048780488
B85: Second and third dev servers | F85: Dev servers
B86: Monday: | C86: 1 | D86: =C86/SUM($C$86:$C$92) -> 0.04 | F86: Monday: | G86: =COUNTIF(F3:F75,"Monday") -> 2 | H86: =G86/SUM($G$86:$G$92) -> 0.028571429
B87: Tuesday: | C87: 3 | D87: =C87/SUM($C$86:$C$92) -> 0.12 | F87: Tuesday: | G87: =COUNTIF(F3:F75,"Tuesday") -> 8 | H87: =G87/SUM($G$86:$G$92) -> 0.11428571
B88: Wednesday: | C88: 8 | D88: =C88/SUM($C$86:$C$92) -> 0.32 | F88: Wednesday: | G88: =COUNTIF(F3:F75,"Wednesday") -> 10 | H88: =G88/SUM($G$86:$G$92) -> 0.14285714
B89: Thursday: | C89: 5 | D89: =C89/SUM($C$86:$C$92) -> 0.2 | F89: Thursday: | G89: =COUNTIF(F3:F75,"Thursday") -> 11 | H89: =G89/SUM($G$86:$G$92) -> 0.15714286
B90: Friday: | C90: 1 | D90: =C90/SUM($C$86:$C$92) -> 0.04 | F90: Friday: | G90: =COUNTIF(F3:F75,"Friday") -> 16 | H90: =G90/SUM($G$86:$G$92) -> 0.22857143
B91: Saturday: | C91: 7 | D91: =C91/SUM($C$86:$C$92) -> 0.28 | F91: Saturday: | G91: =COUNTIF(F3:F75,"Saturday") -> 21 | H91: =G91/SUM($G$86:$G$92) -> 0.3
B92: Sunday: | C92: 0 | D92: =C92/SUM($C$86:$C$92) -> 0 | F92: Sunday: | G92: =COUNTIF(F3:F75,"Sunday") -> 2 | H92: =G92/SUM($G$86:$G$92) -> 0.028571429

Sheet Summary
A1: Summary
A2: Version | B2: Name | C2: Leak | E2: First devblog | G2: Teaser | I2: Dev stream | K2: Dev server | M2: Release
A3: =Updates!A33 -> 1.87 | B3: =Updates!B33 -> Locked On | C3: - | E3: =Devblogs!CR$2 -> 43511 | F3: =Devblogs!CS$2 -> Friday | G3: - | I3: ='Dev streams'!C3 -> 43523 | J3: ='Dev streams'!D3 -> Wednesday | K3: ='Dev servers'!C26 -> 43526 | L3: ='Dev servers'!F26 -> Saturday | M3: =Updates!C33 -> 43536 | N3: =Updates!D33 -> Tuesday
K4: ='Dev servers'!C27 -> 43530 | L4: ='Dev servers'!F27 -> Wednesday
A5: =Updates!A34 -> 1.89 | B5: =Updates!B34 -> Imperial Navy | C5: - | E5: =Devblogs!CO$2 -> 43588 | F5: =Devblogs!CP$2 -> Friday | G5: - | I5: ='Dev streams'!C4 -> 43602 | J5: ='Dev streams'!D4 -> Friday | K5: ='Dev servers'!C28 -> 43603 | L5: ='Dev servers'!F28 -> Saturday | M5: =Updates!C34 -> 43614 | N5: =Updates!D34 -> Wednesday
K6: ='Dev servers'!C29 -> 43610 | L6: ='Dev servers'!F29 -> Saturday
A7: =Updates!A35 -> 1.91 | B7: =Updates!B35 -> Night Vision | C7: - | E7: =Devblogs!CL$2 -> 43690 | F7: =Devblogs!CM$2 -> Tuesday | G7: - | I7: ='Dev streams'!C5 -> 43707 | J7: ='Dev streams'!D5 -> Friday | K7: ='Dev servers'!C30 -> 43708 | L7: ='Dev servers'!F30 -> Saturday | M7: =Updates!C35 -> 43719 | N7: =Updates!D35 -> Wednesday
K8: ='Dev servers'!C31 -> 43713 | L8: ='Dev servers'!F31 -> Thursday
A9: =Updates!A36 -> 1.93 | B9: =Updates!B36 -> Shark Attack | C9: - | E9: =Devblogs!CI$2 -> 43749 | F9: =Devblogs!CJ$2 -> Friday | G9: - | I9: ='Dev streams'!C6 -> 43762 | J9: ='Dev streams'!D6 -> Thursday | K9: ='Dev servers'!C32 -> 43762 | L9: ='Dev servers'!F32 -> Thursday | M9: =Updates!C36 -> 43767 | N9: =Updates!D36 -> Tuesday
A10: =Updates!A37 -> 1.95 | B10: =Updates!B37 -> Northern Wind | C10: - | E10: =Devblogs!CF$2 -> 43797 | F10: =Devblogs!CG$2 -> Thursday | G10: - | I10: ='Dev streams'!C7 -> 43811 | J10: ='Dev streams'!D7 -> Thursday | K10: ='Dev servers'!C33 -> 43811 | L10: ='Dev servers'!F33 -> Thursday | M10: =Updates!C37 -> 43816 | N10: =Updates!D37 -> Tuesday
A11: =Updates!A38 -> 1.97 | B11: =Updates!B38 -> Viking Fury | C11: - | E11: =Devblogs!CC$2 -> 43881 | F11: =Devblogs!CD$2 -> Thursday | G11: - | I11: ='Dev streams'!C8 -> 43893 | J11: ='Dev streams'!D8 -> Tuesday | K11: ='Dev servers'!C34 -> 43893 | L11: ='Dev servers'!F34 -> Tuesday | M11: =Updates!C38 -> 43906 | N11: =Updates!D38 -> Monday
K12: ='Dev servers'!C35 -> 43897 | L12: ='Dev servers'!F35 -> Saturday
A13: =Updates!A39 -> 1.99 | B13: =Updates!B39 -> Starfighters | C13: - | E13: =Devblogs!BZ$2 -> 43956 | F13: =Devblogs!CA$2 -> Tuesday | G13: - | I13: ='Dev streams'!C9 -> 43966 | J13: ='Dev streams'!D9 -> Friday | K13: ='Dev servers'!C36 -> 43967 | L13: ='Dev servers'!F36 -> Saturday | M13: =Updates!C39 -> 43977 | N13: =Updates!D39 -> Tuesday
K14: ='Dev servers'!C37 -> 43972 | L14: ='Dev servers'!F37 -> Thursday
A15: =Updates!A40 -> 1.101 | B15: =Updates!B40 -> Raining Fire | C15: - | E15: =Devblogs!BW$2 -> 44057 | F15: =Devblogs!BX$2 -> Friday | G15: - | I15: ='Dev streams'!C10 -> 44064 | J15: ='Dev streams'!D10 -> Friday | K15: ='Dev servers'!C38 -> 44065 | L15: ='Dev servers'!F38 -> Saturday | M15: =Updates!C40 -> 44076 | N15: =Updates!D40 -> Wednesday
K16: ='Dev servers'!C39 -> 44069 | L16: ='Dev servers'!F39 -> Wednesday
A17: =Updates!A41 -> 2.1 | B17: =Updates!B41 -> New Power | C17: - | E17: =Devblogs!BT$2 -> 44124 | F17: =Devblogs!BU$2 -> Tuesday | G17: =Teasers!C3 -> 44127 | H17: =Teasers!E3 -> Friday | I17: ='Dev streams'!C11 -> 44134 | J17: ='Dev streams'!D11 -> Friday | K17: ='Dev servers'!C40 -> 44138 | L17: ='Dev servers'!F40 -> Tuesday | M17: =Updates!C41 -> 44152 | N17: =Updates!D41 -> Tuesday
K18: ='Dev servers'!C41 -> 44145 | L18: ='Dev servers'!F41 -> Tuesday
A19: =Updates!A42 -> 2.3 | B19: =Updates!B42 -> Hot Tracks | C19: - | E19: =Devblogs!BQ$2 -> 44172 | F19: =Devblogs!BR$2 -> Monday | G19: - | I19: ='Dev streams'!C12 -> 44176 | J19: ='Dev streams'!D12 -> Friday | K19: ='Dev servers'!C42 -> 44177 | L19: ='Dev servers'!F42 -> Saturday | M19: =Updates!C42 -> 44183 | N19: =Updates!D42 -> Friday
A20: =Updates!A43 -> 2.5 | B20: =Updates!B43 -> Ixwa Strike | C20: - | E20: =Devblogs!BN$2 -> 44242 | F20: =Devblogs!BO$2 -> Monday | G20: =Teasers!C4 -> 44245 | H20: =Teasers!E4 -> Thursday | I20: ='Dev streams'!C13 -> 44247 | J20: ='Dev streams'!D13 -> Saturday | K20: ='Dev servers'!C43 -> 44248 | L20: ='Dev servers'!F43 -> Sunday | M20: =Updates!C43 -> 44265 | N20: =Updates!D43 -> Wednesday
K21: ='Dev servers'!C44 -> 44258 | L21: ='Dev servers'!F44 -> Wednesday
A22: =Updates!A44 -> 2.7 | B22: =Updates!B44 -> Red Skies | C22: - | E22: =Devblogs!BK$2 -> 44328 | F22: =Devblogs!BL$2 -> Wednesday | G22: =Teasers!C5 -> 44336 | H22: =Teasers!E5 -> Thursday | I22: ='Dev streams'!C14 -> 44337 | J22: ='Dev streams'!D14 -> Friday | K22: ='Dev servers'!C45 -> 44338 | L22: ='Dev servers'!F45 -> Saturday | M22: =Updates!C44 -> 44349 | N22: =Updates!D44 -> Wednesday
K23: ='Dev servers'!C46 -> 44342 | L23: ='Dev servers'!F46 -> Wednesday
A24: =Updates!A45 -> 2.9 | B24: =Updates!B45 -> Direct Hit | C24: - | E24: =Devblogs!BH$2 -> 44426 | F24: =Devblogs!BI$2 -> Wednesday | G24: =Teasers!C6 -> 44432 | H24: =Teasers!E6 -> Tuesday | I24: ='Dev streams'!C15 -> 44435 | J24: ='Dev streams'!D15 -> Friday | K24: ='Dev servers'!C47 -> 44436 | L24: ='Dev servers'!F47 -> Saturday | M24: =Updates!C45 -> 44446 | N24: =Updates!D45 -> Tuesday
K25: ='Dev servers'!C48 -> 44440 | L25: ='Dev servers'!F48 -> Wednesday
A26: =Updates!A46 -> 2.11 | B26: =Updates!B46 -> Ground Breaking | C26: - | E26: =Devblogs!BE$2 -> 44477 | F26: =Devblogs!BF$2 -> Friday | G26: =Teasers!C7 -> 44481 | H26: =Teasers!E7 -> Tuesday | I26: ='Dev streams'!C16 -> 44484 | J26: ='Dev streams'!D16 -> Friday | K26: ='Dev servers'!C49 -> 44484 | L26: ='Dev servers'!F49 -> Friday | M26: =Updates!C46 -> 44497 | N26: =Updates!D46 -> Thursday
K27: ='Dev servers'!C50 -> 44489 | L27: ='Dev servers'!F50 -> Wednesday
K28: ='Dev servers'!C51 -> 44490 | L28: ='Dev servers'!F51 -> Thursday
A29: =Updates!A47 -> 2.13 | B29: =Updates!B47 -> Winged Lions | C29: - | E29: =Devblogs!BB$2 -> 44530 | F29: =Devblogs!BC$2 -> Tuesday | G29: =Teasers!C8 -> 44532 | H29: =Teasers!E8 -> Thursday | I29: ='Dev streams'!C17 -> 44533 | J29: ='Dev streams'!D17 -> Friday | K29: ='Dev servers'!C52 -> 44533 | L29: ='Dev servers'!F52 -> Friday | M29: =Updates!C47 -> 44544 | N29: =Updates!D47 -> Tuesday
K30: ='Dev servers'!C53 -> 44538 | L30: ='Dev servers'!F53 -> Wednesday
A31: =Updates!A48 -> 2.15 | B31: =Updates!B48 -> Wind of Change | C31: - | E31: =Devblogs!AY$2 -> 44610 | F31: =Devblogs!AZ$2 -> Friday | G31: =Teasers!C9 -> 44630 | H31: =Teasers!E9 -> Thursday | I31: ='Dev streams'!C18 -> 44631 | J31: ='Dev streams'!D18 -> Friday | K31: ='Dev servers'!C54 -> 44631 | L31: ='Dev servers'!F54 -> Friday | M31: =Updates!C48 -> 44644 | N31: =Updates!D48 -> Thursday
K32: ='Dev servers'!C55 -> 44636 | L32: ='Dev servers'!F55 -> Wednesday
A33: =Updates!A49 -> 2.17 | B33: =Updates!B49 -> Danger Zone | C33: - | E33: =Devblogs!AV$2 -> 44699 | F33: =Devblogs!AW$2 -> Wednesday | G33: =Teasers!C10 -> 44707 | H33: =Teasers!E10 -> Thursday | I33: ='Dev streams'!C19 -> 44708 | J33: ='Dev streams'!D19 -> Friday | K33: ='Dev servers'!C56 -> 44708 | L33: ='Dev servers'!F56 -> Friday | M33: =Updates!C49 -> 44727 | N33: =Updates!D49 -> Wednesday
K34: ='Dev servers'!C57 -> 44715 | L34: ='Dev servers'!F57 -> Friday
A35: =Updates!A50 -> 2.19 | B35: =Updates!B50 -> Drone Age | C35: - | E35: =Devblogs!AS$2 -> 44789 | F35: =Devblogs!AT$2 -> Tuesday | G35: =Teasers!C12 -> 44805 | H35: =Teasers!E12 -> Thursday | I35: ='Dev streams'!C20 -> 44806 | J35: ='Dev streams'!D21 -> Friday | K35: ='Dev servers'!C58 -> 44806 | L35: ='Dev servers'!F58 -> Friday | M35: =Updates!C50 -> 44818 | N35: =Updates!D50 -> Wednesday
A36: =Updates!A51 -> 2.21 | B36: =Updates!B51 -> Fire and Ice | C36: - | E36: =Devblogs!AP$2 -> 44846 | F36: =Devblogs!AQ$2 -> Wednesday | G36: =Teasers!C13 -> 44847 | H36: =Teasers!E13 -> Thursday | I36: ='Dev streams'!C21 -> 44848 | J36: ='Dev streams'!D21 -> Friday | K36: ='Dev servers'!C59 -> 44848 | L36: ='Dev servers'!F59 -> Friday | M36: =Updates!C51 -> 44860 | N36: =Updates!D51 -> Wednesday
A37: =Updates!A52 -> 2.23 | B37: =Updates!B52 -> Apex Predators | C37: - | E37: =Devblogs!AM$2 -> 44894 | F37: =Devblogs!AN$2 -> Tuesday | G37: =Teasers!C14 -> 44903 | H37: =Teasers!E14 -> Thursday | I37: ='Dev streams'!C22 -> 44904 | J37: ='Dev streams'!D22 -> Friday | K37: ='Dev servers'!C60 -> 44904 | L37: ='Dev servers'!F60 -> Friday | M37: =Updates!C52 -> 44915 | N37: =Updates!D52 -> Tuesday
A38: =Updates!A53 -> 2.25 | B38: =Updates!B53 -> Sky Guardians | C38: - | E38: =Devblogs!AJ$2 -> 44967 | F38: =Devblogs!AK$2 -> Friday | G38: =Teasers!C15 -> 44980 | H38: =Teasers!E15 -> Thursday | I38: ='Dev streams'!C23 -> 44982 | J38: ='Dev streams'!D23 -> Saturday | K38: ='Dev servers'!C61 -> 44982 | L38: ='Dev servers'!F61 -> Saturday | M38: =Updates!C53 -> 44992 | N38: =Updates!D53 -> Tuesday
A39: =Updates!A54 -> 2.27 | B39: =Updates!B54 -> La Royale | C39: - | E39: =Devblogs!AG$2 -> 45037 | F39: =Devblogs!AH$2 -> Friday | G39: =Teasers!C16 -> 45064 | H39: =Teasers!E16 -> Thursday | I39: ='Dev streams'!C24 -> 45065 | J39: ='Dev streams'!D24 -> Friday | K39: ='Dev servers'!C62 -> 45065 | L39: ='Dev servers'!F62 -> Friday | M39: =Updates!C54 -> 45091 | N39: =Updates!D54 -> Wednesday
K40: ='Dev servers'!C63 -> 45076 | L40: ='Dev servers'!F63 -> Tuesday
A41: =Updates!A55 -> 2.29 | B41: =Updates!B55 -> Sons of Attila | C41: =Leaks!C$3 -> 45160 | D41: =Leaks!D$3 -> Tuesday | E41: =Devblogs!AD$2 -> 45159 | F41: =Devblogs!AE$2 -> Monday | G41: =Teasers!C17 -> 45169 | H41: =Teasers!E17 -> Thursday | I41: ='Dev streams'!C25 -> 45170 | J41: ='Dev streams'!D25 -> Friday | K41: ='Dev servers'!C64 -> 45170 | L41: ='Dev servers'!F64 -> Friday | M41: =Updates!C55 -> 45188 | N41: =Updates!D55 -> Tuesday
K42: ='Dev servers'!C65 -> 45181 | L42: ='Dev servers'!F65 -> Tuesday
A43: =Updates!A56 -> 2.31 | B43: =Updates!B56 -> Kings of Battle | C43: =Leaks!C$4 -> 45209 | D43: =Leaks!D$4 -> Tuesday | E43: =Devblogs!AA$2 -> 45212 | F43: =Devblogs!AB$2 -> Friday | G43: =Teasers!C18 -> 45218 | H43: =Teasers!E18 -> Thursday | I43: ='Dev streams'!C26 -> 45219 | J43: ='Dev streams'!D26 -> Friday | K43: ='Dev servers'!C66 -> 45219 | L43: ='Dev servers'!F66 -> Friday | M43: =Updates!C56 -> 45230 | N43: =Updates!D56 -> Tuesday
A44: =Updates!A57 -> 2.33 | B44: =Updates!B57 -> Air Superiority | C44: =Leaks!C$5 -> 45254 | D44: =Leaks!D$5 -> Friday | E44: =Devblogs!X$2 -> 45261 | F44: =Devblogs!Y$2 -> Friday | G44: =Teasers!C19 -> 45266 | H44: =Teasers!E19 -> Wednesday | I44: ='Dev streams'!C27 -> 45267 | J44: ='Dev streams'!D27 -> Thursday | K44: ='Dev servers'!C67 -> 45267 | L44: ='Dev servers'!F67 -> Thursday | M44: =Updates!C57 -> 45274 | N44: =Updates!D57 -> Thursday
A45: =Updates!A58 -> 2.35 | B45: =Updates!B58 -> Alpha Strike | C45: =Leaks!C$6 -> 45344 | D45: =Leaks!D$6 -> Thursday | E45: =Devblogs!U$2 -> 45344 | F45: =Devblogs!V$2 -> Thursday | G45: =Teasers!C20 -> 45351 | H45: =Teasers!E20 -> Thursday | I45: ='Dev streams'!C28 -> 45352 | J45: ='Dev streams'!D28 -> Friday | K45: ='Dev servers'!C68 -> 45352 | L45: ='Dev servers'!F68 -> Friday | M45: =Updates!C58 -> 45364 | N45: =Updates!D58 -> Wednesday
A46: =Updates!A59 -> 2.37 | B46: =Updates!B59 -> Seek & Destroy | C46: =Leaks!C7 -> 45416 | D46: =Leaks!D$7 -> Saturday | E46: =Devblogs!R$2 -> 45436 | F46: =Devblogs!S$2 -> Friday | G46: =Teasers!C21 -> 45442 | H46: =Teasers!E21 -> Thursday | I46: ='Dev streams'!C29 -> 45443 | J46: ='Dev streams'!D29 -> Friday | K46: ='Dev servers'!C69 -> 45443 | L46: ='Dev servers'!F69 -> Friday | M46: =Updates!C59 -> 45462 | N46: =Updates!D59 -> Wednesday
A47: =Updates!A60 -> 2.39 | B47: =Updates!B60 -> Dance of Dragons | C47: =Leaks!C$8 -> 45515 | D47: =Leaks!D$8 -> Sunday | E47: =Devblogs!O$2 -> 45526 | F47: =Devblogs!P$2 -> Thursday | G47: =Teasers!C22 -> 45533 | H47: =Teasers!E22 -> Thursday | I47: ='Dev streams'!C30 -> 45534 | J47: ='Dev streams'!D30 -> Friday | K47: ='Dev servers'!C70 -> 45534 | L47: ='Dev servers'!F70 -> Friday | M47: =Updates!C60 -> 45545 | N47: =Updates!D60 -> Tuesday
A48: =Updates!A61 -> 2.41 | B48: =Updates!B61 -> Firebirds | C48: =Leaks!C$9 -> 45583 | D48: =Leaks!D$9 -> Friday | E48: =Devblogs!L$2 -> 45580 | F48: =Devblogs!M$2 -> Tuesday | G48: =Teasers!C23 -> 45589 | H48: =Teasers!E23 -> Thursday | I48: ='Dev streams'!C31 -> 45590 | J48: ='Dev streams'!D31 -> Friday | K48: ='Dev servers'!C71 -> 45590 | L48: ='Dev servers'!F71 -> Friday | M48: =Updates!C61 -> 45615 | N48: =Updates!D61 -> Tuesday
A49: =Updates!A62 -> 2.43 | B49: =Updates!B62 -> Storm Warning | C49: =Leaks!C$10 -> 45623 | D49: =Leaks!D$10 -> Wednesday | E49: =Devblogs!I$2 -> 45631 | F49: =Devblogs!J$2 -> Thursday | G49: =Teasers!C24 -> 45635 | H49: =Teasers!E24 -> Monday | I49: ='Dev streams'!C32 -> 45636 | J49: ='Dev streams'!D32 -> Tuesday | K49: ='Dev servers'!C72 -> 45636 | L49: ='Dev servers'!F72 -> Tuesday | M49: =Updates!C62 -> 45642 | N49: =Updates!D62 -> Monday
A50: =Updates!A63 -> 2.45 | B50: =Updates!B63 -> 0 | C50: =Leaks!C$11 -> 45708 | D50: =Leaks!D$11 -> Thursday | E50: =Devblogs!F$2 -> 45708 | F50: =Devblogs!G$2 -> Thursday | G50: =Teasers!C25 -> 0 | H50: =Teasers!E25 -> 0 | I50: ='Dev streams'!C33 -> 0 | J50: ='Dev streams'!D33 -> 0 | K50: ='Dev servers'!C73 -> 0 | L50: ='Dev servers'!F73 -> 0 | M50: =Updates!C63 -> 0 | N50: =Updates!D63 -> 0

Sheet Devblogs
E1: =IF(Updates!$B63<>"",CONCATENATE(Updates!$A63, " """, Updates!$B63, """"), Updates!$A63) -> 2.45 | H1: =IF(Updates!$B62<>"",CONCATENATE(Updates!$A62, " """, Updates!$B62, """"), Updates!$A62) -> 2.43 "Storm Warning" | K1: =IF(Updates!$B61<>"",CONCATENATE(Updates!$A61, " """, Updates!$B61, """"), Updates!$A61) -> 2.41 "Firebirds" | N1: =IF(Updates!$B60<>"",CONCATENATE(Updates!$A60, " """, Updates!$B60, """"), Updates!$A60) -> 2.39 "Dance of Dragons" | Q1: =IF(Updates!$B59<>"",CONCATENATE(Updates!$A59, " """, Updates!$B59, """"), Updates!$A59) -> 2.37 "Seek & Destroy" | T1: =IF(Updates!$B58<>"",CONCATENATE(Updates!$A58, " """, Updates!$B58, """"), Updates!$A58) -> 2.35 "Alpha Strike" | W1: =IF(Updates!$B57<>"",CONCATENATE(Updates!$A57, " """, Updates!$B57, """"), Updates!$A57) -> 2.33 "Air Superiority" | Z1: =IF(Updates!$B56<>"",CONCATENATE(Updates!$A56, " """, Updates!$B56, """"), Updates!$A56) -> 2.31 "Kings of Battle" | AC1: =IF(Updates!$B55<>"",CONCATENATE(Updates!$A55, " """, Updates!$B55, """"), Updates!$A55) -> 2.29 "Sons of Attila" | AF1: =IF(Updates!$B54<>"",CONCATENATE(Updates!$A54, " """, Updates!$B54, """"), Updates!$A54) -> 2.27 "La Royale" | AI1: =IF(Updates!$B53<>"",CONCATENATE(Updates!$A53, " """, Updates!$B53, """"), Updates!$A53) -> 2.25 "Sky Guardians" | AL1: =IF(Updates!$B52<>"",CONCATENATE(Updates!$A52, " """, Updates!$B52, """"), Updates!$A52) -> 2.23 "Apex Predators" | AO1: =IF(Updates!$B51<>"",CONCATENATE(Updates!$A51, " """, Updates!$B51, """"), Updates!$A51) -> 2.21 "Fire and Ice" | AR1: =IF(Updates!$B50<>"",CONCATENATE(Updates!$A50, " """, Updates!$B50, """"), Updates!$A50) -> 2.19 "Drone Age" | AU1: =IF(Updates!$B49<>"",CONCATENATE(Updates!$A49, " """, Updates!$B49, """"), Updates!$A49) -> 2.17 "Danger Zone" | AX1: =IF(Updates!$B48<>"",CONCATENATE(Updates!$A48, " """, Updates!$B48, """"), Updates!$A48) -> 2.15 "Wind of Change" | BA1: =IF(Updates!$B47<>"",CONCATENATE(Updates!$A47, " """, Updates!$B47, """"), Updates!$A47) -> 2.13 "Winged Lions" | BD1: =IF(Updates!$B46<>"",CONCATENATE(Updates!$A46, " """, Updates!$B46, """"), Updates!$A46) -> 2.11 "Ground Breaking" | BG1: =IF(Updates!$B45<>"",CONCATENATE(Updates!$A45, " """, Updates!$B45, """"), Updates!$A45) -> 2.9 "Direct Hit" | BJ1: =IF(Updates!$B44<>"",CONCATENATE(Updates!$A44, " """, Updates!$B44, """"), Updates!$A44) -> 2.7 "Red Skies" | BM1: =IF(Updates!$B43<>"",CONCATENATE(Updates!$A43, " """, Updates!$B43, """"), Updates!$A43) -> 2.5 "Ixwa Strike" | BP1: =IF(Updates!$B42<>"",CONCATENATE(Updates!$A42, " """, Updates!$B42, """"), Updates!$A42) -> 2.3 "Hot Tracks" | BS1: =IF(Updates!$B41<>"",CONCATENATE(Updates!$A41, " """, Updates!$B41, """"), Updates!$A41) -> 2.1 "New Power" | BV1: =IF(Updates!$B40<>"",CONCATENATE(Updates!$A40, " """, Updates!$B40, """"), Updates!$A40) -> 1.101 "Raining Fire" | BY1: =IF(Updates!$B39<>"",CONCATENATE(Updates!$A39, " """, Updates!$B39, """"), Updates!$A39) -> 1.99 "Starfighters" | CB1: =IF(Updates!$B38<>"",CONCATENATE(Updates!$A38, " """, Updates!$B38, """"), Updates!$A38) -> 1.97 "Viking Fury" | CE1: =IF(Updates!$B37<>"",CONCATENATE(Updates!$A37, " """, Updates!$B37, """"), Updates!$A37) -> 1.95 "Northern Wind" | CH1: =IF(Updates!$B36<>"",CONCATENATE(Updates!$A36, " """, Updates!$B36, """"), Updates!$A36) -> 1.93 "Shark Attack" | CK1: =IF(Updates!$B35<>"",CONCATENATE(Updates!$A35, " """, Updates!$B35, """"), Updates!$A35) -> 1.91 "Night Vision" | CN1: =IF(Updates!$B34<>"",CONCATENATE(Updates!$A34, " """, Updates!$B34, """"), Updates!$A34) -> 1.89 "Imperial Navy" | CQ1: =IF(Updates!$B33<>"",CONCATENATE(Updates!$A33, " """, Updates!$B33, """"), Updates!$A33) -> 1.87 "Locked On" | CT1: =IF(Updates!$B32<>"",CONCATENATE(Updates!$A32, " """, Updates!$B32, """"), Updates!$A32) -> 1.85 "Supersonic" | CW1: =IF(Updates!$B31<>"",CONCATENATE(Updates!$A31, " """, Updates!$B31, """"), Updates!$A31) -> 1.83 "Masters of the Sea" | CZ1: =IF(Updates!$B30<>"",CONCATENATE(Updates!$A30, " """, Updates!$B30, """"), Updates!$A30) -> 1.81 "The Valkyries" | DC1: =IF(Updates!$B29<>"",CONCATENATE(Updates!$A29, " """, Updates!$B29, """"), Updates!$A29) -> 1.79 "Project X" | DF1: =IF(Updates!$B28<>"",CONCATENATE(Updates!$A28, " """, Updates!$B28, """"), Updates!$A28) -> 1.77 "Advancing Storm" | DI1: =IF(Updates!$B27<>"",CONCATENATE(Updates!$A27, " """, Updates!$B27, """"), Updates!$A27) -> 1.75 "La Résistance" | DL1: =IF(Updates!$B26<>"",CONCATENATE(Updates!$A26, " """, Updates!$B26, """"), Updates!$A26) -> 1.73 "Vive la France" | DO1: =IF(Updates!$B25<>"",CONCATENATE(Updates!$A25, " """, Updates!$B25, """"), Updates!$A25) -> 1.71 "New E.R.A." | DR1: =IF(Updates!$B24<>"",CONCATENATE(Updates!$A24, " """, Updates!$B24, """"), Updates!$A24) -> 1.69 "Regia Aeronautica" | DU1: =IF(Updates!$B23<>"",CONCATENATE(Updates!$A23, " """, Updates!$B23, """"), Updates!$A23) -> 1.67 "Assault" | DX1: =IF(Updates!$B22<>"",CONCATENATE(Updates!$A22, " """, Updates!$B22, """"), Updates!$A22) -> 1.65 "Way of the Samurai" | EA1: =IF(Updates!$B21<>"",CONCATENATE(Updates!$A21, " """, Updates!$B21, """"), Updates!$A21) -> 1.63 "Desert Hunters" | ED1: =IF(Updates!$B20<>"",CONCATENATE(Updates!$A20, " """, Updates!$B20, """"), Updates!$A20) -> 1.61 "Road to Glory" | EG1: =IF(Updates!$B19<>"",CONCATENATE(Updates!$A19, " """, Updates!$B19, """"), Updates!$A19) -> 1.59 "Flaming Arrows" | EJ1: =IF(Updates!$B18<>"",CONCATENATE(Updates!$A18, " """, Updates!$B18, """"), Updates!$A18) -> 1.57 "Battle March" | EM1: =IF(Updates!$B17<>"",CONCATENATE(Updates!$A17, " """, Updates!$B17, """"), Updates!$A17) -> 1.55 "Royal Armour" | EP1: =IF(Updates!$B16<>"",CONCATENATE(Updates!$A16, " """, Updates!$B16, """"), Updates!$A16) -> 1.53 "Firestorm" | ES1: =IF(Updates!$B15<>"",CONCATENATE(Updates!$A15, " """, Updates!$B15, """"), Updates!$A15) -> 1.51 "Cold Steel" | EV1: =IF(Updates!$B14<>"",CONCATENATE(Updates!$A14, " """, Updates!$B14, """"), Updates!$A14) -> 1.49 "Weapons of Victory" | EY1: =IF(Updates!$B13<>"",CONCATENATE(Updates!$A13, " """, Updates!$B13, """"), Updates!$A13) -> 1.47 "Big Guns" | FB1: =IF(Updates!$B12<>"",CONCATENATE(Updates!$A12, " """, Updates!$B12, """"), Updates!$A12) -> 1.45 "Steel Generals" | FE1: =CONCATENATE(Updates!A11) -> 1.43 | FH1: =CONCATENATE(Updates!A10) -> 1.41 | FK1: =CONCATENATE(Updates!A9) -> 1.39 | FN1: =CONCATENATE(Updates!A8) -> 1.37
A2: Devblogs | E2: Warspite (03) | F2: 45708 | G2: =CHOOSE(WEEKDAY(F2,2),"Monday","Tuesday","Wednesday","Thursday","Friday","Saturday","Sunday") -> Thursday | H2: VBCI VCI | I2: 45631 | J2: =CHOOSE(WEEKDAY(I2,2),"Monday","Tuesday","Wednesday","Thursday","Friday","Saturday","Sunday") -> Thursday | K2: T77E1 & Skink [USA] & Ram Mk. II [GBR] | L2: 45580 | M2: =CHOOSE(WEEKDAY(L2,2),"Monday","Tuesday","Wednesday","Thursday","Friday","Saturday","Sunday") -> Tuesday | N2: T1E1 (90 mm) | O2: 45526 | P2: =CHOOSE(WEEKDAY(O2,2),"Monday","Tuesday","Wednesday","Thursday","Friday","Saturday","Sunday") -> Thursday | Q2: FOX-3: Active Radar Homing Missiles | R2: 45436 | S2: =CHOOSE(WEEKDAY(R2,2),"Monday","Tuesday","Wednesday","Thursday","Friday","Saturday","Sunday") -> Friday | T2: Centauro MGS [OMN] & strv 121B «Christian II» | U2: 45344 | V2: =CHOOSE(WEEKDAY(U2,2),"Monday","Tuesday","Wednesday","Thursday","Friday","Saturday","Sunday") -> Thursday | W2: M1A1HC "Click-Bait" & Challenger 2 OES & Tier VIII tanks | X2: 45261 | Y2: =CHOOSE(WEEKDAY(X2,2),"Monday","Tuesday","Wednesday","Thursday","Friday","Saturday","Sunday") -> Friday | Z2: Vickers Mk. 11 | AA2: 45212 | AB2: =CHOOSE(WEEKDAY(AA2,2),"Monday","Tuesday","Wednesday","Thursday","Friday","Saturday","Sunday") -> Friday | AC2: 2S1 | AD2: 45159 | AE2: =CHOOSE(WEEKDAY(AD2,2),"Monday","Tuesday","Wednesday","Thursday","Friday","Saturday","Sunday") -> Monday | AF2: M1 (KVT) | AG2: 45037 | AH2: =CHOOSE(WEEKDAY(AG2,2),"Monday","Tuesday","Wednesday","Thursday","Friday","Saturday","Sunday") -> Friday | AI2: Sd.Kfz. 222 | AJ2: 44967 | AK2: =CHOOSE(WEEKDAY(AJ2,2),"Monday","Tuesday","Wednesday","Thursday","Friday","Saturday","Sunday") -> Friday | AL2: 9A35M2 | AM2: 44894 | AN2: =CHOOSE(WEEKDAY(AM2,2),"Monday","Tuesday","Wednesday","Thursday","Friday","Saturday","Sunday") -> Tuesday | AO2: Fusō | AP2: 44846 | AQ2: =CHOOSE(WEEKDAY(AP2,2),"Monday","Tuesday","Wednesday","Thursday","Friday","Saturday","Sunday") -> Wednesday | AR2: Alaska (CB-1) | AS2: 44789 | AT2: =CHOOSE(WEEKDAY(AS2,2),"Monday","Tuesday","Wednesday","Thursday","Friday","Saturday","Sunday") -> Tuesday | AU2: VCAC MEPHISTO | AV2: 44699 | AW2: =CHOOSE(WEEKDAY(AV2,2),"Monday","Tuesday","Wednesday","Thursday","Friday","Saturday","Sunday") -> Wednesday | AX2: Arizona (BB-39) | AY2: 44610 | AZ2: =CHOOSE(WEEKDAY(AY2,2),"Monday","Tuesday","Wednesday","Thursday","Friday","Saturday","Sunday") -> Friday | BA2: Challenger 2 (TES) | BB2: 44530 | BC2: =CHOOSE(WEEKDAY(BB2,2),"Monday","Tuesday","Wednesday","Thursday","Friday","Saturday","Sunday") -> Tuesday | BD2: Tigre (TI) | BE2: 44477 | BF2: =CHOOSE(WEEKDAY(BE2,2),"Monday","Tuesday","Wednesday","Thursday","Friday","Saturday","Sunday") -> Friday | BG2: Pbv 301 | BH2: 44426 | BI2: =CHOOSE(WEEKDAY(BH2,2),"Monday","Tuesday","Wednesday","Thursday","Friday","Saturday","Sunday") -> Wednesday | BJ2: Liverpool (11) | BK2: 44328 | BL2: =CHOOSE(WEEKDAY(BK2,2),"Monday","Tuesday","Wednesday","Thursday","Friday","Saturday","Sunday") -> Wednesday | BM2: Blackpool (F 77) | BN2: 44242 | BO2: =CHOOSE(WEEKDAY(BN2,2),"Monday","Tuesday","Wednesday","Thursday","Friday","Saturday","Sunday") -> Monday | BP2: LTV A-7D Corsair II | BQ2: 44172 | BR2: =CHOOSE(WEEKDAY(BQ2,2),"Monday","Tuesday","Wednesday","Thursday","Friday","Saturday","Sunday") -> Monday | BS2: CDC 37L (SA 37) | BT2: 44124 | BU2: =CHOOSE(WEEKDAY(BT2,2),"Monday","Tuesday","Wednesday","Thursday","Friday","Saturday","Sunday") -> Tuesday | BV2: Akebono | BW2: 44057 | BX2: =CHOOSE(WEEKDAY(BW2,2),"Monday","Tuesday","Wednesday","Thursday","Friday","Saturday","Sunday") -> Friday | BY2: ZSD63 (PG87) | BZ2: 43956 | CA2: =CHOOSE(WEEKDAY(BZ2,2),"Monday","Tuesday","Wednesday","Thursday","Friday","Saturday","Sunday") -> Tuesday | CB2: strv m/31 | CC2: 43881 | CD2: =CHOOSE(WEEKDAY(CC2,2),"Monday","Tuesday","Wednesday","Thursday","Friday","Saturday","Sunday") -> Thursday | CE2: Svenska Aero J 6B | CF2: 43797 | CG2: =CHOOSE(WEEKDAY(CF2,2),"Monday","Tuesday","Wednesday","Thursday","Friday","Saturday","Sunday") -> Thursday | CH2: Kamov Ka-50 | CI2: 43749 | CJ2: =CHOOSE(WEEKDAY(CI2,2),"Monday","Tuesday","Wednesday","Thursday","Friday","Saturday","Sunday") -> Friday | CK2: RIP Maus | CL2: 43690 | CM2: =CHOOSE(WEEKDAY(CL2,2),"Monday","Tuesday","Wednesday","Thursday","Friday","Saturday","Sunday") -> Tuesday | CN2: Japanese Fleet | CO2: 43588 | CP2: =CHOOSE(WEEKDAY(CO2,2),"Monday","Tuesday","Wednesday","Thursday","Friday","Saturday","Sunday") -> Friday | CQ2: Challenger 2 (Dorchester 2E) & Tier VII tanks | CR2: 43511 | CS2: =CHOOSE(WEEKDAY(CR2,2),"Monday","Tuesday","Wednesday","Thursday","Friday","Saturday","Sunday") -> Friday | CT2: Italian tanks | CU2: 43427 | CV2: =CHOOSE(WEEKDAY(CU2,2),"Monday","Tuesday","Wednesday","Thursday","Friday","Saturday","Sunday") -> Friday | CW2: Navy OBT | CX2: 43382 | CY2: =CHOOSE(WEEKDAY(CX2,2),"Monday","Tuesday","Wednesday","Thursday","Friday","Saturday","Sunday") -> Tuesday | CZ2: Mil Mi-24 & Bell AH-1F | DA2: 43333 | DB2: =CHOOSE(WEEKDAY(DA2,2),"Monday","Tuesday","Wednesday","Thursday","Friday","Saturday","Sunday") -> Tuesday | DC2: Type 90 | DD2: 43231 | DE2: =CHOOSE(WEEKDAY(DD2,2),"Monday","Tuesday","Wednesday","Thursday","Friday","Saturday","Sunday") -> Friday | DF2: Dagor 5.0: TAA | DG2: 43138 | DH2: =CHOOSE(WEEKDAY(DG2,2),"Monday","Tuesday","Wednesday","Thursday","Friday","Saturday","Sunday") -> Wednesday | DI2: French tanks | DJ2: 43071 | DK2: =CHOOSE(WEEKDAY(DJ2,2),"Monday","Tuesday","Wednesday","Thursday","Friday","Saturday","Sunday") -> Saturday | DL2: Dewoitine D.371 | DM2: 43019 | DN2: =CHOOSE(WEEKDAY(DM2,2),"Monday","Tuesday","Wednesday","Thursday","Friday","Saturday","Sunday") -> Wednesday | DO2: Waffenträger Krupp-Steyr | DP2: 42965 | DQ2: =CHOOSE(WEEKDAY(DP2,2),"Monday","Tuesday","Wednesday","Thursday","Friday","Saturday","Sunday") -> Friday | DR2: Fiat CR.32 | DS2: 42857 | DT2: =CHOOSE(WEEKDAY(DS2,2),"Monday","Tuesday","Wednesday","Thursday","Friday","Saturday","Sunday") -> Tuesday | DU2: New tracers | DV2: 42780 | DW2: =CHOOSE(WEEKDAY(DV2,2),"Monday","Tuesday","Wednesday","Thursday","Friday","Saturday","Sunday") -> Tuesday | DX2: Ka-Mi | DY2: 42684 | DZ2: =CHOOSE(WEEKDAY(DY2,2),"Monday","Tuesday","Wednesday","Thursday","Friday","Saturday","Sunday") -> Thursday | EA2: M163 | EB2: 42615 | EC2: =CHOOSE(WEEKDAY(EB2,2),"Monday","Tuesday","Wednesday","Thursday","Friday","Saturday","Sunday") -> Friday | ED2: Supermarine Spitfire F. Mk. IX rework | EE2: 42557 | EF2: =CHOOSE(WEEKDAY(EE2,2),"Monday","Tuesday","Wednesday","Thursday","Friday","Saturday","Sunday") -> Wednesday | EG2: New squadron features | EH2: 42452 | EI2: =CHOOSE(WEEKDAY(EH2,2),"Monday","Tuesday","Wednesday","Thursday","Friday","Saturday","Sunday") -> Wednesday | EJ2: New Thermodynamics | EK2: 42395 | EL2: =CHOOSE(WEEKDAY(EK2,2),"Monday","Tuesday","Wednesday","Thursday","Friday","Saturday","Sunday") -> Tuesday | EM2: Churchill Mk. III & VII | EN2: 42341 | EO2: =CHOOSE(WEEKDAY(EN2,2),"Monday","Tuesday","Wednesday","Thursday","Friday","Saturday","Sunday") -> Thursday | EP2: Advance to the Rhine | EQ2: 42221 | ER2: =CHOOSE(WEEKDAY(EQ2,2),"Monday","Tuesday","Wednesday","Thursday","Friday","Saturday","Sunday") -> Wednesday | ES2: Sector indicator | ET2: 42171 | EU2: =CHOOSE(WEEKDAY(ET2,2),"Monday","Tuesday","Wednesday","Thursday","Friday","Saturday","Sunday") -> Tuesday | EV2: Hürtgen Forest | EW2: 42111 | EX2: =CHOOSE(WEEKDAY(EW2,2),"Monday","Tuesday","Wednesday","Thursday","Friday","Saturday","Sunday") -> Friday | EY2: New Ground Vehicle Views | EZ2: 42037 | FA2: =CHOOSE(WEEKDAY(EZ2,2),"Monday","Tuesday","Wednesday","Thursday","Friday","Saturday","Sunday") -> Monday | FB2: M2 | FC2: 41941 | FD2: =CHOOSE(WEEKDAY(FC2,2),"Monday","Tuesday","Wednesday","Thursday","Friday","Saturday","Sunday") -> Wednesday | FE2: Nakajima Ki 27 Otsu | FF2: 41795 | FG2: =CHOOSE(WEEKDAY(FF2,2),"Monday","Tuesday","Wednesday","Thursday","Friday","Saturday","Sunday") -> Thursday | FH2: New aircraft | FI2: 41747 | FJ2: =CHOOSE(WEEKDAY(FI2,2),"Monday","Tuesday","Wednesday","Thursday","Friday","Saturday","Sunday") -> Friday | FK2: Lavochkin 174 cockpit | FL2: 41649 | FM2: =CHOOSE(WEEKDAY(FL2,2),"Monday","Tuesday","Wednesday","Thursday","Friday","Saturday","Sunday") -> Friday | FN2: Tank sounds recording | FO2: 41561 | FP2: =CHOOSE(WEEKDAY(FO2,2),"Monday","Tuesday","Wednesday","Thursday","Friday","Saturday","Sunday") -> Monday
H3: Thai aircraft | I3: 45632 | J3: =CHOOSE(WEEKDAY(I3,2),"Monday","Tuesday","Wednesday","Thursday","Friday","Saturday","Sunday") -> Friday | K3: Scimitar | L3: 45582 | M3: =CHOOSE(WEEKDAY(L3,2),"Monday","Tuesday","Wednesday","Thursday","Friday","Saturday","Sunday") -> Thursday | N3: ZSU-23-4M2 | O3: 45527 | P3: =CHOOSE(WEEKDAY(O3,2),"Monday","Tuesday","Wednesday","Thursday","Friday","Saturday","Sunday") -> Friday | Q3: =HYPERLINK("https://warthunder.com/en/news/8897-development-xm800t-brave-prowess-en", "XM800T") -> XM800T | R3: 45436 | S3: =CHOOSE(WEEKDAY(R3,2),"Monday","Tuesday","Wednesday","Thursday","Friday","Saturday","Sunday") -> Friday | T3: Westland Wessex H.U. Mk. 5 | U3: 45348 | V3: =CHOOSE(WEEKDAY(U3,2),"Monday","Tuesday","Wednesday","Thursday","Friday","Saturday","Sunday") -> Monday | W3: Panavia IDS-Tornado (WTD 61) | X3: 45265 | Y3: =CHOOSE(WEEKDAY(X3,2),"Monday","Tuesday","Wednesday","Thursday","Friday","Saturday","Sunday") -> Tuesday | Z3: Iron Duke (18) & Yamashiro | AA3: 45217 | AB3: =CHOOSE(WEEKDAY(AA3,2),"Monday","Tuesday","Wednesday","Thursday","Friday","Saturday","Sunday") -> Wednesday | AC3: MBT-2000 | AD3: 45160 | AE3: =CHOOSE(WEEKDAY(AD3,2),"Monday","Tuesday","Wednesday","Thursday","Friday","Saturday","Sunday") -> Tuesday | AF3: Curtiss BF2C-1 | AG3: 45050 | AH3: =CHOOSE(WEEKDAY(AG3,2),"Monday","Tuesday","Wednesday","Thursday","Friday","Saturday","Sunday") -> Thursday | AI3: Optimization of the War Thunder file structure | AJ3: 44971 | AK3: =CHOOSE(WEEKDAY(AJ3,2),"Monday","Tuesday","Wednesday","Thursday","Friday","Saturday","Sunday") -> Tuesday | AL3: Grumman A-6E (WCSI) & Tier VIII aircraft | AM3: 44895 | AN3: =CHOOSE(WEEKDAY(AM3,2),"Monday","Tuesday","Wednesday","Thursday","Friday","Saturday","Sunday") -> Wednesday | AO3: Bosvark | AP3: 44847 | AQ3: =CHOOSE(WEEKDAY(AP3,2),"Monday","Tuesday","Wednesday","Thursday","Friday","Saturday","Sunday") -> Thursday | AR3: Pbv 302 (Rb 56) | AS3: 44791 | AT3: =CHOOSE(WEEKDAY(AS3,2),"Monday","Tuesday","Wednesday","Thursday","Friday","Saturday","Sunday") -> Thursday | AU3: pvkv III | AV3: 44700 | AW3: =CHOOSE(WEEKDAY(AV3,2),"Monday","Tuesday","Wednesday","Thursday","Friday","Saturday","Sunday") -> Thursday | AX3: Erprobungsträger mit Dreiachsig stabilisierter Turm III F | AY3: 44614 | AZ3: =CHOOSE(WEEKDAY(AY3,2),"Monday","Tuesday","Wednesday","Thursday","Friday","Saturday","Sunday") -> Tuesday | BA3: Krischan der Große | BB3: 44531 | BC3: =CHOOSE(WEEKDAY(BB3,2),"Monday","Tuesday","Wednesday","Thursday","Friday","Saturday","Sunday") -> Wednesday | BD3: ZTL11 | BE3: 44480 | BF3: =CHOOSE(WEEKDAY(BE3,2),"Monday","Tuesday","Wednesday","Thursday","Friday","Saturday","Sunday") -> Monday | BG3: ZTZ99 (Phase 2) & Nánchāng A5C | BH3: 44427 | BI3: =CHOOSE(WEEKDAY(BH3,2),"Monday","Tuesday","Wednesday","Thursday","Friday","Saturday","Sunday") -> Thursday | BJ3: Northrop F-5C Freedom Fighter | BK3: 44329 | BL3: =CHOOSE(WEEKDAY(BK3,2),"Monday","Tuesday","Wednesday","Thursday","Friday","Saturday","Sunday") -> Thursday | BM3: Fokker D.XXI | BN3: 44243 | BO3: =CHOOSE(WEEKDAY(BN3,2),"Monday","Tuesday","Wednesday","Thursday","Friday","Saturday","Sunday") -> Tuesday | BP3: Von der Tann | BQ3: 44173 | BR3: =CHOOSE(WEEKDAY(BQ3,2),"Monday","Tuesday","Wednesday","Thursday","Friday","Saturday","Sunday") -> Tuesday | BS3: VFM5 | BT3: 44125 | BU3: =CHOOSE(WEEKDAY(BT3,2),"Monday","Tuesday","Wednesday","Thursday","Friday","Saturday","Sunday") -> Wednesday | BV3: SM | BW3: 44058 | BX3: =CHOOSE(WEEKDAY(BW3,2),"Monday","Tuesday","Wednesday","Thursday","Friday","Saturday","Sunday") -> Saturday | BY3: MS 15 & Italian Navy | BZ3: 43957 | CA3: =CHOOSE(WEEKDAY(BZ3,2),"Monday","Tuesday","Wednesday","Thursday","Friday","Saturday","Sunday") -> Wednesday | CB3: strv m/40L | CC3: 43882 | CD3: =CHOOSE(WEEKDAY(CC3,2),"Monday","Tuesday","Wednesday","Thursday","Friday","Saturday","Sunday") -> Friday | CE3: Tobruk (D 37) | CF3: 43798 | CG3: =CHOOSE(WEEKDAY(CF3,2),"Monday","Tuesday","Wednesday","Thursday","Friday","Saturday","Sunday") -> Friday | CH3: Centurion Mk. 7 (CMT) | CI3: 43753 | CJ3: =CHOOSE(WEEKDAY(CI3,2),"Monday","Tuesday","Wednesday","Thursday","Friday","Saturday","Sunday") -> Tuesday | CK3: Westland Lynx A.H. Mk. 1 & G-LYNX | CL3: 43692 | CM3: =CHOOSE(WEEKDAY(CL3,2),"Monday","Tuesday","Wednesday","Thursday","Friday","Saturday","Sunday") -> Thursday | CN3: No. 4 | CO3: 43591 | CP3: =CHOOSE(WEEKDAY(CO3,2),"Monday","Tuesday","Wednesday","Thursday","Friday","Saturday","Sunday") -> Monday | CQ3: Hawker Sea Hawk | CR3: 43514 | CS3: =CHOOSE(WEEKDAY(CR3,2),"Monday","Tuesday","Wednesday","Thursday","Friday","Saturday","Sunday") -> Monday | CT3: 105/25 M43 | CU3: 43427 | CV3: =CHOOSE(WEEKDAY(CU3,2),"Monday","Tuesday","Wednesday","Thursday","Friday","Saturday","Sunday") -> Friday | CW3: Nepal (G 25) | CX3: 43383 | CY3: =CHOOSE(WEEKDAY(CX3,2),"Monday","Tuesday","Wednesday","Thursday","Friday","Saturday","Sunday") -> Wednesday | CZ3: Mil Mi-4 & Bell UH-1 | DA3: 43333 | DB3: =CHOOSE(WEEKDAY(DA3,2),"Monday","Tuesday","Wednesday","Thursday","Friday","Saturday","Sunday") -> Tuesday | DC3: Vought F4U-7 Corsair | DD3: 43235 | DE3: =CHOOSE(WEEKDAY(DD3,2),"Monday","Tuesday","Wednesday","Thursday","Friday","Saturday","Sunday") -> Tuesday | DF3: Leopard 2K | DG3: 43140 | DH3: =CHOOSE(WEEKDAY(DG3,2),"Monday","Tuesday","Wednesday","Thursday","Friday","Saturday","Sunday") -> Friday | DI3: AMX 13 (SS.11) | DJ3: 43071 | DK3: =CHOOSE(WEEKDAY(DJ3,2),"Monday","Tuesday","Wednesday","Thursday","Friday","Saturday","Sunday") -> Saturday | DL3: Potez 630 & 631 | DM3: 43025 | DN3: =CHOOSE(WEEKDAY(DM3,2),"Monday","Tuesday","Wednesday","Thursday","Friday","Saturday","Sunday") -> Tuesday | DO3: T-64A | DP3: 42969 | DQ3: =CHOOSE(WEEKDAY(DP3,2),"Monday","Tuesday","Wednesday","Thursday","Friday","Saturday","Sunday") -> Tuesday | DR3: Fiat G.55 Centauro | DS3: 42859 | DT3: =CHOOSE(WEEKDAY(DS3,2),"Monday","Tuesday","Wednesday","Thursday","Friday","Saturday","Sunday") -> Thursday | DU3: Supermarine Spitfire Mk. II rework | DV3: 42780 | DW3: =CHOOSE(WEEKDAY(DV3,2),"Monday","Tuesday","Wednesday","Thursday","Friday","Saturday","Sunday") -> Tuesday | DX3: Chi-Ha | DY3: 42685 | DZ3: =CHOOSE(WEEKDAY(DY3,2),"Monday","Tuesday","Wednesday","Thursday","Friday","Saturday","Sunday") -> Friday | EA3: Sukhoi Su-6 (M-71F) | EB3: 42618 | EC3: =CHOOSE(WEEKDAY(EB3,2),"Monday","Tuesday","Wednesday","Thursday","Friday","Saturday","Sunday") -> Monday | ED3: Republic P-47N-15-RA Thunderbolt | EE3: 42570 | EF3: =CHOOSE(WEEKDAY(EE3,2),"Monday","Tuesday","Wednesday","Thursday","Friday","Saturday","Sunday") -> Tuesday | EG3: Medkits | EH3: 42453 | EI3: =CHOOSE(WEEKDAY(EH3,2),"Monday","Tuesday","Wednesday","Thursday","Friday","Saturday","Sunday") -> Thursday | EJ3: Last Man Standing | EK3: 42396 | EL3: =CHOOSE(WEEKDAY(EK3,2),"Monday","Tuesday","Wednesday","Thursday","Friday","Saturday","Sunday") -> Wednesday | EM3: Tetrarch Mk. I | EN3: 42342 | EO3: =CHOOSE(WEEKDAY(EN3,2),"Monday","Tuesday","Wednesday","Thursday","Friday","Saturday","Sunday") -> Friday | EP3: Dagor 4.0: Physically based rendering | EQ3: 42222 | ER3: =CHOOSE(WEEKDAY(EQ3,2),"Monday","Tuesday","Wednesday","Thursday","Friday","Saturday","Sunday") -> Thursday | ES3: Finland | ET3: 42175 | EU3: =CHOOSE(WEEKDAY(ET3,2),"Monday","Tuesday","Wednesday","Thursday","Friday","Saturday","Sunday") -> Saturday | EV3: M18 GMC & M18 GMC (805th TD.Bat.) «Black Cat» | EW3: 42111 | EX3: =CHOOSE(WEEKDAY(EW3,2),"Monday","Tuesday","Wednesday","Thursday","Friday","Saturday","Sunday") -> Friday | EY3: Ground forces map changes | EZ3: 42038 | FA3: =CHOOSE(WEEKDAY(EZ3,2),"Monday","Tuesday","Wednesday","Thursday","Friday","Saturday","Sunday") -> Tuesday | FB3: M16 MGMC | FC3: 41941 | FD3: =CHOOSE(WEEKDAY(FC3,2),"Monday","Tuesday","Wednesday","Thursday","Friday","Saturday","Sunday") -> Wednesday | FE3: Future of the Japanese aviation in War Thunder | FF3: 41813 | FG3: =CHOOSE(WEEKDAY(FF3,2),"Monday","Tuesday","Wednesday","Thursday","Friday","Saturday","Sunday") -> Monday | FH3: Squadron Battles | FI3: 41748 | FJ3: =CHOOSE(WEEKDAY(FI3,2),"Monday","Tuesday","Wednesday","Thursday","Friday","Saturday","Sunday") -> Saturday | FK3: de Havilland Mosquito F.B. Mk. XVIII & North American F-82E Twin Mustang & Lavochkin La-15 | FL3: 41674 | FM3: =CHOOSE(WEEKDAY(FL3,2),"Monday","Tuesday","Wednesday","Thursday","Friday","Saturday","Sunday") -> Tuesday | FN3: Yakovlev Yak-9U | FO3: 41569 | FP3: =CHOOSE(WEEKDAY(FO3,2),"Monday","Tuesday","Wednesday","Thursday","Friday","Saturday","Sunday") -> Tuesday
H4: La Galissonnière | I4: 45635 | J4: =CHOOSE(WEEKDAY(I4,2),"Monday","Tuesday","Wednesday","Thursday","Friday","Saturday","Sunday") -> Monday | K4: PLZ05 | L4: 45583 | M4: =CHOOSE(WEEKDAY(L4,2),"Monday","Tuesday","Wednesday","Thursday","Friday","Saturday","Sunday") -> Friday | N4: Tennessee (BB-43) | O4: 45530 | P4: =CHOOSE(WEEKDAY(O4,2),"Monday","Tuesday","Wednesday","Thursday","Friday","Saturday","Sunday") -> Monday | Q4: Option for Smaller Team Sizes in Air Realistic Battles | R4: 45439 | S4: =CHOOSE(WEEKDAY(R4,2),"Monday","Tuesday","Wednesday","Thursday","Friday","Saturday","Sunday") -> Monday | T4: AMX VCI (M45) | U4: 45349 | V4: =CHOOSE(WEEKDAY(U4,2),"Monday","Tuesday","Wednesday","Thursday","Friday","Saturday","Sunday") -> Tuesday | W4: Roanoke (CL-145) | X4: 45265 | Y4: =CHOOSE(WEEKDAY(X4,2),"Monday","Tuesday","Wednesday","Thursday","Friday","Saturday","Sunday") -> Tuesday | Z4: 3½t Truck (SAM-1C) | AA4: 45219 | AB4: =CHOOSE(WEEKDAY(AA4,2),"Monday","Tuesday","Wednesday","Thursday","Friday","Saturday","Sunday") -> Friday | AC4: pvkv IV | AD4: 45161 | AE4: =CHOOSE(WEEKDAY(AD4,2),"Monday","Tuesday","Wednesday","Thursday","Friday","Saturday","Sunday") -> Wednesday | AF4: Grumman F-14B-150 Tomcat | AG4: 45052 | AH4: =CHOOSE(WEEKDAY(AG4,2),"Monday","Tuesday","Wednesday","Thursday","Friday","Saturday","Sunday") -> Saturday | AI4: ZTS63 (1979) | AJ4: 44971 | AK4: =CHOOSE(WEEKDAY(AJ4,2),"Monday","Tuesday","Wednesday","Thursday","Friday","Saturday","Sunday") -> Tuesday | AL4: Magach 7 Gimel | AM4: 44896 | AN4: =CHOOSE(WEEKDAY(AM4,2),"Monday","Tuesday","Wednesday","Thursday","Friday","Saturday","Sunday") -> Thursday | AO4: Finnish aviation and tanks | AP4: 44848 | AQ4: =CHOOSE(WEEKDAY(AP4,2),"Monday","Tuesday","Wednesday","Thursday","Friday","Saturday","Sunday") -> Friday | AR4: VK 30.02 (M) V2 | AS4: 44792 | AT4: =CHOOSE(WEEKDAY(AS4,2),"Monday","Tuesday","Wednesday","Thursday","Friday","Saturday","Sunday") -> Friday | AU4: Hood (51) | AV4: 44701 | AW4: =CHOOSE(WEEKDAY(AV4,2),"Monday","Tuesday","Wednesday","Thursday","Friday","Saturday","Sunday") -> Friday | AX4: Albatros (F 543) | AY4: 44616 | AZ4: =CHOOSE(WEEKDAY(AY4,2),"Monday","Tuesday","Wednesday","Thursday","Friday","Saturday","Sunday") -> Thursday | BA4: Leclerc s. 21 | BB4: 44531 | BC4: =CHOOSE(WEEKDAY(BB4,2),"Monday","Tuesday","Wednesday","Thursday","Friday","Saturday","Sunday") -> Wednesday | BD4: Vought V-12D | BE4: 44481 | BF4: =CHOOSE(WEEKDAY(BE4,2),"Monday","Tuesday","Wednesday","Thursday","Friday","Saturday","Sunday") -> Tuesday | BG4: Yūbari | BH4: 44428 | BI4: =CHOOSE(WEEKDAY(BH4,2),"Monday","Tuesday","Wednesday","Thursday","Friday","Saturday","Sunday") -> Friday | BJ4: Sukhoi Su-7BMK | BK4: 44330 | BL4: =CHOOSE(WEEKDAY(BK4,2),"Monday","Tuesday","Wednesday","Thursday","Friday","Saturday","Sunday") -> Friday | BM4: PTL02 | BN4: 44244 | BO4: =CHOOSE(WEEKDAY(BN4,2),"Monday","Tuesday","Wednesday","Thursday","Friday","Saturday","Sunday") -> Wednesday | BP4: Invincible | BQ4: 44174 | BR4: =CHOOSE(WEEKDAY(BQ4,2),"Monday","Tuesday","Wednesday","Thursday","Friday","Saturday","Sunday") -> Wednesday | BS4: FlaRakRad 1 A2 | BT4: 44126 | BU4: =CHOOSE(WEEKDAY(BT4,2),"Monday","Tuesday","Wednesday","Thursday","Friday","Saturday","Sunday") -> Thursday | BV4: T-72B (Kontakt-5) & T-72B3 | BW4: 44061 | BX4: =CHOOSE(WEEKDAY(BW4,2),"Monday","Tuesday","Wednesday","Thursday","Friday","Saturday","Sunday") -> Tuesday | BY4: D2 | BZ4: 43958 | CA4: =CHOOSE(WEEKDAY(BZ4,2),"Monday","Tuesday","Wednesday","Thursday","Friday","Saturday","Sunday") -> Thursday | CB4: sav m/43 | CC4: 43885 | CD4: =CHOOSE(WEEKDAY(CC4,2),"Monday","Tuesday","Wednesday","Thursday","Friday","Saturday","Sunday") -> Monday | CE4: Saab B 3C | CF4: 43801 | CG4: =CHOOSE(WEEKDAY(CF4,2),"Monday","Tuesday","Wednesday","Thursday","Friday","Saturday","Sunday") -> Monday | CH4: BMP-3 | CI4: 43754 | CJ4: =CHOOSE(WEEKDAY(CI4,2),"Monday","Tuesday","Wednesday","Thursday","Friday","Saturday","Sunday") -> Wednesday | CK4: Westland Scout & Wasp | CL4: 43696 | CM4: =CHOOSE(WEEKDAY(CL4,2),"Monday","Tuesday","Wednesday","Thursday","Friday","Saturday","Sunday") -> Monday | CN4: Tama | CO4: 43592 | CP4: =CHOOSE(WEEKDAY(CO4,2),"Monday","Tuesday","Wednesday","Thursday","Friday","Saturday","Sunday") -> Tuesday | CQ4: Alaska | CR4: 43516 | CS4: =CHOOSE(WEEKDAY(CR4,2),"Monday","Tuesday","Wednesday","Thursday","Friday","Saturday","Sunday") -> Wednesday | CT4: Breda 501 | CU4: 43431 | CV4: =CHOOSE(WEEKDAY(CU4,2),"Monday","Tuesday","Wednesday","Thursday","Friday","Saturday","Sunday") -> Tuesday | CW4: Grey Fox (SGB 4) | CX4: 43384 | CY4: =CHOOSE(WEEKDAY(CX4,2),"Monday","Tuesday","Wednesday","Thursday","Friday","Saturday","Sunday") -> Thursday | CZ4: Char 25t & T-80B | DA4: 43334 | DB4: =CHOOSE(WEEKDAY(DA4,2),"Monday","Tuesday","Wednesday","Thursday","Friday","Saturday","Sunday") -> Wednesday | DC4: T-64BV | DD4: 43236 | DE4: =CHOOSE(WEEKDAY(DD4,2),"Monday","Tuesday","Wednesday","Thursday","Friday","Saturday","Sunday") -> Wednesday | DF4: Dagor 5.0: water | DG4: 43140 | DH4: =CHOOSE(WEEKDAY(DG4,2),"Monday","Tuesday","Wednesday","Thursday","Friday","Saturday","Sunday") -> Friday | DI4: B1 ter | DJ4: 43073 | DK4: =CHOOSE(WEEKDAY(DJ4,2),"Monday","Tuesday","Wednesday","Thursday","Friday","Saturday","Sunday") -> Monday | DL4: Caudron C.714 | DM4: 43027 | DN4: =CHOOSE(WEEKDAY(DM4,2),"Monday","Tuesday","Wednesday","Thursday","Friday","Saturday","Sunday") -> Thursday | DO4: M60A1 (RISE/P) | DP4: 42970 | DQ4: =CHOOSE(WEEKDAY(DP4,2),"Monday","Tuesday","Wednesday","Thursday","Friday","Saturday","Sunday") -> Wednesday | DR4: Breda Ba.88 Lince | DS4: 42865 | DT4: =CHOOSE(WEEKDAY(DS4,2),"Monday","Tuesday","Wednesday","Thursday","Friday","Saturday","Sunday") -> Wednesday | DU4: Type 87 | DV4: 42781 | DW4: =CHOOSE(WEEKDAY(DV4,2),"Monday","Tuesday","Wednesday","Thursday","Friday","Saturday","Sunday") -> Wednesday | DX4: Chi-Nu | DY4: 42690 | DZ4: =CHOOSE(WEEKDAY(DY4,2),"Monday","Tuesday","Wednesday","Thursday","Friday","Saturday","Sunday") -> Wednesday | EA4: Nakajima Ki-87 | EB4: 42620 | EC4: =CHOOSE(WEEKDAY(EB4,2),"Monday","Tuesday","Wednesday","Thursday","Friday","Saturday","Sunday") -> Wednesday | ED4: Sturmpanzer | EE4: 42571 | EF4: =CHOOSE(WEEKDAY(EE4,2),"Monday","Tuesday","Wednesday","Thursday","Friday","Saturday","Sunday") -> Wednesday | EG4: Dagor 4.0 New photorealistic technology for sky and cloud rendering | EH4: 42457 | EI4: =CHOOSE(WEEKDAY(EH4,2),"Monday","Tuesday","Wednesday","Thursday","Friday","Saturday","Sunday") -> Monday | EJ4: Dornier Do 335 Pfeil | EK4: 42408 | EL4: =CHOOSE(WEEKDAY(EK4,2),"Monday","Tuesday","Wednesday","Thursday","Friday","Saturday","Sunday") -> Monday | EM4: Cromwell Mk. I | EN4: 42343 | EO4: =CHOOSE(WEEKDAY(EN4,2),"Monday","Tuesday","Wednesday","Thursday","Friday","Saturday","Sunday") -> Saturday | EP4: Destructible environment | EQ4: 42223 | ER4: =CHOOSE(WEEKDAY(EQ4,2),"Monday","Tuesday","Wednesday","Thursday","Friday","Saturday","Sunday") -> Friday | ES4: Neubau-Panzerkampfwagen IV (3,7cm & 7,5cm) | ET4: 42177 | EU4: =CHOOSE(WEEKDAY(ET4,2),"Monday","Tuesday","Wednesday","Thursday","Friday","Saturday","Sunday") -> Monday | EV4: Douglas AD-2 Skyraider & Stu.H. G | EW4: 42112 | EX4: =CHOOSE(WEEKDAY(EW4,2),"Monday","Tuesday","Wednesday","Thursday","Friday","Saturday","Sunday") -> Saturday | EY4: Graphic improvements | EZ4: 42039 | FA4: =CHOOSE(WEEKDAY(EZ4,2),"Monday","Tuesday","Wednesday","Thursday","Friday","Saturday","Sunday") -> Wednesday | FB4: M4A1(76)W | FC4: 41943 | FD4: =CHOOSE(WEEKDAY(FC4,2),"Monday","Tuesday","Wednesday","Thursday","Friday","Saturday","Sunday") -> Friday | FE4: Future of the Soviet aviation in War Thunder | FF4: 41816 | FG4: =CHOOSE(WEEKDAY(FF4,2),"Monday","Tuesday","Wednesday","Thursday","Friday","Saturday","Sunday") -> Thursday | FH4: Ki 45 cockpit | FI4: 41754 | FJ4: =CHOOSE(WEEKDAY(FI4,2),"Monday","Tuesday","Wednesday","Thursday","Friday","Saturday","Sunday") -> Friday | FK4: Mikoyan-Gurevich MiG-15bis [DEU] & Canadair CL-13A Sabre Mk. 5 & North American F-86F-30 Kyokkō | FL4: 41688 | FM4: =CHOOSE(WEEKDAY(FL4,2),"Monday","Tuesday","Wednesday","Thursday","Friday","Saturday","Sunday") -> Tuesday | FN4: Hawker Tempest F.B. Mk. 2 | FO4: 41573 | FP4: =CHOOSE(WEEKDAY(FO4,2),"Monday","Tuesday","Wednesday","Thursday","Friday","Saturday","Sunday") -> Saturday
A5: Monday: | B5: =COUNTIF(D2:FP45,"Monday") -> 170 | C5: =B5/SUM($B$5:$B$11) -> 0.15813953 | H5: Attica | I5: 45635 | J5: =CHOOSE(WEEKDAY(I5,2),"Monday","Tuesday","Wednesday","Thursday","Friday","Saturday","Sunday") -> Monday | K5: Dunkerque | L5: 45587 | M5: =CHOOSE(WEEKDAY(L5,2),"Monday","Tuesday","Wednesday","Thursday","Friday","Saturday","Sunday") -> Tuesday | N5: KV-1A | O5: 45531 | P5: =CHOOSE(WEEKDAY(O5,2),"Monday","Tuesday","Wednesday","Thursday","Friday","Saturday","Sunday") -> Tuesday | Q5: Leopard 2 A4M CAN | R5: 45440 | S5: =CHOOSE(WEEKDAY(R5,2),"Monday","Tuesday","Wednesday","Thursday","Friday","Saturday","Sunday") -> Tuesday | T5: Blackburn Buccaneer S. Mk. 2B | U5: 45350 | V5: =CHOOSE(WEEKDAY(U5,2),"Monday","Tuesday","Wednesday","Thursday","Friday","Saturday","Sunday") -> Wednesday | W5: Volcano Valley | X5: 45266 | Y5: =CHOOSE(WEEKDAY(X5,2),"Monday","Tuesday","Wednesday","Thursday","Friday","Saturday","Sunday") -> Wednesday | Z5: Agusta AH-129D | AA5: 45222 | AB5: =CHOOSE(WEEKDAY(AA5,2),"Monday","Tuesday","Wednesday","Thursday","Friday","Saturday","Sunday") -> Monday | AC5: TO-55 | AD5: 45162 | AE5: =CHOOSE(WEEKDAY(AD5,2),"Monday","Tuesday","Wednesday","Thursday","Friday","Saturday","Sunday") -> Thursday | AF5: Le Malin (X 82) | AG5: 45054 | AH5: =CHOOSE(WEEKDAY(AG5,2),"Monday","Tuesday","Wednesday","Thursday","Friday","Saturday","Sunday") -> Monday | AI5: Nenohi | AJ5: 44973 | AK5: =CHOOSE(WEEKDAY(AJ5,2),"Monday","Tuesday","Wednesday","Thursday","Friday","Saturday","Sunday") -> Thursday | AL5: AMX 32 P1 | AM5: 44900 | AN5: =CHOOSE(WEEKDAY(AM5,2),"Monday","Tuesday","Wednesday","Thursday","Friday","Saturday","Sunday") -> Monday | AO5: M1A2 SEPv1 (TUSK 1) | AP5: 44848 | AQ5: =CHOOSE(WEEKDAY(AP5,2),"Monday","Tuesday","Wednesday","Thursday","Friday","Saturday","Sunday") -> Friday | AR5: Mikhail Kutuzov | AS5: 44796 | AT5: =CHOOSE(WEEKDAY(AS5,2),"Monday","Tuesday","Wednesday","Thursday","Friday","Saturday","Sunday") -> Tuesday | AU5: G6-45 | AV5: 44704 | AW5: =CHOOSE(WEEKDAY(AV5,2),"Monday","Tuesday","Wednesday","Thursday","Friday","Saturday","Sunday") -> Monday | AX5: Dagor Engine 6.5: New Surface Rendering | AY5: 44629 | AZ5: =CHOOSE(WEEKDAY(AY5,2),"Monday","Tuesday","Wednesday","Thursday","Friday","Saturday","Sunday") -> Wednesday | BA5: Improving the flight physics of the SACLOS/MCLOS missiles | BB5: 44532 | BC5: =CHOOSE(WEEKDAY(BB5,2),"Monday","Tuesday","Wednesday","Thursday","Friday","Saturday","Sunday") -> Thursday | BD5: VCC-80 Dardo (HITFIST 30) | BE5: 44482 | BF5: =CHOOSE(WEEKDAY(BE5,2),"Monday","Tuesday","Wednesday","Thursday","Friday","Saturday","Sunday") -> Wednesday | BG5: Reports concerning the protection of post-war combat vehicles | BH5: 44431 | BI5: =CHOOSE(WEEKDAY(BH5,2),"Monday","Tuesday","Wednesday","Thursday","Friday","Saturday","Sunday") -> Monday | BJ5: New effects for the nuclear blast | BK5: 44333 | BL5: =CHOOSE(WEEKDAY(BK5,2),"Monday","Tuesday","Wednesday","Thursday","Friday","Saturday","Sunday") -> Monday | BM5: M3A3 CFV | BN5: 44245 | BO5: =CHOOSE(WEEKDAY(BN5,2),"Monday","Tuesday","Wednesday","Thursday","Friday","Saturday","Sunday") -> Thursday | BP5: Blackburn Buccaneer S. Mk. 2 | BQ5: 44175 | BR5: =CHOOSE(WEEKDAY(BQ5,2),"Monday","Tuesday","Wednesday","Thursday","Friday","Saturday","Sunday") -> Thursday | BS5: Dagor 6.0: new skies | BT5: 44131 | BU5: =CHOOSE(WEEKDAY(BT5,2),"Monday","Tuesday","Wednesday","Thursday","Friday","Saturday","Sunday") -> Tuesday | BV5: Nánchāng Q5 | BW5: 44062 | BX5: =CHOOSE(WEEKDAY(BW5,2),"Monday","Tuesday","Wednesday","Thursday","Friday","Saturday","Sunday") -> Wednesday | BY5: HSTV(L) | BZ5: 43959 | CA5: =CHOOSE(WEEKDAY(BZ5,2),"Monday","Tuesday","Wednesday","Thursday","Friday","Saturday","Sunday") -> Friday | CB5: Lago I | CC5: 43886 | CD5: =CHOOSE(WEEKDAY(CC5,2),"Monday","Tuesday","Wednesday","Thursday","Friday","Saturday","Sunday") -> Tuesday | CE5: New Zealand cape | CF5: 43801 | CG5: =CHOOSE(WEEKDAY(CF5,2),"Monday","Tuesday","Wednesday","Thursday","Friday","Saturday","Sunday") -> Monday | CH5: Bréguet Br.693AB2 | CI5: 43755 | CJ5: =CHOOSE(WEEKDAY(CI5,2),"Monday","Tuesday","Wednesday","Thursday","Friday","Saturday","Sunday") -> Thursday | CK5: Map filter | CL5: 43697 | CM5: =CHOOSE(WEEKDAY(CL5,2),"Monday","Tuesday","Wednesday","Thursday","Friday","Saturday","Sunday") -> Tuesday | CN5: M2 (ADATS) | CO5: 43592 | CP5: =CHOOSE(WEEKDAY(CO5,2),"Monday","Tuesday","Wednesday","Thursday","Friday","Saturday","Sunday") -> Tuesday | CQ5: Somers (DD-381) | CR5: 43516 | CS5: =CHOOSE(WEEKDAY(CR5,2),"Monday","Tuesday","Wednesday","Thursday","Friday","Saturday","Sunday") -> Wednesday | CT5: M14/41 | CU5: 43433 | CV5: =CHOOSE(WEEKDAY(CU5,2),"Monday","Tuesday","Wednesday","Thursday","Friday","Saturday","Sunday") -> Thursday | CW5: Haida (G 63) | CX5: 43385 | CY5: =CHOOSE(WEEKDAY(CX5,2),"Monday","Tuesday","Wednesday","Thursday","Friday","Saturday","Sunday") -> Friday | CZ5: TAM & M247 | DA5: 43334 | DB5: =CHOOSE(WEEKDAY(DA5,2),"Monday","Tuesday","Wednesday","Thursday","Friday","Saturday","Sunday") -> Wednesday | DC5: Curtiss P-40F-10-CU | DD5: 43238 | DE5: =CHOOSE(WEEKDAY(DD5,2),"Monday","Tuesday","Wednesday","Thursday","Friday","Saturday","Sunday") -> Friday | DF5: Dagor 5.0: weather | DG5: 43145 | DH5: =CHOOSE(WEEKDAY(DG5,2),"Monday","Tuesday","Wednesday","Thursday","Friday","Saturday","Sunday") -> Wednesday | DI5: M4A1 (FL10) | DJ5: 43074 | DK5: =CHOOSE(WEEKDAY(DJ5,2),"Monday","Tuesday","Wednesday","Thursday","Friday","Saturday","Sunday") -> Tuesday | DL5: Arsenal VG 33.C-1 | DM5: 43028 | DN5: =CHOOSE(WEEKDAY(DM5,2),"Monday","Tuesday","Wednesday","Thursday","Friday","Saturday","Sunday") -> Friday | DO5: ERA & Composite | DP5: 42970 | DQ5: =CHOOSE(WEEKDAY(DP5,2),"Monday","Tuesday","Wednesday","Thursday","Friday","Saturday","Sunday") -> Wednesday | DR5: CANT Z.1007 Alcione | DS5: 42866 | DT5: =CHOOSE(WEEKDAY(DS5,2),"Monday","Tuesday","Wednesday","Thursday","Friday","Saturday","Sunday") -> Thursday | DU5: Centurion Mk. 1 | DV5: 42782 | DW5: =CHOOSE(WEEKDAY(DV5,2),"Monday","Tuesday","Wednesday","Thursday","Friday","Saturday","Sunday") -> Thursday | DX5: STA-1 | DY5: 42692 | DZ5: =CHOOSE(WEEKDAY(DY5,2),"Monday","Tuesday","Wednesday","Thursday","Friday","Saturday","Sunday") -> Friday | EA5: Swingfire | EB5: 42621 | EC5: =CHOOSE(WEEKDAY(EB5,2),"Monday","Tuesday","Wednesday","Thursday","Friday","Saturday","Sunday") -> Thursday | ED5: M60A1 (AOS) | EE5: 42572 | EF5: =CHOOSE(WEEKDAY(EE5,2),"Monday","Tuesday","Wednesday","Thursday","Friday","Saturday","Sunday") -> Thursday | EG5: Add-on armour & decorations | EH5: 42457 | EI5: =CHOOSE(WEEKDAY(EH5,2),"Monday","Tuesday","Wednesday","Thursday","Friday","Saturday","Sunday") -> Monday | EJ5: T-44-100 | EK5: 46063 | EL5: =CHOOSE(WEEKDAY(EK5,2),"Monday","Tuesday","Wednesday","Thursday","Friday","Saturday","Sunday") -> Tuesday | EM5: Mitsubishi A7M2 Reppū | EN5: 42345 | EO5: =CHOOSE(WEEKDAY(EN5,2),"Monday","Tuesday","Wednesday","Thursday","Friday","Saturday","Sunday") -> Monday | EP5: War Thunder Sound Recordings: The Lancaster | EQ5: 42233 | ER5: =CHOOSE(WEEKDAY(EQ5,2),"Monday","Tuesday","Wednesday","Thursday","Friday","Saturday","Sunday") -> Monday | ES5: Enduring Confrontation | ET5: 42178 | EU5: =CHOOSE(WEEKDAY(ET5,2),"Monday","Tuesday","Wednesday","Thursday","Friday","Saturday","Sunday") -> Tuesday | EV5: M3 GMC & Mitsubishi Ki-21-I | EW5: 42114 | EX5: =CHOOSE(WEEKDAY(EW5,2),"Monday","Tuesday","Wednesday","Thursday","Friday","Saturday","Sunday") -> Monday | EY5: Cockpit lights & Junkers Ju 87 D-5 gunpods | EZ5: 42040 | FA5: =CHOOSE(WEEKDAY(EZ5,2),"Monday","Tuesday","Wednesday","Thursday","Friday","Saturday","Sunday") -> Thursday | FB5: M41A1 | FC5: 41944 | FD5: =CHOOSE(WEEKDAY(FC5,2),"Monday","Tuesday","Wednesday","Thursday","Friday","Saturday","Sunday") -> Saturday | FE5: Future of the German aviation in War Thunder | FF5: 41817 | FG5: =CHOOSE(WEEKDAY(FF5,2),"Monday","Tuesday","Wednesday","Thursday","Friday","Saturday","Sunday") -> Friday | FH5: Horten Ho 229 V3 | FI5: 41760 | FJ5: =CHOOSE(WEEKDAY(FI5,2),"Monday","Tuesday","Wednesday","Thursday","Friday","Saturday","Sunday") -> Thursday | FK5: Progression system (update) | FL5: 41740 | FM5: =CHOOSE(WEEKDAY(FL5,2),"Monday","Tuesday","Wednesday","Thursday","Friday","Saturday","Sunday") -> Friday | FN5: Mitsubishi A6M5b Model 52 Otsu Reisen | FO5: 41575 | FP5: =CHOOSE(WEEKDAY(FO5,2),"Monday","Tuesday","Wednesday","Thursday","Friday","Saturday","Sunday") -> Monday
A6: Tuesday: | B6: =COUNTIF(D2:FP45,"Tuesday") -> 199 | C6: =B6/SUM($B$5:$B$11) -> 0.18511628 | H6: Sukhoi Su-33 | I6: 45636 | J6: =CHOOSE(WEEKDAY(I6,2),"Monday","Tuesday","Wednesday","Thursday","Friday","Saturday","Sunday") -> Tuesday | K6: Object 140 | L6: 45587 | M6: =CHOOSE(WEEKDAY(L6,2),"Monday","Tuesday","Wednesday","Thursday","Friday","Saturday","Sunday") -> Tuesday | N6: AVIC CAC / PAC JF-17A (Block 1) | O6: 45534 | P6: =CHOOSE(WEEKDAY(O6,2),"Monday","Tuesday","Wednesday","Thursday","Friday","Saturday","Sunday") -> Friday | Q6: Sukhoi Su-27SM | R6: 45440 | S6: =CHOOSE(WEEKDAY(R6,2),"Monday","Tuesday","Wednesday","Thursday","Friday","Saturday","Sunday") -> Tuesday | T6: Hungarian aircraft | U6: 45351 | V6: =CHOOSE(WEEKDAY(U6,2),"Monday","Tuesday","Wednesday","Thursday","Friday","Saturday","Sunday") -> Thursday | W6: Challenger 3 (Technology Demonstrator) | X6: 45267 | Y6: =CHOOSE(WEEKDAY(X6,2),"Monday","Tuesday","Wednesday","Thursday","Friday","Saturday","Sunday") -> Thursday | Z6: M109 & M109A1 & M 109 G | AA6: 45222 | AB6: =CHOOSE(WEEKDAY(AA6,2),"Monday","Tuesday","Wednesday","Thursday","Friday","Saturday","Sunday") -> Monday | AC6: Texas (BB-35) | AD6: 45163 | AE6: =CHOOSE(WEEKDAY(AD6,2),"Monday","Tuesday","Wednesday","Thursday","Friday","Saturday","Sunday") -> Friday | AF6: Bravy | AG6: 45055 | AH6: =CHOOSE(WEEKDAY(AG6,2),"Monday","Tuesday","Wednesday","Thursday","Friday","Saturday","Sunday") -> Tuesday | AI6: Pyrenees & Ardennes (winter) & Maginot Line (winter) & Seversk-13 (winter) | AJ6: 44973 | AK6: =CHOOSE(WEEKDAY(AJ6,2),"Monday","Tuesday","Wednesday","Thursday","Friday","Saturday","Sunday") -> Thursday | AL6: SUB-I-2 (MK 20) | AM6: 44901 | AN6: =CHOOSE(WEEKDAY(AM6,2),"Monday","Tuesday","Wednesday","Thursday","Friday","Saturday","Sunday") -> Tuesday | AO6: Mitsubishi XT-2 (Conversion to Late-model) | AP6: 44852 | AQ6: =CHOOSE(WEEKDAY(AP6,2),"Monday","Tuesday","Wednesday","Thursday","Friday","Saturday","Sunday") -> Tuesday | AR6: AFT09 | AS6: 44797 | AT6: =CHOOSE(WEEKDAY(AS6,2),"Monday","Tuesday","Wednesday","Thursday","Friday","Saturday","Sunday") -> Wednesday | AU6: VBC Centauro PT 2 | AV6: 44705 | AW6: =CHOOSE(WEEKDAY(AV6,2),"Monday","Tuesday","Wednesday","Thursday","Friday","Saturday","Sunday") -> Tuesday | AX6: Dagor Engine 6.5: Zoom in... Enhance it! | AY6: 44630 | AZ6: =CHOOSE(WEEKDAY(AY6,2),"Monday","Tuesday","Wednesday","Thursday","Friday","Saturday","Sunday") -> Thursday | BA6: Israeli Air CBT | BB6: 44532 | BC6: =CHOOSE(WEEKDAY(BB6,2),"Monday","Tuesday","Wednesday","Thursday","Friday","Saturday","Sunday") -> Thursday | BD6: Marlborough | BE6: 44483 | BF6: =CHOOSE(WEEKDAY(BE6,2),"Monday","Tuesday","Wednesday","Thursday","Friday","Saturday","Sunday") -> Thursday | BG6: Vickers Mk. 3 | BH6: 44432 | BI6: =CHOOSE(WEEKDAY(BH6,2),"Monday","Tuesday","Wednesday","Thursday","Friday","Saturday","Sunday") -> Tuesday | BJ6: de Havilland Sea Vixen F.(A.W.) Mk. 2 | BK6: 44335 | BL6: =CHOOSE(WEEKDAY(BK6,2),"Monday","Tuesday","Wednesday","Thursday","Friday","Saturday","Sunday") -> Wednesday | BM6: Kaiser | BN6: 44245 | BO6: =CHOOSE(WEEKDAY(BN6,2),"Monday","Tuesday","Wednesday","Thursday","Friday","Saturday","Sunday") -> Thursday | BP6: STA-3 | BQ6: 44176 | BR6: =CHOOSE(WEEKDAY(BQ6,2),"Monday","Tuesday","Wednesday","Thursday","Friday","Saturday","Sunday") -> Friday | BS6: Mikoyan-Gurevich MiG-21bis | BT6: 44131 | BU6: =CHOOSE(WEEKDAY(BT6,2),"Monday","Tuesday","Wednesday","Thursday","Friday","Saturday","Sunday") -> Tuesday | BV6: Zara | BW6: 44063 | BX6: =CHOOSE(WEEKDAY(BW6,2),"Monday","Tuesday","Wednesday","Thursday","Friday","Saturday","Sunday") -> Thursday | BY6: British rockets | BZ6: 43962 | CA6: =CHOOSE(WEEKDAY(BZ6,2),"Monday","Tuesday","Wednesday","Thursday","Friday","Saturday","Sunday") -> Monday | CB6: Douglas A-4B Skyhawk | CC6: 43886 | CD6: =CHOOSE(WEEKDAY(CC6,2),"Monday","Tuesday","Wednesday","Thursday","Friday","Saturday","Sunday") -> Tuesday | CE6: Saab B 17A | CF6: 43802 | CG6: =CHOOSE(WEEKDAY(CF6,2),"Monday","Tuesday","Wednesday","Thursday","Friday","Saturday","Sunday") -> Tuesday | CH6: Mil Mi-28N Havoc | CI6: 43756 | CJ6: =CHOOSE(WEEKDAY(CI6,2),"Monday","Tuesday","Wednesday","Thursday","Friday","Saturday","Sunday") -> Friday | CK6: Atlanta (CL-51) | CL6: 43699 | CM6: =CHOOSE(WEEKDAY(CL6,2),"Monday","Tuesday","Wednesday","Thursday","Friday","Saturday","Sunday") -> Thursday | CN6: 9P149M | CO6: 43593 | CP6: =CHOOSE(WEEKDAY(CO6,2),"Monday","Tuesday","Wednesday","Thursday","Friday","Saturday","Sunday") -> Wednesday | CQ6: Mikoyan-Gurevich MiG-19S | CR6: 43517 | CS6: =CHOOSE(WEEKDAY(CR6,2),"Monday","Tuesday","Wednesday","Thursday","Friday","Saturday","Sunday") -> Thursday | CT6: Sho't Kal Dalet | CU6: 43434 | CV6: =CHOOSE(WEEKDAY(CU6,2),"Monday","Tuesday","Wednesday","Thursday","Friday","Saturday","Sunday") -> Friday | CW6: MBB BO 105 | CX6: 43388 | CY6: =CHOOSE(WEEKDAY(CX6,2),"Monday","Tuesday","Wednesday","Thursday","Friday","Saturday","Sunday") -> Monday | CZ6: AGM-12 Bullpup | DA6: 43339 | DB6: =CHOOSE(WEEKDAY(DA6,2),"Monday","Tuesday","Wednesday","Thursday","Friday","Saturday","Sunday") -> Monday | DC6: Centurion AVRE | DD6: 43242 | DE6: =CHOOSE(WEEKDAY(DD6,2),"Monday","Tuesday","Wednesday","Thursday","Friday","Saturday","Sunday") -> Tuesday | DF6: Lavochkin La-200 | DG6: 43145 | DH6: =CHOOSE(WEEKDAY(DG6,2),"Monday","Tuesday","Wednesday","Thursday","Friday","Saturday","Sunday") -> Wednesday | DI6: SAu 40 | DJ6: 43075 | DK6: =CHOOSE(WEEKDAY(DJ6,2),"Monday","Tuesday","Wednesday","Thursday","Friday","Saturday","Sunday") -> Wednesday | DL6: French cockpits | DM6: 43032 | DN6: =CHOOSE(WEEKDAY(DM6,2),"Monday","Tuesday","Wednesday","Thursday","Friday","Saturday","Sunday") -> Tuesday | DO6: KPz. 70 & MBT 70 | DP6: 42971 | DQ6: =CHOOSE(WEEKDAY(DP6,2),"Monday","Tuesday","Wednesday","Thursday","Friday","Saturday","Sunday") -> Thursday | DR6: T-55A | DS6: 42870 | DT6: =CHOOSE(WEEKDAY(DS6,2),"Monday","Tuesday","Wednesday","Thursday","Friday","Saturday","Sunday") -> Monday | DU6: Martin B-10B | DV6: 42783 | DW6: =CHOOSE(WEEKDAY(DV6,2),"Monday","Tuesday","Wednesday","Thursday","Friday","Saturday","Sunday") -> Friday | DX6: I-Gō Otsu | DY6: 42695 | DZ6: =CHOOSE(WEEKDAY(DY6,2),"Monday","Tuesday","Wednesday","Thursday","Friday","Saturday","Sunday") -> Monday | EA6: Leopard 1 A1 A1 | EB6: 42623 | EC6: =CHOOSE(WEEKDAY(EB6,2),"Monday","Tuesday","Wednesday","Thursday","Friday","Saturday","Sunday") -> Saturday | ED6: Kawasaki Ki-100-I | EE6: 42576 | EF6: =CHOOSE(WEEKDAY(EE6,2),"Monday","Tuesday","Wednesday","Thursday","Friday","Saturday","Sunday") -> Monday | EG6: KV-2 variants | EH6: 42487 | EI6: =CHOOSE(WEEKDAY(EH6,2),"Monday","Tuesday","Wednesday","Thursday","Friday","Saturday","Sunday") -> Wednesday | EJ6: Falcon | EK6: 42412 | EL6: =CHOOSE(WEEKDAY(EK6,2),"Monday","Tuesday","Wednesday","Thursday","Friday","Saturday","Sunday") -> Friday | EM6: A.C. Mk. IV | EN6: 42345 | EO6: =CHOOSE(WEEKDAY(EN6,2),"Monday","Tuesday","Wednesday","Thursday","Friday","Saturday","Sunday") -> Monday | EP6: BM-8-24 | EQ6: 42235 | ER6: =CHOOSE(WEEKDAY(EQ6,2),"Monday","Tuesday","Wednesday","Thursday","Friday","Saturday","Sunday") -> Wednesday | ES6: Orders | ET6: 42178 | EU6: =CHOOSE(WEEKDAY(ET6,2),"Monday","Tuesday","Wednesday","Thursday","Friday","Saturday","Sunday") -> Tuesday | EV6: Normandy | EW6: 42114 | EX6: =CHOOSE(WEEKDAY(EW6,2),"Monday","Tuesday","Wednesday","Thursday","Friday","Saturday","Sunday") -> Monday | EY6: Maus | EZ6: 42041 | FA6: =CHOOSE(WEEKDAY(EZ6,2),"Monday","Tuesday","Wednesday","Thursday","Friday","Saturday","Sunday") -> Friday | FB6: M103 | FC6: 41945 | FD6: =CHOOSE(WEEKDAY(FC6,2),"Monday","Tuesday","Wednesday","Thursday","Friday","Saturday","Sunday") -> Sunday | FE6: Future of the American aviation in War Thunder | FF6: 41821 | FG6: =CHOOSE(WEEKDAY(FF6,2),"Monday","Tuesday","Wednesday","Thursday","Friday","Saturday","Sunday") -> Tuesday | FH6: Supermarine Spitfire F. Mk. XIV | FI6: 41765 | FJ6: =CHOOSE(WEEKDAY(FI6,2),"Monday","Tuesday","Wednesday","Thursday","Friday","Saturday","Sunday") -> Tuesday | FK6: CDK | FL6: 41745 | FM6: =CHOOSE(WEEKDAY(FL6,2),"Monday","Tuesday","Wednesday","Thursday","Friday","Saturday","Sunday") -> Wednesday | FN6: Focke-Wulf Fw 190 D-9 | FO6: 41575 | FP6: =CHOOSE(WEEKDAY(FO6,2),"Monday","Tuesday","Wednesday","Thursday","Friday","Saturday","Sunday") -> Monday
A7: Wednesday: | B7: =COUNTIF(D2:FP45,"Wednesday") -> 207 | C7: =B7/SUM($B$5:$B$11) -> 0.19255814 | H7: M44 & M44A1 | I7: 45637 | J7: =CHOOSE(WEEKDAY(I7,2),"Monday","Tuesday","Wednesday","Thursday","Friday","Saturday","Sunday") -> Wednesday | K7: Panavia Tornado G.R. Mk. 4 | L7: 45589 | M7: =CHOOSE(WEEKDAY(L7,2),"Monday","Tuesday","Wednesday","Thursday","Friday","Saturday","Sunday") -> Thursday | N7: FFA P-16 Mk. III | O7: 45534 | P7: =CHOOSE(WEEKDAY(O7,2),"Monday","Tuesday","Wednesday","Thursday","Friday","Saturday","Sunday") -> Friday | Q7: Bernau (343) | R7: 45441 | S7: =CHOOSE(WEEKDAY(R7,2),"Monday","Tuesday","Wednesday","Thursday","Friday","Saturday","Sunday") -> Wednesday | T7: Northrop-Grumman F-20A Tigershark | U7: 45352 | V7: =CHOOSE(WEEKDAY(U7,2),"Monday","Tuesday","Wednesday","Thursday","Friday","Saturday","Sunday") -> Friday | W7: T-90M | X7: 45267 | Y7: =CHOOSE(WEEKDAY(X7,2),"Monday","Tuesday","Wednesday","Thursday","Friday","Saturday","Sunday") -> Thursday | Z7: Flanders | AA7: 45223 | AB7: =CHOOSE(WEEKDAY(AA7,2),"Monday","Tuesday","Wednesday","Thursday","Friday","Saturday","Sunday") -> Tuesday | AC7: AMX 10 M | AD7: 45166 | AE7: =CHOOSE(WEEKDAY(AD7,2),"Monday","Tuesday","Wednesday","Thursday","Friday","Saturday","Sunday") -> Monday | AF7: Iberian Castle | AG7: 45057 | AH7: =CHOOSE(WEEKDAY(AG7,2),"Monday","Tuesday","Wednesday","Thursday","Friday","Saturday","Sunday") -> Thursday | AI7: Type 16 MCV (15th RDR) | AJ7: 44974 | AK7: =CHOOSE(WEEKDAY(AJ7,2),"Monday","Tuesday","Wednesday","Thursday","Friday","Saturday","Sunday") -> Friday | AL7: Mikoyan-Gurevich MiG-21bis (Lazur) & Lockheed F-104S/CB (TUR) & Israel Aircraft Industries Kfir Gderot | AM7: 44903 | AN7: =CHOOSE(WEEKDAY(AM7,2),"Monday","Tuesday","Wednesday","Thursday","Friday","Saturday","Sunday") -> Thursday | AO7: Zachlam (TCM-20) | AP7: 44853 | AQ7: =CHOOSE(WEEKDAY(AP7,2),"Monday","Tuesday","Wednesday","Thursday","Friday","Saturday","Sunday") -> Wednesday | AR7: VRCC Centauro | AS7: 44798 | AT7: =CHOOSE(WEEKDAY(AS7,2),"Monday","Tuesday","Wednesday","Thursday","Friday","Saturday","Sunday") -> Thursday | AU7: Bayern | AV7: 44706 | AW7: =CHOOSE(WEEKDAY(AV7,2),"Monday","Tuesday","Wednesday","Thursday","Friday","Saturday","Sunday") -> Wednesday | AX7: Sun City | AY7: 44630 | AZ7: =CHOOSE(WEEKDAY(AY7,2),"Monday","Tuesday","Wednesday","Thursday","Friday","Saturday","Sunday") -> Thursday | BA7: Type 10 | BB7: 44533 | BC7: =CHOOSE(WEEKDAY(BB7,2),"Monday","Tuesday","Wednesday","Thursday","Friday","Saturday","Sunday") -> Friday | BD7: Wiesel (x3) | BE7: 44484 | BF7: =CHOOSE(WEEKDAY(BE7,2),"Monday","Tuesday","Wednesday","Thursday","Friday","Saturday","Sunday") -> Friday | BG7: 2S25 | BH7: 44433 | BI7: =CHOOSE(WEEKDAY(BH7,2),"Monday","Tuesday","Wednesday","Thursday","Friday","Saturday","Sunday") -> Wednesday | BJ7: PGZ04A | BK7: 44336 | BL7: =CHOOSE(WEEKDAY(BK7,2),"Monday","Tuesday","Wednesday","Thursday","Friday","Saturday","Sunday") -> Thursday | BM7: Olifant Mk. 1A | BN7: 44246 | BO7: =CHOOSE(WEEKDAY(BN7,2),"Monday","Tuesday","Wednesday","Thursday","Friday","Saturday","Sunday") -> Friday | BP7: Visual effects for ground vehicles | BQ7: 44177 | BR7: =CHOOSE(WEEKDAY(BQ7,2),"Monday","Tuesday","Wednesday","Thursday","Friday","Saturday","Sunday") -> Saturday | BS7: Dagor 6.0: visual effects | BT7: 44132 | BU7: =CHOOSE(WEEKDAY(BT7,2),"Monday","Tuesday","Wednesday","Thursday","Friday","Saturday","Sunday") -> Wednesday | BV7: Long 12cm SPG | BW7: 44068 | BX7: =CHOOSE(WEEKDAY(BW7,2),"Monday","Tuesday","Wednesday","Thursday","Friday","Saturday","Sunday") -> Tuesday | BY7: Trento | BZ7: 43963 | CA7: =CHOOSE(WEEKDAY(BZ7,2),"Monday","Tuesday","Wednesday","Thursday","Friday","Saturday","Sunday") -> Tuesday | CB7: ikv 103 | CC7: 43887 | CD7: =CHOOSE(WEEKDAY(CC7,2),"Monday","Tuesday","Wednesday","Thursday","Friday","Saturday","Sunday") -> Wednesday | CE7: Prinz Eugen | CF7: 43803 | CG7: =CHOOSE(WEEKDAY(CF7,2),"Monday","Tuesday","Wednesday","Thursday","Friday","Saturday","Sunday") -> Wednesday | CH7: Vickers Mk. 7 | CI7: 43759 | CJ7: =CHOOSE(WEEKDAY(CI7,2),"Monday","Tuesday","Wednesday","Thursday","Friday","Saturday","Sunday") -> Monday | CK7: Object 685 | CL7: 43699 | CM7: =CHOOSE(WEEKDAY(CL7,2),"Monday","Tuesday","Wednesday","Thursday","Friday","Saturday","Sunday") -> Thursday | CN7: Fiat F-86K (FR) | CO7: 43595 | CP7: =CHOOSE(WEEKDAY(CO7,2),"Monday","Tuesday","Wednesday","Thursday","Friday","Saturday","Sunday") -> Friday | CQ7: Brooklyn (CL-40) | CR7: 43518 | CS7: =CHOOSE(WEEKDAY(CR7,2),"Monday","Tuesday","Wednesday","Thursday","Friday","Saturday","Sunday") -> Friday | CT7: Challenger 1 Mk. 3 | CU7: 43435 | CV7: =CHOOSE(WEEKDAY(CU7,2),"Monday","Tuesday","Wednesday","Thursday","Friday","Saturday","Sunday") -> Saturday | CW7: Aérospatiale SA.313B | CX7: 43389 | CY7: =CHOOSE(WEEKDAY(CX7,2),"Monday","Tuesday","Wednesday","Thursday","Friday","Saturday","Sunday") -> Tuesday | CZ7: Leopard 1 A1 A1 (Rh120-44) | DA7: 43340 | DB7: =CHOOSE(WEEKDAY(DA7,2),"Monday","Tuesday","Wednesday","Thursday","Friday","Saturday","Sunday") -> Tuesday | DC7: Italy | DD7: 43243 | DE7: =CHOOSE(WEEKDAY(DD7,2),"Monday","Tuesday","Wednesday","Thursday","Friday","Saturday","Sunday") -> Wednesday | DF7: Challenger 1 Mk. 2 | DG7: 43146 | DH7: =CHOOSE(WEEKDAY(DG7,2),"Monday","Tuesday","Wednesday","Thursday","Friday","Saturday","Sunday") -> Thursday | DI7: S 35 | DJ7: 43076 | DK7: =CHOOSE(WEEKDAY(DJ7,2),"Monday","Tuesday","Wednesday","Thursday","Friday","Saturday","Sunday") -> Thursday | DL7: Farman F.222.2 | DM7: 43033 | DN7: =CHOOSE(WEEKDAY(DM7,2),"Monday","Tuesday","Wednesday","Thursday","Friday","Saturday","Sunday") -> Wednesday | DO7: Fulda Gap | DP7: 42971 | DQ7: =CHOOSE(WEEKDAY(DP7,2),"Monday","Tuesday","Wednesday","Thursday","Friday","Saturday","Sunday") -> Thursday | DR7: Fiat G.91 pre-serie | DS7: 42870 | DT7: =CHOOSE(WEEKDAY(DS7,2),"Monday","Tuesday","Wednesday","Thursday","Friday","Saturday","Sunday") -> Monday | DU7: Ru 251 | DV7: 42784 | DW7: =CHOOSE(WEEKDAY(DV7,2),"Monday","Tuesday","Wednesday","Thursday","Friday","Saturday","Sunday") -> Saturday | DX7: Chi-He | DY7: 42697 | DZ7: =CHOOSE(WEEKDAY(DY7,2),"Monday","Tuesday","Wednesday","Thursday","Friday","Saturday","Sunday") -> Wednesday | EA7: Grumman F-9J Cougar | EB7: 42625 | EC7: =CHOOSE(WEEKDAY(EB7,2),"Monday","Tuesday","Wednesday","Thursday","Friday","Saturday","Sunday") -> Monday | ED7: T-62 | EE7: 42576 | EF7: =CHOOSE(WEEKDAY(EE7,2),"Monday","Tuesday","Wednesday","Thursday","Friday","Saturday","Sunday") -> Monday | EG7: Oculus Rift | EH7: 42495 | EI7: =CHOOSE(WEEKDAY(EH7,2),"Monday","Tuesday","Wednesday","Thursday","Friday","Saturday","Sunday") -> Thursday | EJ7: Focke-Wulf Fw 189 A-1 Uhu | EK7: 42416 | EL7: =CHOOSE(WEEKDAY(EK7,2),"Monday","Tuesday","Wednesday","Thursday","Friday","Saturday","Sunday") -> Tuesday | EM7: Centurion Mk. 3 & Conqueror | EN7: 42346 | EO7: =CHOOSE(WEEKDAY(EN7,2),"Monday","Tuesday","Wednesday","Thursday","Friday","Saturday","Sunday") -> Tuesday | EP7: War Thunder Sound Recordings: The Tiger II | EQ7: 42236 | ER7: =CHOOSE(WEEKDAY(EQ7,2),"Monday","Tuesday","Wednesday","Thursday","Friday","Saturday","Sunday") -> Thursday | ES7: Blackburn Firebrand T.F. Mk. IV | ET7: 42179 | EU7: =CHOOSE(WEEKDAY(ET7,2),"Monday","Tuesday","Wednesday","Thursday","Friday","Saturday","Sunday") -> Wednesday | EV7: Arado Ar 234 C-3 | EW7: 42115 | EX7: =CHOOSE(WEEKDAY(EW7,2),"Monday","Tuesday","Wednesday","Thursday","Friday","Saturday","Sunday") -> Tuesday | EY7: Enhanced vehicle to surface interaction | EZ7: 42042 | FA7: =CHOOSE(WEEKDAY(EZ7,2),"Monday","Tuesday","Wednesday","Thursday","Friday","Saturday","Sunday") -> Saturday | FB7: M24 | FC7: 41967 | FD7: =CHOOSE(WEEKDAY(FC7,2),"Monday","Tuesday","Wednesday","Thursday","Friday","Saturday","Sunday") -> Monday | FE7: T-54-1 | FF7: 41827 | FG7: =CHOOSE(WEEKDAY(FF7,2),"Monday","Tuesday","Wednesday","Thursday","Friday","Saturday","Sunday") -> Monday | FH7: Multi Turreted Control | FI7: 41766 | FJ7: =CHOOSE(WEEKDAY(FI7,2),"Monday","Tuesday","Wednesday","Thursday","Friday","Saturday","Sunday") -> Wednesday | FN7: Lavochkin La-9 | FO7: 41575 | FP7: =CHOOSE(WEEKDAY(FO7,2),"Monday","Tuesday","Wednesday","Thursday","Friday","Saturday","Sunday") -> Monday
